Rtype_and_or/src/control.sv
module control (
    // IN
    input logic [6:0] op,
    input logic [2:0] func3,
    input logic [6:0] func7,
    input logic alu_zero,

    // OUT
    output logic [2:0] alu_control,
    output logic [1:0] imm_source,
    output logic mem_write,
    output logic reg_write,
    output logic alu_source,
    output logic write_back_source
);

/**
* MAIN DECODER
*/

logic [1:0] alu_op;

always_comb begin
    case (op)
        // I-type
        7'b0000011 : begin
            reg_write = 1'b1;
            imm_source = 2'b00;
            mem_write = 1'b0;
            alu_op = 2'b00;
            alu_source = 1'b1; //imm
            write_back_source = 1'b1; //memory_read
        end
        // S-Type
        7'b0100011 : begin
            reg_write = 1'b0;
            imm_source = 2'b01;
            mem_write = 1'b1;
            alu_op = 2'b00;
            alu_source = 1'b1; //imm
        end
        // R-Type
        7'b0110011 : begin
            reg_write = 1'b1;
            mem_write = 1'b0;
            alu_op = 2'b10;
            alu_source = 1'b0; //reg2
            write_back_source = 1'b0; //alu_result
        end
        // EVERYTHING ELSE
        default: begin
            reg_write = 1'b0;
            imm_source = 2'b00;
            mem_write = 1'b0;
            alu_op = 2'b00;
        end
    endcase
end

/**
* ALU DECODER
*/

always_comb begin
    case (alu_op)
        // LW, SW
        2'b00 : alu_control = 3'b000;
        // R-Types
        2'b10 : begin
            case (func3)
                // ADD (and later SUB with a different F7)
                3'b000 : alu_control = 3'b000;
		        // AND
		        3'b111 : alu_control = 3'b010; 
		        //OR
		        3'b110 : alu_control = 3'b011;
                // ALL THE OTHERS
                default: alu_control = 3'b111;
            endcase
        end
        default: alu_control = 3'b111;
    endcase
end
    
endmodule

Rtype_and_or/tb/controlLogic/dump.vcd
$version Generated by VerilatedVcd $end
$timescale 1ps $end
 $scope module $rootio $end
  $var wire 7 # op [6:0] $end
  $var wire 3 $ func3 [2:0] $end
  $var wire 7 % func7 [6:0] $end
  $var wire 1 & alu_zero $end
  $var wire 3 ' alu_control [2:0] $end
  $var wire 2 ( imm_source [1:0] $end
  $var wire 1 ) mem_write $end
  $var wire 1 * reg_write $end
  $var wire 1 + alu_source $end
  $var wire 1 , write_back_source $end
 $upscope $end
 $scope module control $end
  $var wire 7 - op [6:0] $end
  $var wire 3 . func3 [2:0] $end
  $var wire 7 / func7 [6:0] $end
  $var wire 1 0 alu_zero $end
  $var wire 3 1 alu_control [2:0] $end
  $var wire 2 2 imm_source [1:0] $end
  $var wire 1 3 mem_write $end
  $var wire 1 4 reg_write $end
  $var wire 1 5 alu_source $end
  $var wire 1 6 write_back_source $end
  $var wire 2 7 alu_op [1:0] $end
 $upscope $end
$enddefinitions $end


#0
b0000000 #
b000 $
b0000000 %
0&
b000 '
b00 (
0)
0*
0+
0,
b0000000 -
b000 .
b0000000 /
00
b000 1
b00 2
03
04
05
06
b00 7
#1000
b0000011 #
1*
1+
1,
b0000011 -
14
15
16
#12001
b0100011 #
b01 (
1)
0*
b0100011 -
b01 2
13
04
#23002
b0110011 #
0)
1*
0+
0,
b0110011 -
03
14
05
06
b10 7
#25003
b0000000 #
b00 (
0*
b0000000 -
b00 2
04
b00 7
#36003
b0110011 #
b111 $
b010 '
1*
b0110011 -
b111 .
b010 1
14
b10 7
#38004
b0000000 #
b000 $
b000 '
0*
b0000000 -
b000 .
b000 1
04
b00 7
#49004
b0110011 #
b110 $
b011 '
1*
b0110011 -
b110 .
b011 1
14
b10 7
