otherItype/src/control.sv
`timescale 1ns/1ps


module control (
    // IN
    input logic [6:0] op,
    input logic [2:0] func3,
    input logic [6:0] func7,
    input logic alu_zero,

    // OUT
    output logic [3:0] alu_control,
    output logic [2:0] imm_source,
    output logic mem_write,
    output logic reg_write,
    output logic alu_source,
    output logic [1:0] write_back_source,
    output logic pc_source,
    output logic second_add_source
);

/**
* MAIN DECODER
*/

logic [1:0] alu_op;
logic branch;
logic jump;

always_comb begin
    reg_write         = 1'b0; // Required to aviod latchup warnings
    imm_source        = 3'b000;// varaibales assinged in one case and not assigned in anaother case, get treated as memory/reg
    mem_write         = 1'b0;  // for example varaible set in I type, but not in B type, carry the same assignment in  Btype
    alu_op            = 2'b00; // simulator sees this as an latch (its a latch by defination)
    alu_source        = 1'b0; // So we assign a initial value to all the varaibles, see EOF for explanation
    write_back_source = 2'b00;
    branch            = 1'b0;
    jump              = 1'b0;
    second_add_source = 1'b0;
    case (op)
        // I-type (LW)
        7'b0000011 : begin
            reg_write = 1'b1;
            imm_source = 3'b000;
            mem_write = 1'b0;
            alu_op = 2'b00;
            alu_source = 1'b1; //imm
            write_back_source = 2'b01; //memory_read
	        branch = 1'b0;
	        jump = 1'b0;
        end
        // ALU I Type
        7'b0010011 : begin
            reg_write = 1'b1;
            imm_source = 3'b000;
            alu_source = 1'b1; //imm
            mem_write = 1'b0;
            alu_op = 2'b10;
            write_back_source = 2'b00; //alu_result
            branch = 1'b0;
            jump = 1'b0;
         end
        // S-Type
        7'b0100011 : begin
            reg_write = 1'b0;
            imm_source = 3'b001;
            mem_write = 1'b1;
            alu_op = 2'b00;
            alu_source = 1'b1; //imm
	        branch = 1'b0;
	        jump = 1'b0;
        end
        // R-Type
        7'b0110011 : begin
            reg_write = 1'b1;
            mem_write = 1'b0;
            alu_op = 2'b10;
            alu_source = 1'b0; //reg2
            write_back_source = 2'b00; //alu_result
	        branch = 1'b0;
	        jump = 1'b0;
        end
	   // B-Type
	   7'b1100011 : begin
            reg_write = 1'b0;
            imm_source = 3'b010;
            alu_source = 1'b0;
            mem_write = 1'b0;
            alu_op = 2'b01;
            branch = 1'b1;
	        jump = 1'b0;
        end
        // J-Type
        7'b1101111 : begin
            reg_write = 1'b1;
            imm_source = 3'b011;
            mem_write = 1'b0;
            write_back_source = 2'b10; 
            branch = 1'b0;
            jump = 1'b1;
        end
        // U-type
        7'b0110111, 7'b0010111 : begin
            imm_source = 3'b100;
            mem_write = 1'b0;
            reg_write = 1'b1;
            write_back_source = 2'b11;
            branch = 1'b0;
            jump = 1'b0;
            case(op[5])
                1'b1 : second_add_source = 1'b1; // lui
                1'b0 : second_add_source = 1'b0; // auipc
            endcase
        end
        // EVERYTHING ELSE
        default: begin
            reg_write = 1'b0;
            imm_source = 3'b000;
            mem_write = 1'b0;
            alu_op = 2'b00;
	        reg_write = 1'b0;
            mem_write = 1'b0;
	    jump = 1'b0;
        end
    endcase
end

/**
* ALU DECODER
*/

always_comb begin
    case (alu_op)
        // LW, SW
        2'b00 : alu_control = 4'b0000;
        // R-Types
        2'b10 : begin
            case (func3)
                // ADD (and later SUB with a different F7)
                3'b000 : alu_control = 4'b0000;
                // AND
                3'b111 : alu_control = 4'b0010;
                // OR
                3'b110 : alu_control = 4'b0011;
                // SLTI
                3'b010 : alu_control = 4'b0101;
                // SLTIU
                3'b011 : alu_control = 4'b0111;
                // XOR
                3'b100 : alu_control = 4'b1000;
                default: alu_control = 4'b0000;
            endcase
        end
        // BEQ, SUB
        2'b01 : alu_control = 4'b0001;
        default: alu_control = 4'b0000;
    endcase
end

//logic assert_branch;
//
//always_comb begin : branch_logic_decode
//    case (func3)
//        // BEQ
//        3'b000 : assert_branch = alu_zero & branch;
//        // BLT, BLTU
//        F3_BLT, F3_BLTU : assert_branch = alu_last_bit & branch;
//        // BNE
//        F3_BNE : assert_branch = ~alu_zero & branch;
//        // BGE, BGEU
//        F3_BGE, F3_BGEU : assert_branch = ~alu_last_bit & branch;
//        default : assert_branch = 1'b0;
//    endcase
//end
//
//assign pc_source = (assert_branch & (op == 7'b1100011)) | jump;
    
assign pc_source = (alu_zero & branch) | jump;


endmodule

///// EXPLANATION BELOW///////////////////

//1. How is a Latch formed?In Verilog, an always_comb block is a set of instructions for building combinational gates (AND, OR, NOT).If you write a case statement but don't cover a specific signal in a specific branch, you are effectively telling the hardware:"If the Opcode is BEQ, change the branch signal to 1. If the Opcode is LW, I'm not going to mention the branch signal at all."The hardware logic then asks: "If it's LW, what should I do with the branch wire? Should it be 0? Should it be 1?"Because you didn't give an instruction for the LW case, the hardware assumes you want the signal to stay exactly what it was before. To "stay what it was," the hardware must create a physical loop or a storage element to remember the old state. That storage element is a Latch.
//
//2. Why Latches are Bad for CPUsIn a CPU, you want your control signals to be "clean."If you run a BEQ instruction, branch becomes 1.If the next instruction is a LW, and you didn't explicitly set branch to 0, the Latch will keep branch at 1.The Result: Your LW instruction will accidentally try to branch!
//
//3. How Default Values Solve the LatchWhen you assign values at the very beginning of the always_comb block, you are creating a "Default Path" for every single wire.Think of it like a waterfall of logic:Verilogalways_comb begin
//    branch = 1'b0; // <--- This is the "Floor". Every signal starts here.
//
//    case (op)
//        7'b1100011: begin // BEQ
//            branch = 1'b1; // This "overwrites" the 0.
//        end
//        7'b0000011: begin // LW
//            // We don't mention 'branch' here.
//            // Since we set it to 0 at the top, it STAYS 0.
//        end
//    endcase
//end
//By setting the value at the top, you have covered every possible path. Even if your case statement doesn't mention a signal, the signal already has a value (the default).The hardware result: Instead of a Latch (storage), the compiler builds a simple piece of combinational logic that defaults to 0 unless the specific BEQ condition is met.Summary Table: Latch vs. CombinationalScenarioLogic InterpretationHardware ResultNo Default + Missing Case"Keep the old value if not specified."Latch (Memory element)With Default + Missing Case"Use the default value if not specified."Gates (Pure logic)
//
//Pro-Tip for Verilator is extra strict. It checks every single logic variable inside an always_comb. If there is even a $0.00001\%$ chance a signal doesn't get assigned a value, it will throw that Warning-LATCH. Using the "Default at Top" method is the industry-standard way to keep your code clean and your warnings at zero.

otherItype/tb/controlLogic/dump.vcd
$version Generated by VerilatedVcd $end
$timescale 1ps $end
 $scope module $rootio $end
  $var wire 7 # op [6:0] $end
  $var wire 3 $ func3 [2:0] $end
  $var wire 7 % func7 [6:0] $end
  $var wire 1 & alu_zero $end
  $var wire 4 ' alu_control [3:0] $end
  $var wire 3 ( imm_source [2:0] $end
  $var wire 1 ) mem_write $end
  $var wire 1 * reg_write $end
  $var wire 1 + alu_source $end
  $var wire 2 , write_back_source [1:0] $end
  $var wire 1 - pc_source $end
  $var wire 1 . second_add_source $end
 $upscope $end
 $scope module control $end
  $var wire 7 / op [6:0] $end
  $var wire 3 0 func3 [2:0] $end
  $var wire 7 1 func7 [6:0] $end
  $var wire 1 2 alu_zero $end
  $var wire 4 3 alu_control [3:0] $end
  $var wire 3 4 imm_source [2:0] $end
  $var wire 1 5 mem_write $end
  $var wire 1 6 reg_write $end
  $var wire 1 7 alu_source $end
  $var wire 2 8 write_back_source [1:0] $end
  $var wire 1 9 pc_source $end
  $var wire 1 : second_add_source $end
  $var wire 2 ; alu_op [1:0] $end
  $var wire 1 < branch $end
  $var wire 1 = jump $end
 $upscope $end
$enddefinitions $end


#0
b0000000 #
b000 $
b0000000 %
0&
b0000 '
b000 (
0)
0*
0+
b00 ,
0-
0.
b0000000 /
b000 0
b0000000 1
02
b0000 3
b000 4
05
06
07
b00 8
09
0:
b00 ;
0<
0=
#1000
b0000011 #
1*
1+
b01 ,
b0000011 /
16
17
b01 8
#12001
b0100011 #
b001 (
1)
0*
b00 ,
b0100011 /
b001 4
15
06
b00 8
#23002
b0110011 #
b000 (
0)
1*
0+
b0110011 /
b000 4
05
16
07
b10 ;
#25003
b0000000 #
0*
b0000000 /
06
b00 ;
#36003
b0110011 #
b111 $
b0010 '
1*
b0110011 /
b111 0
b0010 3
16
b10 ;
#38004
b0000000 #
b000 $
b0000 '
0*
b0000000 /
b000 0
b0000 3
06
b00 ;
#49004
b0110011 #
b110 $
b0011 '
1*
b0110011 /
b110 0
b0011 3
16
b10 ;
#51005
b0000000 #
b000 $
b0000 '
0*
b0000000 /
b000 0
b0000 3
06
b00 ;
#62005
b1100011 #
b0001 '
b010 (
b1100011 /
b0001 3
b010 4
b01 ;
1<
#66005
1&
1-
12
19
#68006
b0000000 #
b0000 '
b000 (
0-
b0000000 /
b0000 3
b000 4
09
b00 ;
0<
#79006
b1101111 #
b011 (
1*
b10 ,
1-
b1101111 /
b011 4
16
b10 8
19
1=
#81007
b0000000 #
b000 (
0*
b00 ,
0-
b0000000 /
b000 4
06
b00 8
09
0=
#92007
b0010011 #
1*
1+
b0010011 /
16
17
b10 ;
#94008
b0000000 #
0*
0+
b0000000 /
06
07
b00 ;
#105008
b0010111 #
b100 (
1*
b11 ,
b0010111 /
b100 4
16
b11 8
#107009
b0000000 #
b000 (
0*
b00 ,
b0000000 /
b000 4
06
b00 8
#118009
b0010011 #
b010 $
b0101 '
1*
1+
b0010011 /
b010 0
b0101 3
16
17
b10 ;
#120010
b0000000 #
b000 $
b0000 '
0*
0+
b0000000 /
b000 0
b0000 3
06
07
b00 ;
#131010
b0010011 #
b011 $
b0111 '
1*
1+
b0010011 /
b011 0
b0111 3
16
17
b10 ;
#133011
b0000000 #
b000 $
b0000 '
0*
0+
b0000000 /
b000 0
b0000 3
06
07
b00 ;
#144011
b0010011 #
b100 $
b1000 '
1*
1+
b0010011 /
b100 0
b1000 3
16
17
b10 ;
