beq/src/signext.sv
// signext.sv

module signext (
    // IN
    input logic [24:0] raw_src,
    input logic [1:0] imm_source,

    // OUT (immediate)
    output logic [31:0] immediate
);

logic [11:0] gathered_imm;

always_comb begin
    case (imm_source)
        // For I-Types
        2'b00 : gathered_imm = raw_src[24:13];
        // For S-types
        2'b01 : gathered_imm = {raw_src[24:18],raw_src[4:0]};
	// For B-types
        2'b10 : gathered_imm = {raw_src[0],raw_src[23:18],raw_src[4:1],1'b0};
        default: gathered_imm = 12'b0;
    endcase
end

// assign immediate = {{20{gathered_imm[11]}}, gathered_imm};
assign immediate = (imm_source == 2'b10) ? 
                   {{20{raw_src[24]}}, gathered_imm} : 
                   {{20{gathered_imm[11]}}, gathered_imm};    
endmodule


// https://fraserinnovations.com/risc-v/risc-v-instruction-set-explanation/
// above link has the best explanations on each type of riscv instructions



// Instruction guide for b type
// Map of index

// raw_src       = [0, 1, 2, 3,  4,  5,  6,  7,  8,  9,  10, 11, 12, 13, 14, 15, 16, 17, 18, 19, 20, 21, 22, 23, 24]
// instruction   = [7, 8, 9, 10, 11, 12, 13, 14, 15, 16, 17, 18, 19, 20, 21, 22, 23, 24, 25, 26, 27, 28, 29, 30, 31]
// 


// Instruction[6:0] = opcode
// Instruction[7] = immediate[11]
// Instruction[11:8] = immediate[4:1]
// Instruction[12:14] = func3
// Instruction[15:19] = RS1
// Instruction[24:20] = RS2
// Instruction[30:25] = immediate[10:5]
// Instruction[31] = immediate[12]

// immediate represenst memory offset, so having immedite[0] = 0, is the only choice.
// The memory is multiples of 2, immediate[0] ensures that the number is always even and mutiple of 2

beq/tb/signExt/dump.vcd
$version Generated by VerilatedVcd $end
$timescale 1ps $end
 $scope module $rootio $end
  $var wire 25 # raw_src [24:0] $end
  $var wire 2 $ imm_source [1:0] $end
  $var wire 32 % immediate [31:0] $end
 $upscope $end
 $scope module signext $end
  $var wire 25 & raw_src [24:0] $end
  $var wire 2 ' imm_source [1:0] $end
  $var wire 32 ( immediate [31:0] $end
  $var wire 12 ) gathered_imm [11:0] $end
 $upscope $end
$enddefinitions $end


#0
b0000000000000000000000000 #
b00 $
b00000000000000000000000000000000 %
b0000000000000000000000000 &
b00 '
b00000000000000000000000000000000 (
b000000000000 )
#1000
b0000011110111010101010101 #
b00000000000000000000000001111011 %
b0000011110111010101010101 &
b00000000000000000000000001111011 (
b000001111011 )
#3000
b1111110101101010101010101 #
b11111111111111111111111111010110 %
b1111110101101010101010101 &
b11111111111111111111111111010110 (
b111111010110 )
#104001
b0011100000000000000001111 #
b01 $
b00000000000000000000001110001111 %
b0011100000000000000001111 &
b01 '
b00000000000000000000001110001111 (
b001110001111 )
#106001
b1010010000000000000011100 #
b11111111111111111111101001011100 %
b1010010000000000000011100 &
b11111111111111111111101001011100 (
b101001011100 )
#207001
b0011011000000000000000011 #
b00000000000000000000001101100011 %
b0011011000000000000000011 &
b00000000000000000000001101100011 (
b001101100011 )
#209001
b1100010000000000000000101 #
b11111111111111111111110001000101 %
b1100010000000000000000101 &
b11111111111111111111110001000101 (
b110001000101 )
#310001
b0000000000000000000010001 #
b00000000000000000000000000010001 %
b0000000000000000000010001 &
b00000000000000000000000000010001 (
b000000010001 )
#312001
b1110111000000000000010000 #
b11111111111111111111111011110000 %
b1110111000000000000010000 &
b11111111111111111111111011110000 (
b111011110000 )
#413001
b0001011000000000000010111 #
b00000000000000000000000101110111 %
b0001011000000000000010111 &
b00000000000000000000000101110111 (
b000101110111 )
#415001
b1011001000000000000010011 #
b11111111111111111111101100110011 %
b1011001000000000000010011 &
b11111111111111111111101100110011 (
b101100110011 )
#516001
b0011000000000000000010100 #
b00000000000000000000001100010100 %
b0011000000000000000010100 &
b00000000000000000000001100010100 (
b001100010100 )
#518001
b1001001000000000000011111 #
b11111111111111111111100100111111 %
b1001001000000000000011111 &
b11111111111111111111100100111111 (
b100100111111 )
#619001
b0011001000000000000001101 #
b00000000000000000000001100101101 %
b0011001000000000000001101 &
b00000000000000000000001100101101 (
b001100101101 )
#621001
b1011000000000000000001111 #
b11111111111111111111101100001111 %
b1011000000000000000001111 &
b11111111111111111111101100001111 (
b101100001111 )
#722001
b0001110000000000000001110 #
b00000000000000000000000111001110 %
b0001110000000000000001110 &
b00000000000000000000000111001110 (
b000111001110 )
#724001
b1101100000000000000010000 #
b11111111111111111111110110010000 %
b1101100000000000000010000 &
b11111111111111111111110110010000 (
b110110010000 )
#825001
b0010001000000000000011001 #
b00000000000000000000001000111001 %
b0010001000000000000011001 &
b00000000000000000000001000111001 (
b001000111001 )
#827001
b1011000000000000000001000 #
b11111111111111111111101100001000 %
b1011000000000000000001000 &
b11111111111111111111101100001000 (
b101100001000 )
#928001
b0011001000000000000001001 #
b00000000000000000000001100101001 %
b0011001000000000000001001 &
b00000000000000000000001100101001 (
b001100101001 )
#930001
b1111010000000000000011010 #
b11111111111111111111111101011010 %
b1111010000000000000011010 &
b11111111111111111111111101011010 (
b111101011010 )
#1031001
b0000110000000000000001000 #
b00000000000000000000000011001000 %
b0000110000000000000001000 &
b00000000000000000000000011001000 (
b000011001000 )
#1033001
b1010001000000000000011000 #
b11111111111111111111101000111000 %
b1010001000000000000011000 &
b11111111111111111111101000111000 (
b101000111000 )
#1134001
b0010011000000000000001111 #
b00000000000000000000001001101111 %
b0010011000000000000001111 &
b00000000000000000000001001101111 (
b001001101111 )
#1136001
b1011100000000000000010011 #
b11111111111111111111101110010011 %
b1011100000000000000010011 &
b11111111111111111111101110010011 (
b101110010011 )
#1237001
b0010100000000000000011100 #
b00000000000000000000001010011100 %
b0010100000000000000011100 &
b00000000000000000000001010011100 (
b001010011100 )
#1239001
b1111011000000000000011001 #
b11111111111111111111111101111001 %
b1111011000000000000011001 &
b11111111111111111111111101111001 (
b111101111001 )
#1340001
b0001110000000000000001100 #
b00000000000000000000000111001100 %
b0001110000000000000001100 &
b00000000000000000000000111001100 (
b000111001100 )
#1342001
b1111110000000000000010100 #
b11111111111111111111111111010100 %
b1111110000000000000010100 &
b11111111111111111111111111010100 (
b111111010100 )
#1443001
b0000110000000000000001010 #
b00000000000000000000000011001010 %
b0000110000000000000001010 &
b00000000000000000000000011001010 (
b000011001010 )
#1445001
b1101000000000000000001101 #
b11111111111111111111110100001101 %
b1101000000000000000001101 &
b11111111111111111111110100001101 (
b110100001101 )
#1546001
b0010001000000000000001001 #
b00000000000000000000001000101001 %
b0010001000000000000001001 &
b00000000000000000000001000101001 (
b001000101001 )
#1548001
b1111001000000000000001011 #
b11111111111111111111111100101011 %
b1111001000000000000001011 &
b11111111111111111111111100101011 (
b111100101011 )
#1649001
b0010101000000000000010110 #
b00000000000000000000001010110110 %
b0010101000000000000010110 &
b00000000000000000000001010110110 (
b001010110110 )
#1651001
b1000110000000000000011000 #
b11111111111111111111100011011000 %
b1000110000000000000011000 &
b11111111111111111111100011011000 (
b100011011000 )
#1752001
b0011011000000000000011001 #
b00000000000000000000001101111001 %
b0011011000000000000011001 &
b00000000000000000000001101111001 (
b001101111001 )
#1754001
b1010000000000000000010010 #
b11111111111111111111101000010010 %
b1010000000000000000010010 &
b11111111111111111111101000010010 (
b101000010010 )
#1855001
b0000101000000000000001101 #
b00000000000000000000000010101101 %
b0000101000000000000001101 &
b00000000000000000000000010101101 (
b000010101101 )
#1857001
b1010100000000000000011101 #
b11111111111111111111101010011101 %
b1010100000000000000011101 &
b11111111111111111111101010011101 (
b101010011101 )
#1958001
b0010011000000000000000101 #
b00000000000000000000001001100101 %
b0010011000000000000000101 &
b00000000000000000000001001100101 (
b001001100101 )
#1960001
b1100110000000000000010001 #
b11111111111111111111110011010001 %
b1100110000000000000010001 &
b11111111111111111111110011010001 (
b110011010001 )
#2061001
b0010001000000000000010010 #
b00000000000000000000001000110010 %
b0010001000000000000010010 &
b00000000000000000000001000110010 (
b001000110010 )
#2063001
b1101001000000000000000010 #
b11111111111111111111110100100010 %
b1101001000000000000000010 &
b11111111111111111111110100100010 (
b110100100010 )
#2164001
b0000101000000000000000010 #
b00000000000000000000000010100010 %
b0000101000000000000000010 &
b00000000000000000000000010100010 (
b000010100010 )
#2166001
b1111101000000000000001101 #
b11111111111111111111111110101101 %
b1111101000000000000001101 &
b11111111111111111111111110101101 (
b111110101101 )
#2267001
b0010011000000000000010000 #
b00000000000000000000001001110000 %
b0010011000000000000010000 &
b00000000000000000000001001110000 (
b001001110000 )
#2269001
b1000001000000000000011011 #
b11111111111111111111100000111011 %
b1000001000000000000011011 &
b11111111111111111111100000111011 (
b100000111011 )
#2370001
b0000111000000000000000010 #
b00000000000000000000000011100010 %
b0000111000000000000000010 &
b00000000000000000000000011100010 (
b000011100010 )
#2372001
b1110010000000000000000101 #
b11111111111111111111111001000101 %
b1110010000000000000000101 &
b11111111111111111111111001000101 (
b111001000101 )
#2473001
b0011010000000000000001111 #
b00000000000000000000001101001111 %
b0011010000000000000001111 &
b00000000000000000000001101001111 (
b001101001111 )
#2475001
b1101011000000000000010000 #
b11111111111111111111110101110000 %
b1101011000000000000010000 &
b11111111111111111111110101110000 (
b110101110000 )
#2576001
b0000011000000000000000011 #
b00000000000000000000000001100011 %
b0000011000000000000000011 &
b00000000000000000000000001100011 (
b000001100011 )
#2578001
b1000100000000000000001000 #
b11111111111111111111100010001000 %
b1000100000000000000001000 &
b11111111111111111111100010001000 (
b100010001000 )
#2679001
b0000001000000000000001011 #
b00000000000000000000000000101011 %
b0000001000000000000001011 &
b00000000000000000000000000101011 (
b000000101011 )
#2681001
b1110001000000000000000100 #
b11111111111111111111111000100100 %
b1110001000000000000000100 &
b11111111111111111111111000100100 (
b111000100100 )
#2782001
b0001110000000000000011010 #
b00000000000000000000000111011010 %
b0001110000000000000011010 &
b00000000000000000000000111011010 (
b000111011010 )
#2784001
b1111000000000000000001111 #
b11111111111111111111111100001111 %
b1111000000000000000001111 &
b11111111111111111111111100001111 (
b111100001111 )
#2885001
b0000110000000000000001110 #
b00000000000000000000000011001110 %
b0000110000000000000001110 &
b00000000000000000000000011001110 (
b000011001110 )
#2887001
b1010100000000000000001110 #
b11111111111111111111101010001110 %
b1010100000000000000001110 &
b11111111111111111111101010001110 (
b101010001110 )
#2988001
b0011111000000000000001100 #
b00000000000000000000001111101100 %
b0011111000000000000001100 &
b00000000000000000000001111101100 (
b001111101100 )
#2990001
b1101101000000000000001100 #
b11111111111111111111110110101100 %
b1101101000000000000001100 &
b11111111111111111111110110101100 (
b110110101100 )
#3091001
b0011111000000000000001111 #
b00000000000000000000001111101111 %
b0011111000000000000001111 &
b00000000000000000000001111101111 (
b001111101111 )
#3093001
b1001000000000000000011110 #
b11111111111111111111100100011110 %
b1001000000000000000011110 &
b11111111111111111111100100011110 (
b100100011110 )
#3194001
b0000010000000000000000101 #
b00000000000000000000000001000101 %
b0000010000000000000000101 &
b00000000000000000000000001000101 (
b000001000101 )
#3196001
b1111001000000000000011010 #
b11111111111111111111111100111010 %
b1111001000000000000011010 &
b11111111111111111111111100111010 (
b111100111010 )
#3297001
b0011111000000000000011110 #
b00000000000000000000001111111110 %
b0011111000000000000011110 &
b00000000000000000000001111111110 (
b001111111110 )
#3299001
b1010001000000000000010101 #
b11111111111111111111101000110101 %
b1010001000000000000010101 &
b11111111111111111111101000110101 (
b101000110101 )
#3400001
b0011111000000000000011110 #
b00000000000000000000001111111110 %
b0011111000000000000011110 &
b00000000000000000000001111111110 (
b001111111110 )
#3402001
b1101000000000000000000111 #
b11111111111111111111110100000111 %
b1101000000000000000000111 &
b11111111111111111111110100000111 (
b110100000111 )
#3503001
b0011000000000000000001101 #
b00000000000000000000001100001101 %
b0011000000000000000001101 &
b00000000000000000000001100001101 (
b001100001101 )
#3505001
b1010111000000000000001111 #
b11111111111111111111101011101111 %
b1010111000000000000001111 &
b11111111111111111111101011101111 (
b101011101111 )
#3606001
b0010101000000000000011110 #
b00000000000000000000001010111110 %
b0010101000000000000011110 &
b00000000000000000000001010111110 (
b001010111110 )
#3608001
b1000000000000000000000100 #
b11111111111111111111100000000100 %
b1000000000000000000000100 &
b11111111111111111111100000000100 (
b100000000100 )
#3709001
b0000011000000000000011110 #
b00000000000000000000000001111110 %
b0000011000000000000011110 &
b00000000000000000000000001111110 (
b000001111110 )
#3711001
b1000010000000000000011100 #
b11111111111111111111100001011100 %
b1000010000000000000011100 &
b11111111111111111111100001011100 (
b100001011100 )
#3812001
b0001001000000000000010010 #
b00000000000000000000000100110010 %
b0001001000000000000010010 &
b00000000000000000000000100110010 (
b000100110010 )
#3814001
b1110001000000000000001100 #
b11111111111111111111111000101100 %
b1110001000000000000001100 &
b11111111111111111111111000101100 (
b111000101100 )
#3915001
b0000100000000000000001000 #
b00000000000000000000000010001000 %
b0000100000000000000001000 &
b00000000000000000000000010001000 (
b000010001000 )
#3917001
b1100111000000000000001101 #
b11111111111111111111110011101101 %
b1100111000000000000001101 &
b11111111111111111111110011101101 (
b110011101101 )
#4018001
b0010111000000000000011110 #
b00000000000000000000001011111110 %
b0010111000000000000011110 &
b00000000000000000000001011111110 (
b001011111110 )
#4020001
b1001000000000000000010011 #
b11111111111111111111100100010011 %
b1001000000000000000010011 &
b11111111111111111111100100010011 (
b100100010011 )
#4121001
b0011111000000000000011010 #
b00000000000000000000001111111010 %
b0011111000000000000011010 &
b00000000000000000000001111111010 (
b001111111010 )
#4123001
b1110011000000000000010110 #
b11111111111111111111111001110110 %
b1110011000000000000010110 &
b11111111111111111111111001110110 (
b111001110110 )
#4224001
b0010010000000000000001111 #
b00000000000000000000001001001111 %
b0010010000000000000001111 &
b00000000000000000000001001001111 (
b001001001111 )
#4226001
b1101001000000000000000000 #
b11111111111111111111110100100000 %
b1101001000000000000000000 &
b11111111111111111111110100100000 (
b110100100000 )
#4327001
b0011000000000000000011010 #
b00000000000000000000001100011010 %
b0011000000000000000011010 &
b00000000000000000000001100011010 (
b001100011010 )
#4329001
b1110011000000000000001010 #
b11111111111111111111111001101010 %
b1110011000000000000001010 &
b11111111111111111111111001101010 (
b111001101010 )
#4430001
b0010011000000000000011000 #
b00000000000000000000001001111000 %
b0010011000000000000011000 &
b00000000000000000000001001111000 (
b001001111000 )
#4432001
b1000111000000000000000000 #
b11111111111111111111100011100000 %
b1000111000000000000000000 &
b11111111111111111111100011100000 (
b100011100000 )
#4533001
b0001000000000000000001111 #
b00000000000000000000000100001111 %
b0001000000000000000001111 &
b00000000000000000000000100001111 (
b000100001111 )
#4535001
b1110111000000000000001011 #
b11111111111111111111111011101011 %
b1110111000000000000001011 &
b11111111111111111111111011101011 (
b111011101011 )
#4636001
b0011010000000000000000110 #
b00000000000000000000001101000110 %
b0011010000000000000000110 &
b00000000000000000000001101000110 (
b001101000110 )
#4638001
b1001011000000000000001000 #
b11111111111111111111100101101000 %
b1001011000000000000001000 &
b11111111111111111111100101101000 (
b100101101000 )
#4739001
b0010101000000000000011010 #
b00000000000000000000001010111010 %
b0010101000000000000011010 &
b00000000000000000000001010111010 (
b001010111010 )
#4741001
b1011000000000000000000010 #
b11111111111111111111101100000010 %
b1011000000000000000000010 &
b11111111111111111111101100000010 (
b101100000010 )
#4842001
b0011100000000000000010100 #
b00000000000000000000001110010100 %
b0011100000000000000010100 &
b00000000000000000000001110010100 (
b001110010100 )
#4844001
b1110100000000000000011100 #
b11111111111111111111111010011100 %
b1110100000000000000011100 &
b11111111111111111111111010011100 (
b111010011100 )
#4945001
b0011011000000000000001111 #
b00000000000000000000001101101111 %
b0011011000000000000001111 &
b00000000000000000000001101101111 (
b001101101111 )
#4947001
b1111101000000000000000000 #
b11111111111111111111111110100000 %
b1111101000000000000000000 &
b11111111111111111111111110100000 (
b111110100000 )
#5048001
b0000111000000000000010000 #
b00000000000000000000000011110000 %
b0000111000000000000010000 &
b00000000000000000000000011110000 (
b000011110000 )
#5050001
b1111111000000000000010110 #
b11111111111111111111111111110110 %
b1111111000000000000010110 &
b11111111111111111111111111110110 (
b111111110110 )
#5151001
b0000011000000000000000011 #
b00000000000000000000000001100011 %
b0000011000000000000000011 &
b00000000000000000000000001100011 (
b000001100011 )
#5153001
b1000111000000000000011100 #
b11111111111111111111100011111100 %
b1000111000000000000011100 &
b11111111111111111111100011111100 (
b100011111100 )
#5254001
b0011001000000000000010000 #
b00000000000000000000001100110000 %
b0011001000000000000010000 &
b00000000000000000000001100110000 (
b001100110000 )
#5256001
b1101110000000000000000000 #
b11111111111111111111110111000000 %
b1101110000000000000000000 &
b11111111111111111111110111000000 (
b110111000000 )
#5357001
b0000000000000000000001000 #
b00000000000000000000000000001000 %
b0000000000000000000001000 &
b00000000000000000000000000001000 (
b000000001000 )
#5359001
b1001011000000000000010101 #
b11111111111111111111100101110101 %
b1001011000000000000010101 &
b11111111111111111111100101110101 (
b100101110101 )
#5460001
b0000101000000000000011101 #
b00000000000000000000000010111101 %
b0000101000000000000011101 &
b00000000000000000000000010111101 (
b000010111101 )
#5462001
b1100000000000000000001101 #
b11111111111111111111110000001101 %
b1100000000000000000001101 &
b11111111111111111111110000001101 (
b110000001101 )
#5563001
b0011101000000000000010101 #
b00000000000000000000001110110101 %
b0011101000000000000010101 &
b00000000000000000000001110110101 (
b001110110101 )
#5565001
b1000001000000000000001110 #
b11111111111111111111100000101110 %
b1000001000000000000001110 &
b11111111111111111111100000101110 (
b100000101110 )
#5666001
b0001101000000000000010100 #
b00000000000000000000000110110100 %
b0001101000000000000010100 &
b00000000000000000000000110110100 (
b000110110100 )
#5668001
b1110100000000000000011100 #
b11111111111111111111111010011100 %
b1110100000000000000011100 &
b11111111111111111111111010011100 (
b111010011100 )
#5769001
b0010010000000000000010000 #
b00000000000000000000001001010000 %
b0010010000000000000010000 &
b00000000000000000000001001010000 (
b001001010000 )
#5771001
b1011000000000000000000011 #
b11111111111111111111101100000011 %
b1011000000000000000000011 &
b11111111111111111111101100000011 (
b101100000011 )
#5872001
b0010110000000000000010001 #
b00000000000000000000001011010001 %
b0010110000000000000010001 &
b00000000000000000000001011010001 (
b001011010001 )
#5874001
b1111101000000000000000010 #
b11111111111111111111111110100010 %
b1111101000000000000000010 &
b11111111111111111111111110100010 (
b111110100010 )
#5975001
b0000010000000000000010100 #
b00000000000000000000000001010100 %
b0000010000000000000010100 &
b00000000000000000000000001010100 (
b000001010100 )
#5977001
b1000110000000000000001000 #
b11111111111111111111100011001000 %
b1000110000000000000001000 &
b11111111111111111111100011001000 (
b100011001000 )
#6078001
b0001010000000000000010111 #
b00000000000000000000000101010111 %
b0001010000000000000010111 &
b00000000000000000000000101010111 (
b000101010111 )
#6080001
b1100100000000000000000011 #
b11111111111111111111110010000011 %
b1100100000000000000000011 &
b11111111111111111111110010000011 (
b110010000011 )
#6181001
b0001110000000000000011011 #
b00000000000000000000000111011011 %
b0001110000000000000011011 &
b00000000000000000000000111011011 (
b000111011011 )
#6183001
b1110000000000000000010000 #
b11111111111111111111111000010000 %
b1110000000000000000010000 &
b11111111111111111111111000010000 (
b111000010000 )
#6284001
b0011010000000000000011111 #
b00000000000000000000001101011111 %
b0011010000000000000011111 &
b00000000000000000000001101011111 (
b001101011111 )
#6286001
b1011111000000000000000110 #
b11111111111111111111101111100110 %
b1011111000000000000000110 &
b11111111111111111111101111100110 (
b101111100110 )
#6387001
b0011001000000000000001110 #
b00000000000000000000001100101110 %
b0011001000000000000001110 &
b00000000000000000000001100101110 (
b001100101110 )
#6389001
b1001011000000000000000011 #
b11111111111111111111100101100011 %
b1001011000000000000000011 &
b11111111111111111111100101100011 (
b100101100011 )
#6490001
b0000001000000000000010010 #
b00000000000000000000000000110010 %
b0000001000000000000010010 &
b00000000000000000000000000110010 (
b000000110010 )
#6492001
b1011111000000000000001000 #
b11111111111111111111101111101000 %
b1011111000000000000001000 &
b11111111111111111111101111101000 (
b101111101000 )
#6593001
b0001010000000000000001110 #
b00000000000000000000000101001110 %
b0001010000000000000001110 &
b00000000000000000000000101001110 (
b000101001110 )
#6595001
b1011011000000000000000000 #
b11111111111111111111101101100000 %
b1011011000000000000000000 &
b11111111111111111111101101100000 (
b101101100000 )
#6696001
b0010010000000000000011100 #
b00000000000000000000001001011100 %
b0010010000000000000011100 &
b00000000000000000000001001011100 (
b001001011100 )
#6698001
b1110110000000000000011110 #
b11111111111111111111111011011110 %
b1110110000000000000011110 &
b11111111111111111111111011011110 (
b111011011110 )
#6799001
b0001111000000000000010010 #
b00000000000000000000000111110010 %
b0001111000000000000010010 &
b00000000000000000000000111110010 (
b000111110010 )
#6801001
b1000100000000000000001001 #
b11111111111111111111100010001001 %
b1000100000000000000001001 &
b11111111111111111111100010001001 (
b100010001001 )
#6902001
b0011100000000000000000101 #
b00000000000000000000001110000101 %
b0011100000000000000000101 &
b00000000000000000000001110000101 (
b001110000101 )
#6904001
b1010001000000000000010000 #
b11111111111111111111101000110000 %
b1010001000000000000010000 &
b11111111111111111111101000110000 (
b101000110000 )
#7005001
b0011010000000000000001100 #
b00000000000000000000001101001100 %
b0011010000000000000001100 &
b00000000000000000000001101001100 (
b001101001100 )
#7007001
b1111100000000000000010010 #
b11111111111111111111111110010010 %
b1111100000000000000010010 &
b11111111111111111111111110010010 (
b111110010010 )
#7108001
b0011110000000000000000010 #
b00000000000000000000001111000010 %
b0011110000000000000000010 &
b00000000000000000000001111000010 (
b001111000010 )
#7110001
b1010011000000000000011011 #
b11111111111111111111101001111011 %
b1010011000000000000011011 &
b11111111111111111111101001111011 (
b101001111011 )
#7211001
b0011110000000000000011010 #
b00000000000000000000001111011010 %
b0011110000000000000011010 &
b00000000000000000000001111011010 (
b001111011010 )
#7213001
b1110000000000000000000011 #
b11111111111111111111111000000011 %
b1110000000000000000000011 &
b11111111111111111111111000000011 (
b111000000011 )
#7314001
b0001010000000000000000010 #
b00000000000000000000000101000010 %
b0001010000000000000000010 &
b00000000000000000000000101000010 (
b000101000010 )
#7316001
b1110000000000000000010000 #
b11111111111111111111111000010000 %
b1110000000000000000010000 &
b11111111111111111111111000010000 (
b111000010000 )
#7417001
b0000100000000000000001111 #
b00000000000000000000000010001111 %
b0000100000000000000001111 &
b00000000000000000000000010001111 (
b000010001111 )
#7419001
b1100010000000000000000000 #
b11111111111111111111110001000000 %
b1100010000000000000000000 &
b11111111111111111111110001000000 (
b110001000000 )
#7520001
b0011101000000000000001000 #
b00000000000000000000001110101000 %
b0011101000000000000001000 &
b00000000000000000000001110101000 (
b001110101000 )
#7522001
b1010010000000000000011110 #
b11111111111111111111101001011110 %
b1010010000000000000011110 &
b11111111111111111111101001011110 (
b101001011110 )
#7623001
b0000010000000000000011010 #
b00000000000000000000000001011010 %
b0000010000000000000011010 &
b00000000000000000000000001011010 (
b000001011010 )
#7625001
b1110111000000000000001111 #
b11111111111111111111111011101111 %
b1110111000000000000001111 &
b11111111111111111111111011101111 (
b111011101111 )
#7726001
b0011100000000000000001011 #
b00000000000000000000001110001011 %
b0011100000000000000001011 &
b00000000000000000000001110001011 (
b001110001011 )
#7728001
b1100101000000000000000000 #
b11111111111111111111110010100000 %
b1100101000000000000000000 &
b11111111111111111111110010100000 (
b110010100000 )
#7829001
b0010110000000000000000101 #
b00000000000000000000001011000101 %
b0010110000000000000000101 &
b00000000000000000000001011000101 (
b001011000101 )
#7831001
b1111001000000000000000010 #
b11111111111111111111111100100010 %
b1111001000000000000000010 &
b11111111111111111111111100100010 (
b111100100010 )
#7932001
b0011000000000000000011101 #
b00000000000000000000001100011101 %
b0011000000000000000011101 &
b00000000000000000000001100011101 (
b001100011101 )
#7934001
b1010001000000000000010111 #
b11111111111111111111101000110111 %
b1010001000000000000010111 &
b11111111111111111111101000110111 (
b101000110111 )
#8035001
b0011011000000000000011101 #
b00000000000000000000001101111101 %
b0011011000000000000011101 &
b00000000000000000000001101111101 (
b001101111101 )
#8037001
b1111110000000000000010111 #
b11111111111111111111111111010111 %
b1111110000000000000010111 &
b11111111111111111111111111010111 (
b111111010111 )
#8138001
b0001101000000000000011011 #
b00000000000000000000000110111011 %
b0001101000000000000011011 &
b00000000000000000000000110111011 (
b000110111011 )
#8140001
b1000110000000000000000110 #
b11111111111111111111100011000110 %
b1000110000000000000000110 &
b11111111111111111111100011000110 (
b100011000110 )
#8241001
b0000010000000000000001000 #
b00000000000000000000000001001000 %
b0000010000000000000001000 &
b00000000000000000000000001001000 (
b000001001000 )
#8243001
b1111100000000000000010000 #
b11111111111111111111111110010000 %
b1111100000000000000010000 &
b11111111111111111111111110010000 (
b111110010000 )
#8344001
b0011011000000000000000100 #
b00000000000000000000001101100100 %
b0011011000000000000000100 &
b00000000000000000000001101100100 (
b001101100100 )
#8346001
b1010110000000000000011011 #
b11111111111111111111101011011011 %
b1010110000000000000011011 &
b11111111111111111111101011011011 (
b101011011011 )
#8447001
b0011011000000000000011010 #
b00000000000000000000001101111010 %
b0011011000000000000011010 &
b00000000000000000000001101111010 (
b001101111010 )
#8449001
b1010111000000000000011100 #
b11111111111111111111101011111100 %
b1010111000000000000011100 &
b11111111111111111111101011111100 (
b101011111100 )
#8550001
b0011101000000000000000101 #
b00000000000000000000001110100101 %
b0011101000000000000000101 &
b00000000000000000000001110100101 (
b001110100101 )
#8552001
b1011000000000000000000000 #
b11111111111111111111101100000000 %
b1011000000000000000000000 &
b11111111111111111111101100000000 (
b101100000000 )
#8653001
b0000100000000000000000110 #
b00000000000000000000000010000110 %
b0000100000000000000000110 &
b00000000000000000000000010000110 (
b000010000110 )
#8655001
b1000101000000000000000010 #
b11111111111111111111100010100010 %
b1000101000000000000000010 &
b11111111111111111111100010100010 (
b100010100010 )
#8756001
b0010010000000000000001101 #
b00000000000000000000001001001101 %
b0010010000000000000001101 &
b00000000000000000000001001001101 (
b001001001101 )
#8758001
b1011000000000000000001100 #
b11111111111111111111101100001100 %
b1011000000000000000001100 &
b11111111111111111111101100001100 (
b101100001100 )
#8859001
b0011111000000000000010111 #
b00000000000000000000001111110111 %
b0011111000000000000010111 &
b00000000000000000000001111110111 (
b001111110111 )
#8861001
b1000101000000000000010001 #
b11111111111111111111100010110001 %
b1000101000000000000010001 &
b11111111111111111111100010110001 (
b100010110001 )
#8962001
b0010110000000000000010110 #
b00000000000000000000001011010110 %
b0010110000000000000010110 &
b00000000000000000000001011010110 (
b001011010110 )
#8964001
b1110001000000000000000010 #
b11111111111111111111111000100010 %
b1110001000000000000000010 &
b11111111111111111111111000100010 (
b111000100010 )
#9065001
b0010001000000000000010101 #
b00000000000000000000001000110101 %
b0010001000000000000010101 &
b00000000000000000000001000110101 (
b001000110101 )
#9067001
b1001011000000000000001100 #
b11111111111111111111100101101100 %
b1001011000000000000001100 &
b11111111111111111111100101101100 (
b100101101100 )
#9168001
b0000000000000000000000000 #
b00000000000000000000000000000000 %
b0000000000000000000000000 &
b00000000000000000000000000000000 (
b000000000000 )
#9170001
b1000110000000000000011110 #
b11111111111111111111100011011110 %
b1000110000000000000011110 &
b11111111111111111111100011011110 (
b100011011110 )
#9271001
b0000101000000000000010010 #
b00000000000000000000000010110010 %
b0000101000000000000010010 &
b00000000000000000000000010110010 (
b000010110010 )
#9273001
b1111101000000000000011100 #
b11111111111111111111111110111100 %
b1111101000000000000011100 &
b11111111111111111111111110111100 (
b111110111100 )
#9374001
b0010010000000000000010110 #
b00000000000000000000001001010110 %
b0010010000000000000010110 &
b00000000000000000000001001010110 (
b001001010110 )
#9376001
b1110101000000000000001111 #
b11111111111111111111111010101111 %
b1110101000000000000001111 &
b11111111111111111111111010101111 (
b111010101111 )
#9477001
b0010101000000000000011000 #
b00000000000000000000001010111000 %
b0010101000000000000011000 &
b00000000000000000000001010111000 (
b001010111000 )
#9479001
b1001110000000000000000111 #
b11111111111111111111100111000111 %
b1001110000000000000000111 &
b11111111111111111111100111000111 (
b100111000111 )
#9580001
b0010000000000000000011000 #
b00000000000000000000001000011000 %
b0010000000000000000011000 &
b00000000000000000000001000011000 (
b001000011000 )
#9582001
b1001011000000000000000110 #
b11111111111111111111100101100110 %
b1001011000000000000000110 &
b11111111111111111111100101100110 (
b100101100110 )
#9683001
b0000001000000000000011110 #
b00000000000000000000000000111110 %
b0000001000000000000011110 &
b00000000000000000000000000111110 (
b000000111110 )
#9685001
b1110110000000000000011100 #
b11111111111111111111111011011100 %
b1110110000000000000011100 &
b11111111111111111111111011011100 (
b111011011100 )
#9786001
b0000000000000000000011101 #
b00000000000000000000000000011101 %
b0000000000000000000011101 &
b00000000000000000000000000011101 (
b000000011101 )
#9788001
b1011010000000000000010001 #
b11111111111111111111101101010001 %
b1011010000000000000010001 &
b11111111111111111111101101010001 (
b101101010001 )
#9889001
b0010101000000000000010111 #
b00000000000000000000001010110111 %
b0010101000000000000010111 &
b00000000000000000000001010110111 (
b001010110111 )
#9891001
b1011111000000000000011000 #
b11111111111111111111101111111000 %
b1011111000000000000011000 &
b11111111111111111111101111111000 (
b101111111000 )
#9992001
b0001100000000000000001111 #
b00000000000000000000000110001111 %
b0001100000000000000001111 &
b00000000000000000000000110001111 (
b000110001111 )
#9994001
b1110111000000000000001110 #
b11111111111111111111111011101110 %
b1110111000000000000001110 &
b11111111111111111111111011101110 (
b111011101110 )
#10095001
b0011110000000000000001111 #
b00000000000000000000001111001111 %
b0011110000000000000001111 &
b00000000000000000000001111001111 (
b001111001111 )
#10097001
b1010111000000000000000001 #
b11111111111111111111101011100001 %
b1010111000000000000000001 &
b11111111111111111111101011100001 (
b101011100001 )
#10198001
b0000010000000000000011001 #
b00000000000000000000000001011001 %
b0000010000000000000011001 &
b00000000000000000000000001011001 (
b000001011001 )
#10200001
b1010101000000000000010100 #
b11111111111111111111101010110100 %
b1010101000000000000010100 &
b11111111111111111111101010110100 (
b101010110100 )
#10301001
b0010000000000000000000011 #
b00000000000000000000001000000011 %
b0010000000000000000000011 &
b00000000000000000000001000000011 (
b001000000011 )
