load/src/memoryInit.sv
module memory #(
    parameter WORDS = 64,
    parameter mem_init = ""
) (
    input logic clk,
    input logic [31:0] address,
    input logic [31:0] write_data,
    input logic write_enable,
    input logic rst_n,

    output logic [31:0] read_data
);

reg [31:0] mem [0:WORDS-1];  // Memory array of words (32-bits)

initial begin
    if (mem_init != "") begin
        $readmemh(mem_init, mem);
    end  // Load memory for simulation
end

always @(posedge clk) begin
    // reset logic
    if (rst_n == 1'b0) begin
        for (int i = 0; i < WORDS; i++) begin
            mem[i] <= 32'b0;  
        end
    end
    else if (write_enable) begin
        // Ensure the address is aligned to a word boundary
        // If not, we ignore the write
        if (address[1:0] == 2'b00) begin 
            //here, address[31:2] is the word index
            mem[address[31:0]] <= write_data;
        end
    end
end

// Read logic
always_comb begin
    //here, address[31:2] is the word index
    read_data = mem[address[31:0]]; 
end

endmodule

load/tb/memory/dump.vcd
$version Generated by VerilatedVcd $end
$timescale 1ps $end
 $scope module $rootio $end
  $var wire 1 # clk $end
  $var wire 32 $ address [31:0] $end
  $var wire 32 % write_data [31:0] $end
  $var wire 1 & write_enable $end
  $var wire 1 ' rst_n $end
  $var wire 32 ( read_data [31:0] $end
 $upscope $end
 $scope module memory $end
  $var wire 32 0 WORDS [31:0] $end
  $var wire 8 1 mem_init [7:0] $end
  $var wire 1 ) clk $end
  $var wire 32 * address [31:0] $end
  $var wire 32 + write_data [31:0] $end
  $var wire 1 , write_enable $end
  $var wire 1 - rst_n $end
  $var wire 32 . read_data [31:0] $end
  $scope module unnamedblk1 $end
   $var wire 32 / i [31:0] $end
  $upscope $end
 $upscope $end
$enddefinitions $end


#0
1#
b00000000000000000000000000000000 $
b00000000000000000000000000000000 %
0&
0'
b00000000000000000000000000000000 (
1)
b00000000000000000000000000000000 *
b00000000000000000000000000000000 +
0,
0-
b00000000000000000000000000000000 .
b00000000000000000000000001000000 /
b00000000000000000000000001000000 0
b00000000 1
#5000
0#
0)
#10000
1#
1'
1)
1-
#15000
0#
0)
#20000
1#
1)
#21000
b00000000000000000000000000000001 $
b00000000000000000000000000000001 *
#22000
b00000000000000000000000000000010 $
b00000000000000000000000000000010 *
#23000
b00000000000000000000000000000011 $
b00000000000000000000000000000011 *
#24000
b00000000000000000000000000000100 $
b00000000000000000000000000000100 *
#25000
0#
b00000000000000000000000000000101 $
0)
b00000000000000000000000000000101 *
#26000
b00000000000000000000000000000110 $
b00000000000000000000000000000110 *
#27000
b00000000000000000000000000000111 $
b00000000000000000000000000000111 *
#28000
b00000000000000000000000000001000 $
b00000000000000000000000000001000 *
#29000
b00000000000000000000000000001001 $
b00000000000000000000000000001001 *
#30000
1#
b00000000000000000000000000001010 $
1)
b00000000000000000000000000001010 *
#31000
b00000000000000000000000000001011 $
b00000000000000000000000000001011 *
#32000
b00000000000000000000000000001100 $
b00000000000000000000000000001100 *
#33000
b00000000000000000000000000001101 $
b00000000000000000000000000001101 *
#34000
b00000000000000000000000000001110 $
b00000000000000000000000000001110 *
#35000
0#
b00000000000000000000000000001111 $
0)
b00000000000000000000000000001111 *
#36000
b00000000000000000000000000010000 $
b00000000000000000000000000010000 *
#37000
b00000000000000000000000000010001 $
b00000000000000000000000000010001 *
#38000
b00000000000000000000000000010010 $
b00000000000000000000000000010010 *
#39000
b00000000000000000000000000010011 $
b00000000000000000000000000010011 *
#40000
1#
b00000000000000000000000000010100 $
1)
b00000000000000000000000000010100 *
#41000
b00000000000000000000000000010101 $
b00000000000000000000000000010101 *
#42000
b00000000000000000000000000010110 $
b00000000000000000000000000010110 *
#43000
b00000000000000000000000000010111 $
b00000000000000000000000000010111 *
#44000
b00000000000000000000000000011000 $
b00000000000000000000000000011000 *
#45000
0#
b00000000000000000000000000011001 $
0)
b00000000000000000000000000011001 *
#46000
b00000000000000000000000000011010 $
b00000000000000000000000000011010 *
#47000
b00000000000000000000000000011011 $
b00000000000000000000000000011011 *
#48000
b00000000000000000000000000011100 $
b00000000000000000000000000011100 *
#49000
b00000000000000000000000000011101 $
b00000000000000000000000000011101 *
#50000
1#
b00000000000000000000000000011110 $
1)
b00000000000000000000000000011110 *
#51000
b00000000000000000000000000011111 $
b00000000000000000000000000011111 *
#52000
b00000000000000000000000000100000 $
b00000000000000000000000000100000 *
#53000
b00000000000000000000000000100001 $
b00000000000000000000000000100001 *
#54000
b00000000000000000000000000100010 $
b00000000000000000000000000100010 *
#55000
0#
b00000000000000000000000000100011 $
0)
b00000000000000000000000000100011 *
#56000
b00000000000000000000000000100100 $
b00000000000000000000000000100100 *
#57000
b00000000000000000000000000100101 $
b00000000000000000000000000100101 *
#58000
b00000000000000000000000000100110 $
b00000000000000000000000000100110 *
#59000
b00000000000000000000000000100111 $
b00000000000000000000000000100111 *
#60000
1#
b00000000000000000000000000101000 $
1)
b00000000000000000000000000101000 *
#61000
b00000000000000000000000000101001 $
b00000000000000000000000000101001 *
#62000
b00000000000000000000000000101010 $
b00000000000000000000000000101010 *
#63000
b00000000000000000000000000101011 $
b00000000000000000000000000101011 *
#64000
b00000000000000000000000000101100 $
b00000000000000000000000000101100 *
#65000
0#
b00000000000000000000000000101101 $
0)
b00000000000000000000000000101101 *
#66000
b00000000000000000000000000101110 $
b00000000000000000000000000101110 *
#67000
b00000000000000000000000000101111 $
b00000000000000000000000000101111 *
#68000
b00000000000000000000000000110000 $
b00000000000000000000000000110000 *
#69000
b00000000000000000000000000110001 $
b00000000000000000000000000110001 *
#70000
1#
b00000000000000000000000000110010 $
1)
b00000000000000000000000000110010 *
#71000
b00000000000000000000000000110011 $
b00000000000000000000000000110011 *
#72000
b00000000000000000000000000110100 $
b00000000000000000000000000110100 *
#73000
b00000000000000000000000000110101 $
b00000000000000000000000000110101 *
#74000
b00000000000000000000000000110110 $
b00000000000000000000000000110110 *
#75000
0#
b00000000000000000000000000110111 $
0)
b00000000000000000000000000110111 *
#76000
b00000000000000000000000000111000 $
b00000000000000000000000000111000 *
#77000
b00000000000000000000000000111001 $
b00000000000000000000000000111001 *
#78000
b00000000000000000000000000111010 $
b00000000000000000000000000111010 *
#79000
b00000000000000000000000000111011 $
b00000000000000000000000000111011 *
#80000
1#
b00000000000000000000000000111100 $
1)
b00000000000000000000000000111100 *
#81000
b00000000000000000000000000111101 $
b00000000000000000000000000111101 *
#82000
b00000000000000000000000000111110 $
b00000000000000000000000000111110 *
#83000
b00000000000000000000000000111111 $
b00000000000000000000000000111111 *
#84000
b00000000000000000000000000000000 $
b11011110101011011011111011101111 %
1&
b00000000000000000000000000000000 *
b11011110101011011011111011101111 +
1,
#85000
0#
0)
#90000
1#
0&
b11011110101011011011111011101111 (
1)
0,
b11011110101011011011111011101111 .
#95000
0#
0)
#100000
1#
1)
#105000
0#
0)
#110000
1#
b00000000000000000000000000000100 $
b11001010111111101011101010111110 %
1&
b00000000000000000000000000000000 (
1)
b00000000000000000000000000000100 *
b11001010111111101011101010111110 +
1,
b00000000000000000000000000000000 .
#115000
0#
0)
#120000
1#
0&
b11001010111111101011101010111110 (
1)
0,
b11001010111111101011101010111110 .
#125000
0#
0)
#130000
1#
1)
#135000
0#
0)
#140000
1#
b00000000000000000000000000001000 $
b00010010001101000101011001111000 %
1&
b00000000000000000000000000000000 (
1)
b00000000000000000000000000001000 *
b00010010001101000101011001111000 +
1,
b00000000000000000000000000000000 .
#145000
0#
0)
#150000
1#
0&
b00010010001101000101011001111000 (
1)
0,
b00010010001101000101011001111000 .
#155000
0#
0)
#160000
1#
1)
#165000
0#
0)
#170000
1#
b00000000000000000000000000001100 $
b10100101101001011010010110100101 %
1&
b00000000000000000000000000000000 (
1)
b00000000000000000000000000001100 *
b10100101101001011010010110100101 +
1,
b00000000000000000000000000000000 .
#175000
0#
0)
#180000
1#
0&
b10100101101001011010010110100101 (
1)
0,
b10100101101001011010010110100101 .
