Rtype_and_or/src/alu.sv
// alu.sv
module alu (
    // IN
    input logic [2:0] alu_control,
    input logic [31:0] src1,
    input logic [31:0] src2,
    // OUT
    output logic [31:0] alu_result,
    output logic zero
);

always_comb begin
    case (alu_control)
    	// ADD +
        3'b000 : alu_result = src1 + src2;
	// AND &
	3'b010 : alu_result = src1 & src2;
	// OR |
	3'b011 : alu_result = src1 | src2;
        default: alu_result = 32'b0;
    endcase
end

assign zero = alu_result == 32'b0;
    
endmodule

load/tb/alu/dump.vcd
$version Generated by VerilatedVcd $end
$timescale 1ps $end
 $scope module $rootio $end
  $var wire 3 # alu_control [2:0] $end
  $var wire 32 $ src1 [31:0] $end
  $var wire 32 % src2 [31:0] $end
  $var wire 32 & alu_result [31:0] $end
  $var wire 1 ' zero $end
 $upscope $end
 $scope module alu $end
  $var wire 3 ( alu_control [2:0] $end
  $var wire 32 ) src1 [31:0] $end
  $var wire 32 * src2 [31:0] $end
  $var wire 32 + alu_result [31:0] $end
  $var wire 1 , zero $end
 $upscope $end
$enddefinitions $end


#0
b000 #
b00000000000000000000000000000000 $
b00000000000000000000000000000000 %
b00000000000000000000000000000000 &
1'
b000 (
b00000000000000000000000000000000 )
b00000000000000000000000000000000 *
b00000000000000000000000000000000 +
1,
#1000
b00000011100111110001101100101000 $
b11000000000011011000100000111110 %
b11000011101011001010001101100110 &
0'
b00000011100111110001101100101000 )
b11000000000011011000100000111110 *
b11000011101011001010001101100110 +
0,
#2000
b11001001101010000111000001011000 $
b11100101001110110110000101010100 %
b10101110111000111101000110101100 &
b11001001101010000111000001011000 )
b11100101001110110110000101010100 *
b10101110111000111101000110101100 +
#3000
b00100111000111011101010011101110 $
b00110000010000011111010101001011 %
b01010111010111111100101000111001 &
b00100111000111011101010011101110 )
b00110000010000011111010101001011 *
b01010111010111111100101000111001 +
#4000
b10001010101101000011111011100000 $
b01011101100110001110101001011100 %
b11101000010011010010100100111100 &
b10001010101101000011111011100000 )
b01011101100110001110101001011100 *
b11101000010011010010100100111100 +
#5000
b11101110111101010001101011111101 $
b10001001110100111011100111010111 %
b01111000110010001101010011010100 &
b11101110111101010001101011111101 )
b10001001110100111011100111010111 *
b01111000110010001101010011010100 +
#6000
b11100111100000101110101100000010 $
b11100001111000011011000100101111 %
b11001001011001001001110000110001 &
b11100111100000101110101100000010 )
b11100001111000011011000100101111 *
b11001001011001001001110000110001 +
#7000
b01110111110011110100000110010101 $
b11011001111111110010001101011011 %
b01010001110011100110010011110000 &
b01110111110011110100000110010101 )
b11011001111111110010001101011011 *
b01010001110011100110010011110000 +
#8000
b10111101001011100110001000101011 $
b11010110111010101011000110001101 %
b10010100000110010001001110111000 &
b10111101001011100110001000101011 )
b11010110111010101011000110001101 *
b10010100000110010001001110111000 +
#9000
b00110100000001010010101110001100 $
b10110111010010111010101011010100 %
b11101011010100001101011001100000 &
b00110100000001010010101110001100 )
b10110111010010111010101011010100 *
b11101011010100001101011001100000 +
#10000
b01000101000100001001110010101100 $
b11000101011010000000010001011001 %
b00001010011110001010000100000101 &
b01000101000100001001110010101100 )
b11000101011010000000010001011001 *
b00001010011110001010000100000101 +
#11000
b00011100101100001000001111110100 $
b11110110100011111010110100110001 %
b00010011010000000011000100100101 &
b00011100101100001000001111110100 )
b11110110100011111010110100110001 *
b00010011010000000011000100100101 +
#12000
b00110000111110101010100010110010 $
b00100100110110010100110100111010 %
b01010101110100111111010111101100 &
b00110000111110101010100010110010 )
b00100100110110010100110100111010 *
b01010101110100111111010111101100 +
#13000
b01110010100100001111111000011001 $
b11001000110001001110000010100001 %
b00111011010101011101111010111010 &
b01110010100100001111111000011001 )
b11001000110001001110000010100001 *
b00111011010101011101111010111010 +
#14000
b11110001111011010010001111101010 $
b11100100010100111011101010001001 %
b11010110010000001101111001110011 &
b11110001111011010010001111101010 )
b11100100010100111011101010001001 *
b11010110010000001101111001110011 +
#15000
b10001101101011100101010000111000 $
b11111000100101000100101100001101 %
b10000110010000101001111101000101 &
b10001101101011100101010000111000 )
b11111000100101000100101100001101 *
b10000110010000101001111101000101 +
#16000
b00110001000110011101011101111101 $
b10111100011010000001001100001111 %
b11101101100000011110101010001100 &
b00110001000110011101011101111101 )
b10111100011010000001001100001111 *
b11101101100000011110101010001100 +
#17000
b10000111111000101101010001100100 $
b10110000111111000000100110000111 %
b00111000110111101101110111101011 &
b10000111111000101101010001100100 )
b10110000111111000000100110000111 *
b00111000110111101101110111101011 +
#18000
b00001000100101010010000011001010 $
b01111011111110100011110101000000 %
b10000100100011110101111000001010 &
b00001000100101010010000011001010 )
b01111011111110100011110101000000 *
b10000100100011110101111000001010 +
#19000
b10010111100010100100010101101011 $
b11001110011100011100101001010100 %
b01100101111111000000111110111111 &
b10010111100010100100010101101011 )
b11001110011100011100101001010100 *
b01100101111111000000111110111111 +
#20000
b11101011111110100001111101111110 $
b10110110110110110101010111000011 %
b10100010110101010111010101000001 &
b11101011111110100001111101111110 )
b10110110110110110101010111000011 *
b10100010110101010111010101000001 +
#21000
b01100110011100111101001010010000 $
b11011110110010111111111000100110 %
b01000101001111111101000010110110 &
b01100110011100111101001010010000 )
b11011110110010111111111000100110 *
b01000101001111111101000010110110 +
#22000
b00110010111011100110000101101110 $
b00011111111001010111111000001011 %
b01010010110100111101111101111001 &
b00110010111011100110000101101110 )
b00011111111001010111111000001011 *
b01010010110100111101111101111001 +
#23000
b00001110010011100101100000011010 $
b00110000110101100110111100011110 %
b00111111001001001100011100111000 &
b00001110010011100101100000011010 )
b00110000110101100110111100011110 *
b00111111001001001100011100111000 +
#24000
b00110001101100110001100110101010 $
b10010110001111110110110001011110 %
b11000111111100101000011000001000 &
b00110001101100110001100110101010 )
b10010110001111110110110001011110 *
b11000111111100101000011000001000 +
#25000
b10000010110110111111010000100100 $
b11111010000010001101010110011100 %
b01111100111001001100100111000000 &
b10000010110110111111010000100100 )
b11111010000010001101010110011100 *
b01111100111001001100100111000000 +
#26000
b01100011000010010000100010101011 $
b10001001010000001111000111111100 %
b11101100010010011111101010100111 &
b01100011000010010000100010101011 )
b10001001010000001111000111111100 *
b11101100010010011111101010100111 +
#27000
b10101001010001110001010110011111 $
b10000001100011110101111101101101 %
b00101010110101100111010100001100 &
b10101001010001110001010110011111 )
b10000001100011110101111101101101 *
b00101010110101100111010100001100 +
#28000
b00111000011011100111010000101011 $
b00000010100001011100100111010010 %
b00111010111101000011110111111101 &
b00111000011011100111010000101011 )
b00000010100001011100100111010010 *
b00111010111101000011110111111101 +
#29000
b00010101110000010010100000001101 $
b00100001001101001011000100111110 %
b00110110111101011101100101001011 &
b00010101110000010010100000001101 )
b00100001001101001011000100111110 *
b00110110111101011101100101001011 +
#30000
b01000001001000000010001010001011 $
b10011101011000000111111011000010 %
b11011110100000001010000101001101 &
b01000001001000000010001010001011 )
b10011101011000000111111011000010 *
b11011110100000001010000101001101 +
#31000
b01100010110001110011101011000110 $
b01001000011100100110000001110000 %
b10101011001110011001101100110110 &
b01100010110001110011101011000110 )
b01001000011100100110000001110000 *
b10101011001110011001101100110110 +
#32000
b10100101101010000101000100000100 $
b11101111010110011000101001010000 %
b10010101000000011101101101010100 &
b10100101101010000101000100000100 )
b11101111010110011000101001010000 *
b10010101000000011101101101010100 +
#33000
b11010111010100001001011110001111 $
b10010100111001010010111111010111 %
b01101100001101011100011101100110 &
b11010111010100001001011110001111 )
b10010100111001010010111111010111 *
b01101100001101011100011101100110 +
#34000
b01010101000101011100000001010001 $
b11110000110101001000001011111110 %
b01000101111010100100001101001111 &
b01010101000101011100000001010001 )
b11110000110101001000001011111110 *
b01000101111010100100001101001111 +
#35000
b00001000000001000000101000100101 $
b00010110111101100111010100111010 %
b00011110111110100111111101011111 &
b00001000000001000000101000100101 )
b00010110111101100111010100111010 *
b00011110111110100111111101011111 +
#36000
b10010110011101111111110101101110 $
b10100011110001101010100010000110 %
b00111010001111101010010111110100 &
b10010110011101111111110101101110 )
b10100011110001101010100010000110 *
b00111010001111101010010111110100 +
#37000
b11010110111001001010001111111100 $
b01011011011101100111101010110000 %
b00110010010110110001111010101100 &
b11010110111001001010001111111100 )
b01011011011101100111101010110000 *
b00110010010110110001111010101100 +
#38000
b10110010001111001001001001101011 $
b11000110010011000100100001010011 %
b01111000100010001101101010111110 &
b10110010001111001001001001101011 )
b11000110010011000100100001010011 *
b01111000100010001101101010111110 +
#39000
b01011001001011010100010011110010 $
b11001110100001100011000000011100 %
b00100111101100110111010100001110 &
b01011001001011010100010011110010 )
b11001110100001100011000000011100 *
b00100111101100110111010100001110 +
#40000
b00001111100100110101111000010011 $
b00110010101000011100000010110011 %
b01000010001101010001111011000110 &
b00001111100100110101111000010011 )
b00110010101000011100000010110011 *
b01000010001101010001111011000110 +
#41000
b10000010001100011101000011100011 $
b00100011010110000111011110110100 %
b10100101100010100100100010010111 &
b10000010001100011101000011100011 )
b00100011010110000111011110110100 *
b10100101100010100100100010010111 +
#42000
b00010111010001111111011011010100 $
b10111111111011110110100000100000 %
b11010111001101110101111011110100 &
b00010111010001111111011011010100 )
b10111111111011110110100000100000 *
b11010111001101110101111011110100 +
#43000
b10101111010100001100011111110001 $
b01111111111001000100111010110011 %
b00101111001101010001011010100100 &
b10101111010100001100011111110001 )
b01111111111001000100111010110011 *
b00101111001101010001011010100100 +
#44000
b11001010100110010100010001011111 $
b11100101011010001110011011010100 %
b10110000000000100010101100110011 &
b11001010100110010100010001011111 )
b11100101011010001110011011010100 *
b10110000000000100010101100110011 +
#45000
b00000101100010000001111101101011 $
b10100010101001111000011010001010 %
b10101000001011111010010111110101 &
b00000101100010000001111101101011 )
b10100010101001111000011010001010 *
b10101000001011111010010111110101 +
#46000
b00011010101101100010110001011000 $
b11010001011000110110001100110000 %
b11101100000110011000111110001000 &
b00011010101101100010110001011000 )
b11010001011000110110001100110000 *
b11101100000110011000111110001000 +
#47000
b11110101000010000101001001010011 $
b01000011001011000111110000000111 %
b00111000001101001100111001011010 &
b11110101000010000101001001010011 )
b01000011001011000111110000000111 *
b00111000001101001100111001011010 +
#48000
b11110001110011000000101111001000 $
b11100110100010111011001101010010 %
b11011000010101111011111100011010 &
b11110001110011000000101111001000 )
b11100110100010111011001101010010 *
b11011000010101111011111100011010 +
#49000
b11100110000100001111111101010011 $
b01110110100100001100011010001010 %
b01011100101000011100010111011101 &
b11100110000100001111111101010011 )
b01110110100100001100011010001010 *
b01011100101000011100010111011101 +
#50000
b11010101100101101010010110010001 $
b11101111010011000101100010011010 %
b11000100111000101111111000101011 &
b11010101100101101010010110010001 )
b11101111010011000101100010011010 *
b11000100111000101111111000101011 +
#51000
b01100011000110111111100111111110 $
b10111111110100010010101101110100 %
b00100010111011010010010101110010 &
b01100011000110111111100111111110 )
b10111111110100010010101101110100 *
b00100010111011010010010101110010 +
#52000
b10010111011011100010101110101110 $
b01111001110010110111101001001110 %
b00010001001110011010010111111100 &
b10010111011011100010101110101110 )
b01111001110010110111101001001110 *
b00010001001110011010010111111100 +
#53000
b11011100000010011010000001111001 $
b11010001100101000001111011011010 %
b10101101100111011011111101010011 &
b11011100000010011010000001111001 )
b11010001100101000001111011011010 *
b10101101100111011011111101010011 +
#54000
b10110000011011011111011001010111 $
b10110100100001101011001101000101 %
b01100100111101001010100110011100 &
b10110000011011011111011001010111 )
b10110100100001101011001101000101 *
b01100100111101001010100110011100 +
#55000
b11100010011010011011001011101010 $
b01110111011101001010100111000100 %
b01011001110111100101110010101110 &
b11100010011010011011001011101010 )
b01110111011101001010100111000100 *
b01011001110111100101110010101110 +
#56000
b11101010101001001000100010111100 $
b01001101100100101001110000101010 %
b00111000001101110010010011100110 &
b11101010101001001000100010111100 )
b01001101100100101001110000101010 *
b00111000001101110010010011100110 +
#57000
b10101111100010010100110111010110 $
b11000000010011010001010101001100 %
b01101111110101100110001100100010 &
b10101111100010010100110111010110 )
b11000000010011010001010101001100 *
b01101111110101100110001100100010 +
#58000
b11010111001010111010000001010011 $
b00111010000001100011001011000101 %
b00010001001100011101001100011000 &
b11010111001010111010000001010011 )
b00111010000001100011001011000101 *
b00010001001100011101001100011000 +
#59000
b01110100011110000101001101100100 $
b00001101111101011100101101101001 %
b10000010011011100001111011001101 &
b01110100011110000101001101100100 )
b00001101111101011100101101101001 *
b10000010011011100001111011001101 +
#60000
b00100100111111000001000000011100 $
b01111000000100000011010111100100 %
b10011101000011000100011000000000 &
b00100100111111000001000000011100 )
b01111000000100000011010111100100 *
b10011101000011000100011000000000 +
#61000
b11000100001001111011101001010111 $
b00100011001000000001111000100011 %
b11100111010001111101100001111010 &
b11000100001001111011101001010111 )
b00100011001000000001111000100011 *
b11100111010001111101100001111010 +
#62000
b00111111100011011111100111101000 $
b11111110110111110110010000101000 %
b00111110011011010101111000010000 &
b00111111100011011111100111101000 )
b11111110110111110110010000101000 *
b00111110011011010101111000010000 +
#63000
b01000011001000110011000011110111 $
b00100110001001101101010010011010 %
b01101001010010100000010110010001 &
b01000011001000110011000011110111 )
b00100110001001101101010010011010 *
b01101001010010100000010110010001 +
#64000
b11011101100001001001001000010010 $
b00100100101001000010110000110011 %
b00000010001010001011111001000101 &
b11011101100001001001001000010010 )
b00100100101001000010110000110011 *
b00000010001010001011111001000101 +
#65000
b00001111000000011101000100011000 $
b11111101101111000011101010001011 %
b00001100101111100000101110100011 &
b00001111000000011101000100011000 )
b11111101101111000011101010001011 *
b00001100101111100000101110100011 +
#66000
b01111101011011111111001111110110 $
b00110000011001001011101111100011 %
b10101101110101001010111111011001 &
b01111101011011111111001111110110 )
b00110000011001001011101111100011 *
b10101101110101001010111111011001 +
#67000
b01101111111001111010000110000101 $
b10100011111011111000101111100010 %
b00010011110101110010110101100111 &
b01101111111001111010000110000101 )
b10100011111011111000101111100010 *
b00010011110101110010110101100111 +
#68000
b01001110100011111111001110010101 $
b00111011000011100011000001010111 %
b10001001100111100010001111101100 &
b01001110100011111111001110010101 )
b00111011000011100011000001010111 *
b10001001100111100010001111101100 +
#69000
b10000100000101100100111110110010 $
b11101010101110100100101011100001 %
b01101110110100001001101010010011 &
b10000100000101100100111110110010 )
b11101010101110100100101011100001 *
b01101110110100001001101010010011 +
#70000
b00101110001011011110000000000000 $
b01011110111010001001101111110101 %
b10001101000101100111101111110101 &
b00101110001011011110000000000000 )
b01011110111010001001101111110101 *
b10001101000101100111101111110101 +
#71000
b10100110110000100000100001000000 $
b00011110110111011000000101010000 %
b11000101100111111000100110010000 &
b10100110110000100000100001000000 )
b00011110110111011000000101010000 *
b11000101100111111000100110010000 +
#72000
b10011110110100110111011110111010 $
b11110010000110011110011010111100 %
b10010000111011010101111001110110 &
b10011110110100110111011110111010 )
b11110010000110011110011010111100 *
b10010000111011010101111001110110 +
#73000
b10000100100101010000111001011001 $
b11001101101100000001001010110110 %
b01010010010001010010000100001111 &
b10000100100101010000111001011001 )
b11001101101100000001001010110110 *
b01010010010001010010000100001111 +
#74000
b11000001010010110011011000100011 $
b01000010111000100000001011101101 %
b00000100001011010011100100010000 &
b11000001010010110011011000100011 )
b01000010111000100000001011101101 *
b00000100001011010011100100010000 +
#75000
b11111001011111011101110001001100 $
b11110100010011111101011111011010 %
b11101101110011011011010000100110 &
b11111001011111011101110001001100 )
b11110100010011111101011111011010 *
b11101101110011011011010000100110 +
#76000
b11110010110010010011010110010000 $
b00111100111101111101000010010010 %
b00101111110000010000011000100010 &
b11110010110010010011010110010000 )
b00111100111101111101000010010010 *
b00101111110000010000011000100010 +
#77000
b11000011000011101101101000000111 $
b01001101111110000000100101010111 %
b00010001000001101110001101011110 &
b11000011000011101101101000000111 )
b01001101111110000000100101010111 *
b00010001000001101110001101011110 +
#78000
b00010000011110011010110100001000 $
b01111000111101011000100001110110 %
b10001001011011110011010101111110 &
b00010000011110011010110100001000 )
b01111000111101011000100001110110 *
b10001001011011110011010101111110 +
#79000
b11001011110100011011001111111100 $
b00110000011101000000100100000000 %
b11111100010001011011110011111100 &
b11001011110100011011001111111100 )
b00110000011101000000100100000000 *
b11111100010001011011110011111100 +
#80000
b00110010110110000101000011110000 $
b10110100100101011000001011111011 %
b11100111011011011101001111101011 &
b00110010110110000101000011110000 )
b10110100100101011000001011111011 *
b11100111011011011101001111101011 +
#81000
b01010000100010000111000101011111 $
b10001100101001010011011011010001 %
b11011101001011011010100000110000 &
b01010000100010000111000101011111 )
b10001100101001010011011011010001 *
b11011101001011011010100000110000 +
#82000
b01000000001100010111111010011111 $
b01100010010001001011100001111101 %
b10100010011101100011011100011100 &
b01000000001100010111111010011111 )
b01100010010001001011100001111101 *
b10100010011101100011011100011100 +
#83000
b00110100000001000011001100011100 $
b10010001010010000011011000010010 %
b11000101010011000110100100101110 &
b00110100000001000011001100011100 )
b10010001010010000011011000010010 *
b11000101010011000110100100101110 +
#84000
b10010001110011001000000101001111 $
b11101110101011100101010010000001 %
b10000000011110101101010111010000 &
b10010001110011001000000101001111 )
b11101110101011100101010010000001 *
b10000000011110101101010111010000 +
#85000
b10111100111110110101001011101110 $
b01110010101001100000100110100011 %
b00101111101000010101110010010001 &
b10111100111110110101001011101110 )
b01110010101001100000100110100011 *
b00101111101000010101110010010001 +
#86000
b00011100111010110101101010110100 $
b01100000101000111111000010100101 %
b01111101100011110100101101011001 &
b00011100111010110101101010110100 )
b01100000101000111111000010100101 *
b01111101100011110100101101011001 +
#87000
b00011110001010100000001011111111 $
b01011110000000111000001101000111 %
b01111100001011011000011001000110 &
b00011110001010100000001011111111 )
b01011110000000111000001101000111 *
b01111100001011011000011001000110 +
#88000
b11100010011110011011000101010111 $
b00010101011010111010011101010001 %
b11110111111001010101100010101000 &
b11100010011110011011000101010111 )
b00010101011010111010011101010001 *
b11110111111001010101100010101000 +
#89000
b10000100000111000110000101011011 $
b01101000011101110011100111101000 %
b11101100100100111001101101000011 &
b10000100000111000110000101011011 )
b01101000011101110011100111101000 *
b11101100100100111001101101000011 +
#90000
b01100101100101001110001111111001 $
b01010001000111000000101101010100 %
b10110110101100001110111101001101 &
b01100101100101001110001111111001 )
b01010001000111000000101101010100 *
b10110110101100001110111101001101 +
#91000
b00111001011000111101011011110110 $
b10111111100100101000110010111100 %
b11111000111101100110001110110010 &
b00111001011000111101011011110110 )
b10111111100100101000110010111100 *
b11111000111101100110001110110010 +
#92000
b01011001011010001110010001011111 $
b00010011111100001110000110111100 %
b01101101010110011100011000011011 &
b01011001011010001110010001011111 )
b00010011111100001110000110111100 *
b01101101010110011100011000011011 +
#93000
b10000000111010110010010010011001 $
b10000010001101011100110011011010 %
b00000011001000001111000101110011 &
b10000000111010110010010010011001 )
b10000010001101011100110011011010 *
b00000011001000001111000101110011 +
#94000
b01100001001110100100010100100110 $
b10011001001100010100001011000101 %
b11111010011010111000011111101011 &
b01100001001110100100010100100110 )
b10011001001100010100001011000101 *
b11111010011010111000011111101011 +
#95000
b11101111011100001111111100100101 $
b00110000001010110011100001111110 %
b00011111100111000011011110100011 &
b11101111011100001111111100100101 )
b00110000001010110011100001111110 *
b00011111100111000011011110100011 +
#96000
b00010001001000111010010100000111 $
b11110100111010110111111100111111 %
b00000110000011110010010001000110 &
b00010001001000111010010100000111 )
b11110100111010110111111100111111 *
b00000110000011110010010001000110 +
#97000
b00100001011110110011010100010011 $
b01011100101010111011101101100011 %
b01111110001001101111000001110110 &
b00100001011110110011010100010011 )
b01011100101010111011101101100011 *
b01111110001001101111000001110110 +
#98000
b11000010111001000101110110010101 $
b11111111101000010111000110111101 %
b11000010100001011100111101010010 &
b11000010111001000101110110010101 )
b11111111101000010111000110111101 *
b11000010100001011100111101010010 +
#99000
b01000000111101000101110111110100 $
b11100011010100000010000000001100 %
b00100100010001000111111000000000 &
b01000000111101000101110111110100 )
b11100011010100000010000000001100 *
b00100100010001000111111000000000 +
#100000
b01011101001000111110110001001011 $
b01000110101101110110101001110110 %
b10100011110110110101011011000001 &
b01011101001000111110110001001011 )
b01000110101101110110101001110110 *
b10100011110110110101011011000001 +
#101000
b11010100111011010001110110111101 $
b00110111001101100001011000101110 %
b00001100001000110011001111101011 &
b11010100111011010001110110111101 )
b00110111001101100001011000101110 *
b00001100001000110011001111101011 +
#102000
b11000111010100010000101100001010 $
b11100101100001101101111000101000 %
b10101100110101111110100100110010 &
b11000111010100010000101100001010 )
b11100101100001101101111000101000 *
b10101100110101111110100100110010 +
#103000
b01010111110001000011110001000010 $
b01010010011111101101111111011111 %
b10101010010000110001110000100001 &
b01010111110001000011110001000010 )
b01010010011111101101111111011111 *
b10101010010000110001110000100001 +
#104000
b11000000010110101101111011011100 $
b01110111101111010101101101011110 %
b00111000000110000011101000111010 &
b11000000010110101101111011011100 )
b01110111101111010101101101011110 *
b00111000000110000011101000111010 +
#105000
b01100010111101101011000000011010 $
b00000000011000100011011100001010 %
b01100011010110001110011100100100 &
b01100010111101101011000000011010 )
b00000000011000100011011100001010 *
b01100011010110001110011100100100 +
#106000
b11101101100000100010000011001000 $
b00000111011100101010010101010000 %
b11110100111101001100011000011000 &
b11101101100000100010000011001000 )
b00000111011100101010010101010000 *
b11110100111101001100011000011000 +
#107000
b00101110000010010110100011011101 $
b11011000011111010110011000001000 %
b00000110100001101100111011100101 &
b00101110000010010110100011011101 )
b11011000011111010110011000001000 *
b00000110100001101100111011100101 +
#108000
b00111110100101011010010101010110 $
b11110001010010000000100010011110 %
b00101111110111011010110111110100 &
b00111110100101011010010101010110 )
b11110001010010000000100010011110 *
b00101111110111011010110111110100 +
#109000
b10001101010101001000111101011011 $
b11100000100100011001010100100001 %
b01101101111001100010010001111100 &
b10001101010101001000111101011011 )
b11100000100100011001010100100001 *
b01101101111001100010010001111100 +
#110000
b10111010010111000111010100001111 $
b01011110110100100110010111101100 %
b00011001001011101101101011111011 &
b10111010010111000111010100001111 )
b01011110110100100110010111101100 *
b00011001001011101101101011111011 +
#111000
b10111011001110110001100110010010 $
b10101100111010111110101110100110 %
b01101000001001110000010100111000 &
b10111011001110110001100110010010 )
b10101100111010111110101110100110 *
b01101000001001110000010100111000 +
#112000
b01000010110010110101010100111000 $
b00011110001110000111111101101010 %
b01100001000000111101010010100010 &
b01000010110010110101010100111000 )
b00011110001110000111111101101010 *
b01100001000000111101010010100010 +
#113000
b10010000010001100111011000110011 $
b10010010011000000000001001011111 %
b00100010101001100111100010010010 &
b10010000010001100111011000110011 )
b10010010011000000000001001011111 *
b00100010101001100111100010010010 +
#114000
b10000011101001110110101001010110 $
b01000101000010001100010010101010 %
b11001000101100000010111100000000 &
b10000011101001110110101001010110 )
b01000101000010001100010010101010 *
b11001000101100000010111100000000 +
#115000
b11100001100110010010000000001100 $
b01010000111011001001011001111000 %
b00110010100001011011011010000100 &
b11100001100110010010000000001100 )
b01010000111011001001011001111000 *
b00110010100001011011011010000100 +
#116000
b10010011010011000101010011000001 $
b01101011010000001010001100110001 %
b11111110100011001111011111110010 &
b10010011010011000101010011000001 )
b01101011010000001010001100110001 *
b11111110100011001111011111110010 +
#117000
b00110111001010001010111101110011 $
b11001111111010011101110101001000 %
b00000111000100101000110010111011 &
b00110111001010001010111101110011 )
b11001111111010011101110101001000 *
b00000111000100101000110010111011 +
#118000
b00010000000001101011010001001011 $
b11111010100110001001011010101000 %
b00001010100111110100101011110011 &
b00010000000001101011010001001011 )
b11111010100110001001011010101000 *
b00001010100111110100101011110011 +
#119000
b10011001100000111110111100000111 $
b00001000110011000111101001011110 %
b10100010010100000110100101100101 &
b10011001100000111110111100000111 )
b00001000110011000111101001011110 *
b10100010010100000110100101100101 +
#120000
b01011000010101100101001110111000 $
b10011010100110111110010001011011 %
b11110010111100100011100000010011 &
b01011000010101100101001110111000 )
b10011010100110111110010001011011 *
b11110010111100100011100000010011 +
#121000
b01011100001001111010001101010001 $
b11001011010101111011101100010000 %
b00100111011111110101111001100001 &
b01011100001001111010001101010001 )
b11001011010101111011101100010000 *
b00100111011111110101111001100001 +
#122000
b11011111000011001100111100001011 $
b11001001000100010000101010011101 %
b10101000000111011101100110101000 &
b11011111000011001100111100001011 )
b11001001000100010000101010011101 *
b10101000000111011101100110101000 +
#123000
b11000011000110111111011100110100 $
b10100110011111110011110011101011 %
b01101001100110110011010000011111 &
b11000011000110111111011100110100 )
b10100110011111110011110011101011 *
b01101001100110110011010000011111 +
#124000
b10000110011000101010010101000001 $
b00001111000001010100111100010001 %
b10010101011001111111010001010010 &
b10000110011000101010010101000001 )
b00001111000001010100111100010001 *
b10010101011001111111010001010010 +
#125000
b11001010000101101101011000001101 $
b11001011110001111111111110010011 %
b10010101110111101101010110100000 &
b11001010000101101101011000001101 )
b11001011110001111111111110010011 *
b10010101110111101101010110100000 +
#126000
b00100001111100001001110110000110 $
b01001010001001111001011000111000 %
b01101100000110000011001110111110 &
b00100001111100001001110110000110 )
b01001010001001111001011000111000 *
b01101100000110000011001110111110 +
#127000
b00100010101011110000011110100010 $
b00011110000010101001010100001011 %
b01000000101110011001110010101101 &
b00100010101011110000011110100010 )
b00011110000010101001010100001011 *
b01000000101110011001110010101101 +
#128000
b11111110001001001010010000110000 $
b00000101110000100011010101000110 %
b00000011111001101101100101110110 &
b11111110001001001010010000110000 )
b00000101110000100011010101000110 *
b00000011111001101101100101110110 +
#129000
b00110010110111000111111001101010 $
b00110010111100100111111101001000 %
b01100101110011101111110110110010 &
b00110010110111000111111001101010 )
b00110010111100100111111101001000 *
b01100101110011101111110110110010 +
#130000
b10010001100011110001100100001010 $
b01011011010000111101101011111101 %
b11101100110100101111010000000111 &
b10010001100011110001100100001010 )
b01011011010000111101101011111101 *
b11101100110100101111010000000111 +
#131000
b10101111000110000101101001011010 $
b10000111111100000010100100000100 %
b00110111000010001000001101011110 &
b10101111000110000101101001011010 )
b10000111111100000010100100000100 *
b00110111000010001000001101011110 +
#132000
b10101111100001101001011010101101 $
b01000010000001000000111000110101 %
b11110001100010101010010011100010 &
b10101111100001101001011010101101 )
b01000010000001000000111000110101 *
b11110001100010101010010011100010 +
#133000
b11100110000001011100101111010110 $
b01011110110101001101001001011010 %
b01000100110110101001111000110000 &
b11100110000001011100101111010110 )
b01011110110101001101001001011010 *
b01000100110110101001111000110000 +
#134000
b10111100101100100110110000111111 $
b00000010011010011110101100111001 %
b10111111000111000101011101111000 &
b10111100101100100110110000111111 )
b00000010011010011110101100111001 *
b10111111000111000101011101111000 +
#135000
b11000011111001110101000011101110 $
b11101010100101011000001001101101 %
b10101110011111001101001101011011 &
b11000011111001110101000011101110 )
b11101010100101011000001001101101 *
b10101110011111001101001101011011 +
#136000
b10000010000110110111100100010001 $
b00001010010110001111001101110100 %
b10001100011101000110110010000101 &
b10000010000110110111100100010001 )
b00001010010110001111001101110100 *
b10001100011101000110110010000101 +
#137000
b01000101101101010111011111101010 $
b00110000011111100001010001110000 %
b01110110001100111000110001011010 &
b01000101101101010111011111101010 )
b00110000011111100001010001110000 *
b01110110001100111000110001011010 +
#138000
b11110010110000000001110000010111 $
b00010001101011000111100100110010 %
b00000100011011001001010101001001 &
b11110010110000000001110000010111 )
b00010001101011000111100100110010 *
b00000100011011001001010101001001 +
#139000
b10101010111101000111010111000111 $
b11011000000010111011100110101010 %
b10000011000000000010111101110001 &
b10101010111101000111010111000111 )
b11011000000010111011100110101010 *
b10000011000000000010111101110001 +
#140000
b00000100010001101101000000011010 $
b11111101110011100100010111001000 %
b00000010000101010001010111100010 &
b00000100010001101101000000011010 )
b11111101110011100100010111001000 *
b00000010000101010001010111100010 +
#141000
b00010100010011100111110000111101 $
b00011000011101111100000010001110 %
b00101100110001100011110011001011 &
b00010100010011100111110000111101 )
b00011000011101111100000010001110 *
b00101100110001100011110011001011 +
#142000
b00111000100111100111100010101001 $
b10010110100001010100111101100000 %
b11001111001000111100100000001001 &
b00111000100111100111100010101001 )
b10010110100001010100111101100000 *
b11001111001000111100100000001001 +
#143000
b11001000001010110110100010101101 $
b01011101110111001001100101010101 %
b00100110000010000000001000000010 &
b11001000001010110110100010101101 )
b01011101110111001001100101010101 *
b00100110000010000000001000000010 +
#144000
b11000000001110001111101100111100 $
b11010110111000110111011001000101 %
b10010111000111000111000110000001 &
b11000000001110001111101100111100 )
b11010110111000110111011001000101 *
b10010111000111000111000110000001 +
#145000
b11100101111010100101111011111000 $
b00111001110100101101101100001110 %
b00011111101111010011101000000110 &
b11100101111010100101111011111000 )
b00111001110100101101101100001110 *
b00011111101111010011101000000110 +
#146000
b00000110010101000110000001111111 $
b10001010100010010000001011010001 %
b10010000110111010110001101010000 &
b00000110010101000110000001111111 )
b10001010100010010000001011010001 *
b10010000110111010110001101010000 +
#147000
b00110101001101010010100110101010 $
b00001111000010110011101100001010 %
b01000100010000000110010010110100 &
b00110101001101010010100110101010 )
b00001111000010110011101100001010 *
b01000100010000000110010010110100 +
#148000
b11010100010001011000100010000000 $
b11100110010110001101000011110110 %
b10111010100111100101100101110110 &
b11010100010001011000100010000000 )
b11100110010110001101000011110110 *
b10111010100111100101100101110110 +
#149000
b10111110000010101100110001111010 $
b00000110101011001001010101101000 %
b11000100101101110110000111100010 &
b10111110000010101100110001111010 )
b00000110101011001001010101101000 *
b11000100101101110110000111100010 +
#150000
b10001001010111110101000100110000 $
b11010011100000111111011001001100 %
b01011100111000110100011101111100 &
b10001001010111110101000100110000 )
b11010011100000111111011001001100 *
b01011100111000110100011101111100 +
#151000
b11100000010000011011000000100010 $
b01100110111110011000001101100101 %
b01000111001110110011001110000111 &
b11100000010000011011000000100010 )
b01100110111110011000001101100101 *
b01000111001110110011001110000111 +
#152000
b10011100000101100010000110001010 $
b11000101010001111001110001110111 %
b01100001010111011011111000000001 &
b10011100000101100010000110001010 )
b11000101010001111001110001110111 *
b01100001010111011011111000000001 +
