utype/src/signext.sv
// signext.sv 
module signext (
    // IN
    input logic [24:0] raw_src,
    input logic [2:0] imm_source,

    // OUT (immediate)
    output logic [31:0] immediate
);

always_comb begin
    case (imm_source)
        // For I-Types
        3'b000 : immediate = {{20{raw_src[24]}}, raw_src[24:13]};
        // For S-types
        3'b001 : immediate = {{20{raw_src[24]}},raw_src[24:18],raw_src[4:0]};
        // For B-types
        3'b010 : immediate = {{20{raw_src[24]}},raw_src[0],raw_src[23:18],raw_src[4:1],1'b0};
        // For J-types
        3'b011 : immediate = {{12{raw_src[24]}},
                            raw_src[12:5],
                            raw_src[13],
                            raw_src[23:14],
                            1'b0};
        // For U-Types
        3'b100 : immediate = {raw_src[24:5],12'b000000000000};
        default: immediate = 32'b0;
    endcase
end
    
endmodule


// https://fraserinnovations.com/risc-v/risc-v-instruction-set-explanation/
// above link has the best explanations on each type of riscv instructions



// Instruction guide for b type
// Map of index

// raw_src       = [0, 1, 2, 3,  4,  5,  6,  7,  8,  9,  10, 11, 12, 13, 14, 15, 16, 17, 18, 19, 20, 21, 22, 23, 24]
// instruction   = [7, 8, 9, 10, 11, 12, 13, 14, 15, 16, 17, 18, 19, 20, 21, 22, 23, 24, 25, 26, 27, 28, 29, 30, 31]
// 


// Instruction[6:0] = opcode
// Instruction[7] = immediate[11]
// Instruction[11:8] = immediate[4:1]
// Instruction[12:14] = func3
// Instruction[15:19] = RS1
// Instruction[24:20] = RS2
// Instruction[30:25] = immediate[10:5]
// Instruction[31] = immediate[12]

// immediate represenst memory offset, so having immedite[0] = 0, is the only choice.
// The memory is multiples of 2, immediate[0] ensures that the number is always even and mutiple of 2

utype/tb/signExt/dump.vcd
$version Generated by VerilatedVcd $end
$timescale 1ps $end
 $scope module $rootio $end
  $var wire 25 # raw_src [24:0] $end
  $var wire 3 $ imm_source [2:0] $end
  $var wire 32 % immediate [31:0] $end
 $upscope $end
 $scope module signext $end
  $var wire 25 & raw_src [24:0] $end
  $var wire 3 ' imm_source [2:0] $end
  $var wire 32 ( immediate [31:0] $end
 $upscope $end
$enddefinitions $end


#0
b0000000000000000000000000 #
b000 $
b00000000000000000000000000000000 %
b0000000000000000000000000 &
b000 '
b00000000000000000000000000000000 (
#1000
b0000011110111010101010101 #
b00000000000000000000000001111011 %
b0000011110111010101010101 &
b00000000000000000000000001111011 (
#3000
b1111110101101010101010101 #
b11111111111111111111111111010110 %
b1111110101101010101010101 &
b11111111111111111111111111010110 (
#104001
b0010000000000000000011110 #
b001 $
b00000000000000000000001000011110 %
b0010000000000000000011110 &
b001 '
b00000000000000000000001000011110 (
#106001
b1000111000000000000010100 #
b11111111111111111111100011110100 %
b1000111000000000000010100 &
b11111111111111111111100011110100 (
#207001
b0001111000000000000010111 #
b00000000000000000000000111110111 %
b0001111000000000000010111 &
b00000000000000000000000111110111 (
#209001
b1100110000000000000001101 #
b11111111111111111111110011001101 %
b1100110000000000000001101 &
b11111111111111111111110011001101 (
#310001
b0010100000000000000011111 #
b00000000000000000000001010011111 %
b0010100000000000000011111 &
b00000000000000000000001010011111 (
#312001
b1010011000000000000000101 #
b11111111111111111111101001100101 %
b1010011000000000000000101 &
b11111111111111111111101001100101 (
#413001
b0000001000000000000011000 #
b00000000000000000000000000111000 %
b0000001000000000000011000 &
b00000000000000000000000000111000 (
#415001
b1110000000000000000011101 #
b11111111111111111111111000011101 %
b1110000000000000000011101 &
b11111111111111111111111000011101 (
#516001
b0000000000000000000000001 #
b00000000000000000000000000000001 %
b0000000000000000000000001 &
b00000000000000000000000000000001 (
#518001
b1001011000000000000001101 #
b11111111111111111111100101101101 %
b1001011000000000000001101 &
b11111111111111111111100101101101 (
#619001
b0010001000000000000000110 #
b00000000000000000000001000100110 %
b0010001000000000000000110 &
b00000000000000000000001000100110 (
#621001
b1000011000000000000011110 #
b11111111111111111111100001111110 %
b1000011000000000000011110 &
b11111111111111111111100001111110 (
#722001
b0010100000000000000001000 #
b00000000000000000000001010001000 %
b0010100000000000000001000 &
b00000000000000000000001010001000 (
#724001
b1010010000000000000001001 #
b11111111111111111111101001001001 %
b1010010000000000000001001 &
b11111111111111111111101001001001 (
#825001
b0011111000000000000010111 #
b00000000000000000000001111110111 %
b0011111000000000000010111 &
b00000000000000000000001111110111 (
#827001
b1111010000000000000000000 #
b11111111111111111111111101000000 %
b1111010000000000000000000 &
b11111111111111111111111101000000 (
#928001
b0010100000000000000011101 #
b00000000000000000000001010011101 %
b0010100000000000000011101 &
b00000000000000000000001010011101 (
#930001
b1101010000000000000010111 #
b11111111111111111111110101010111 %
b1101010000000000000010111 &
b11111111111111111111110101010111 (
#1031001
b0010111000000000000011010 #
b00000000000000000000001011111010 %
b0010111000000000000011010 &
b00000000000000000000001011111010 (
#1033001
b1000010000000000000010111 #
b11111111111111111111100001010111 %
b1000010000000000000010111 &
b11111111111111111111100001010111 (
#1134001
b0010000000000000000011011 #
b00000000000000000000001000011011 %
b0010000000000000000011011 &
b00000000000000000000001000011011 (
#1136001
b1101100000000000000010100 #
b11111111111111111111110110010100 %
b1101100000000000000010100 &
b11111111111111111111110110010100 (
#1237001
b0000010000000000000000011 #
b00000000000000000000000001000011 %
b0000010000000000000000011 &
b00000000000000000000000001000011 (
#1239001
b1111000000000000000001000 #
b11111111111111111111111100001000 %
b1111000000000000000001000 &
b11111111111111111111111100001000 (
#1340001
b0000100000000000000010010 #
b00000000000000000000000010010010 %
b0000100000000000000010010 &
b00000000000000000000000010010010 (
#1342001
b1001001000000000000010000 #
b11111111111111111111100100110000 %
b1001001000000000000010000 &
b11111111111111111111100100110000 (
#1443001
b0010110000000000000001000 #
b00000000000000000000001011001000 %
b0010110000000000000001000 &
b00000000000000000000001011001000 (
#1445001
b1101011000000000000011101 #
b11111111111111111111110101111101 %
b1101011000000000000011101 &
b11111111111111111111110101111101 (
#1546001
b0001001000000000000000000 #
b00000000000000000000000100100000 %
b0001001000000000000000000 &
b00000000000000000000000100100000 (
#1548001
b1010001000000000000011001 #
b11111111111111111111101000111001 %
b1010001000000000000011001 &
b11111111111111111111101000111001 (
#1649001
b0010100000000000000011000 #
b00000000000000000000001010011000 %
b0010100000000000000011000 &
b00000000000000000000001010011000 (
#1651001
b1011101000000000000001101 #
b11111111111111111111101110101101 %
b1011101000000000000001101 &
b11111111111111111111101110101101 (
#1752001
b0011000000000000000001101 #
b00000000000000000000001100001101 %
b0011000000000000000001101 &
b00000000000000000000001100001101 (
#1754001
b1011100000000000000001010 #
b11111111111111111111101110001010 %
b1011100000000000000001010 &
b11111111111111111111101110001010 (
#1855001
b0000100000000000000011001 #
b00000000000000000000000010011001 %
b0000100000000000000011001 &
b00000000000000000000000010011001 (
#1857001
b1101011000000000000001011 #
b11111111111111111111110101101011 %
b1101011000000000000001011 &
b11111111111111111111110101101011 (
#1958001
b0010110000000000000001001 #
b00000000000000000000001011001001 %
b0010110000000000000001001 &
b00000000000000000000001011001001 (
#1960001
b1111011000000000000011010 #
b11111111111111111111111101111010 %
b1111011000000000000011010 &
b11111111111111111111111101111010 (
#2061001
b0001111000000000000000110 #
b00000000000000000000000111100110 %
b0001111000000000000000110 &
b00000000000000000000000111100110 (
#2063001
b1111000000000000000001011 #
b11111111111111111111111100001011 %
b1111000000000000000001011 &
b11111111111111111111111100001011 (
#2164001
b0000100000000000000000010 #
b00000000000000000000000010000010 %
b0000100000000000000000010 &
b00000000000000000000000010000010 (
#2166001
b1110000000000000000011111 #
b11111111111111111111111000011111 %
b1110000000000000000011111 &
b11111111111111111111111000011111 (
#2267001
b0000000000000000000000010 #
b00000000000000000000000000000010 %
b0000000000000000000000010 &
b00000000000000000000000000000010 (
#2269001
b1111001000000000000010001 #
b11111111111111111111111100110001 %
b1111001000000000000010001 &
b11111111111111111111111100110001 (
#2370001
b0010101000000000000010101 #
b00000000000000000000001010110101 %
b0010101000000000000010101 &
b00000000000000000000001010110101 (
#2372001
b1000111000000000000011011 #
b11111111111111111111100011111011 %
b1000111000000000000011011 &
b11111111111111111111100011111011 (
#2473001
b0000101000000000000000111 #
b00000000000000000000000010100111 %
b0000101000000000000000111 &
b00000000000000000000000010100111 (
#2475001
b1110011000000000000000001 #
b11111111111111111111111001100001 %
b1110011000000000000000001 &
b11111111111111111111111001100001 (
#2576001
b0000110000000000000010011 #
b00000000000000000000000011010011 %
b0000110000000000000010011 &
b00000000000000000000000011010011 (
#2578001
b1011110000000000000000001 #
b11111111111111111111101111000001 %
b1011110000000000000000001 &
b11111111111111111111101111000001 (
#2679001
b0010001000000000000010101 #
b00000000000000000000001000110101 %
b0010001000000000000010101 &
b00000000000000000000001000110101 (
#2681001
b1001101000000000000011001 #
b11111111111111111111100110111001 %
b1001101000000000000011001 &
b11111111111111111111100110111001 (
#2782001
b0011100000000000000010110 #
b00000000000000000000001110010110 %
b0011100000000000000010110 &
b00000000000000000000001110010110 (
#2784001
b1101000000000000000000010 #
b11111111111111111111110100000010 %
b1101000000000000000000010 &
b11111111111111111111110100000010 (
#2885001
b0011101000000000000010001 #
b00000000000000000000001110110001 %
b0011101000000000000010001 &
b00000000000000000000001110110001 (
#2887001
b1000010000000000000001001 #
b11111111111111111111100001001001 %
b1000010000000000000001001 &
b11111111111111111111100001001001 (
#2988001
b0000010000000000000000000 #
b00000000000000000000000001000000 %
b0000010000000000000000000 &
b00000000000000000000000001000000 (
#2990001
b1000010000000000000001010 #
b11111111111111111111100001001010 %
b1000010000000000000001010 &
b11111111111111111111100001001010 (
#3091001
b0010010000000000000000010 #
b00000000000000000000001001000010 %
b0010010000000000000000010 &
b00000000000000000000001001000010 (
#3093001
b1100100000000000000001001 #
b11111111111111111111110010001001 %
b1100100000000000000001001 &
b11111111111111111111110010001001 (
#3194001
b0010000000000000000010111 #
b00000000000000000000001000010111 %
b0010000000000000000010111 &
b00000000000000000000001000010111 (
#3196001
b1011100000000000000000111 #
b11111111111111111111101110000111 %
b1011100000000000000000111 &
b11111111111111111111101110000111 (
#3297001
b0011110000000000000011100 #
b00000000000000000000001111011100 %
b0011110000000000000011100 &
b00000000000000000000001111011100 (
#3299001
b1110010000000000000011100 #
b11111111111111111111111001011100 %
b1110010000000000000011100 &
b11111111111111111111111001011100 (
#3400001
b0001110000000000000010111 #
b00000000000000000000000111010111 %
b0001110000000000000010111 &
b00000000000000000000000111010111 (
#3402001
b1100010000000000000001101 #
b11111111111111111111110001001101 %
b1100010000000000000001101 &
b11111111111111111111110001001101 (
#3503001
b0010010000000000000011010 #
b00000000000000000000001001011010 %
b0010010000000000000011010 &
b00000000000000000000001001011010 (
#3505001
b1010110000000000000011001 #
b11111111111111111111101011011001 %
b1010110000000000000011001 &
b11111111111111111111101011011001 (
#3606001
b0001010000000000000010110 #
b00000000000000000000000101010110 %
b0001010000000000000010110 &
b00000000000000000000000101010110 (
#3608001
b1110001000000000000011011 #
b11111111111111111111111000111011 %
b1110001000000000000011011 &
b11111111111111111111111000111011 (
#3709001
b0011000000000000000001111 #
b00000000000000000000001100001111 %
b0011000000000000000001111 &
b00000000000000000000001100001111 (
#3711001
b1001001000000000000000100 #
b11111111111111111111100100100100 %
b1001001000000000000000100 &
b11111111111111111111100100100100 (
#3812001
b0010101000000000000010110 #
b00000000000000000000001010110110 %
b0010101000000000000010110 &
b00000000000000000000001010110110 (
#3814001
b1001101000000000000011000 #
b11111111111111111111100110111000 %
b1001101000000000000011000 &
b11111111111111111111100110111000 (
#3915001
b0000111000000000000010010 #
b00000000000000000000000011110010 %
b0000111000000000000010010 &
b00000000000000000000000011110010 (
#3917001
b1010101000000000000011100 #
b11111111111111111111101010111100 %
b1010101000000000000011100 &
b11111111111111111111101010111100 (
#4018001
b0001110000000000000001001 #
b00000000000000000000000111001001 %
b0001110000000000000001001 &
b00000000000000000000000111001001 (
#4020001
b1011101000000000000011000 #
b11111111111111111111101110111000 %
b1011101000000000000011000 &
b11111111111111111111101110111000 (
#4121001
b0011011000000000000010001 #
b00000000000000000000001101110001 %
b0011011000000000000010001 &
b00000000000000000000001101110001 (
#4123001
b1001010000000000000010010 #
b11111111111111111111100101010010 %
b1001010000000000000010010 &
b11111111111111111111100101010010 (
#4224001
b0001110000000000000001011 #
b00000000000000000000000111001011 %
b0001110000000000000001011 &
b00000000000000000000000111001011 (
#4226001
b1001010000000000000011100 #
b11111111111111111111100101011100 %
b1001010000000000000011100 &
b11111111111111111111100101011100 (
#4327001
b0001011000000000000001110 #
b00000000000000000000000101101110 %
b0001011000000000000001110 &
b00000000000000000000000101101110 (
#4329001
b1001011000000000000011100 #
b11111111111111111111100101111100 %
b1001011000000000000011100 &
b11111111111111111111100101111100 (
#4430001
b0011001000000000000010001 #
b00000000000000000000001100110001 %
b0011001000000000000010001 &
b00000000000000000000001100110001 (
#4432001
b1010110000000000000011010 #
b11111111111111111111101011011010 %
b1010110000000000000011010 &
b11111111111111111111101011011010 (
#4533001
b0001101000000000000011010 #
b00000000000000000000000110111010 %
b0001101000000000000011010 &
b00000000000000000000000110111010 (
#4535001
b1001000000000000000010011 #
b11111111111111111111100100010011 %
b1001000000000000000010011 &
b11111111111111111111100100010011 (
#4636001
b0000011000000000000011101 #
b00000000000000000000000001111101 %
b0000011000000000000011101 &
b00000000000000000000000001111101 (
#4638001
b1010010000000000000011011 #
b11111111111111111111101001011011 %
b1010010000000000000011011 &
b11111111111111111111101001011011 (
#4739001
b0000100000000000000011101 #
b00000000000000000000000010011101 %
b0000100000000000000011101 &
b00000000000000000000000010011101 (
#4741001
b1110001000000000000001101 #
b11111111111111111111111000101101 %
b1110001000000000000001101 &
b11111111111111111111111000101101 (
#4842001
b0000001000000000000000101 #
b00000000000000000000000000100101 %
b0000001000000000000000101 &
b00000000000000000000000000100101 (
#4844001
b1011001000000000000000011 #
b11111111111111111111101100100011 %
b1011001000000000000000011 &
b11111111111111111111101100100011 (
#4945001
b0000011000000000000010001 #
b00000000000000000000000001110001 %
b0000011000000000000010001 &
b00000000000000000000000001110001 (
#4947001
b1010001000000000000011000 #
b11111111111111111111101000111000 %
b1010001000000000000011000 &
b11111111111111111111101000111000 (
#5048001
b0011110000000000000010001 #
b00000000000000000000001111010001 %
b0011110000000000000010001 &
b00000000000000000000001111010001 (
#5050001
b1110110000000000000000000 #
b11111111111111111111111011000000 %
b1110110000000000000000000 &
b11111111111111111111111011000000 (
#5151001
b0000000000000000000001110 #
b00000000000000000000000000001110 %
b0000000000000000000001110 &
b00000000000000000000000000001110 (
#5153001
b1111010000000000000000011 #
b11111111111111111111111101000011 %
b1111010000000000000000011 &
b11111111111111111111111101000011 (
#5254001
b0001010000000000000011011 #
b00000000000000000000000101011011 %
b0001010000000000000011011 &
b00000000000000000000000101011011 (
#5256001
b1101111000000000000000100 #
b11111111111111111111110111100100 %
b1101111000000000000000100 &
b11111111111111111111110111100100 (
#5357001
b0000100000000000000010001 #
b00000000000000000000000010010001 %
b0000100000000000000010001 &
b00000000000000000000000010010001 (
#5359001
b1001010000000000000000111 #
b11111111111111111111100101000111 %
b1001010000000000000000111 &
b11111111111111111111100101000111 (
#5460001
b0001111000000000000010010 #
b00000000000000000000000111110010 %
b0001111000000000000010010 &
b00000000000000000000000111110010 (
#5462001
b1101010000000000000011011 #
b11111111111111111111110101011011 %
b1101010000000000000011011 &
b11111111111111111111110101011011 (
#5563001
b0000100000000000000001011 #
b00000000000000000000000010001011 %
b0000100000000000000001011 &
b00000000000000000000000010001011 (
#5565001
b1010111000000000000011100 #
b11111111111111111111101011111100 %
b1010111000000000000011100 &
b11111111111111111111101011111100 (
#5666001
b0001010000000000000010001 #
b00000000000000000000000101010001 %
b0001010000000000000010001 &
b00000000000000000000000101010001 (
#5668001
b1001100000000000000000110 #
b11111111111111111111100110000110 %
b1001100000000000000000110 &
b11111111111111111111100110000110 (
#5769001
b0010101000000000000001101 #
b00000000000000000000001010101101 %
b0010101000000000000001101 &
b00000000000000000000001010101101 (
#5771001
b1001011000000000000010111 #
b11111111111111111111100101110111 %
b1001011000000000000010111 &
b11111111111111111111100101110111 (
#5872001
b0000001000000000000000000 #
b00000000000000000000000000100000 %
b0000001000000000000000000 &
b00000000000000000000000000100000 (
#5874001
b1000100000000000000000001 #
b11111111111111111111100010000001 %
b1000100000000000000000001 &
b11111111111111111111100010000001 (
#5975001
b0010101000000000000000111 #
b00000000000000000000001010100111 %
b0010101000000000000000111 &
b00000000000000000000001010100111 (
#5977001
b1001111000000000000010110 #
b11111111111111111111100111110110 %
b1001111000000000000010110 &
b11111111111111111111100111110110 (
#6078001
b0000001000000000000001111 #
b00000000000000000000000000101111 %
b0000001000000000000001111 &
b00000000000000000000000000101111 (
#6080001
b1111000000000000000001011 #
b11111111111111111111111100001011 %
b1111000000000000000001011 &
b11111111111111111111111100001011 (
#6181001
b0000000000000000000010100 #
b00000000000000000000000000010100 %
b0000000000000000000010100 &
b00000000000000000000000000010100 (
#6183001
b1010000000000000000001011 #
b11111111111111111111101000001011 %
b1010000000000000000001011 &
b11111111111111111111101000001011 (
#6284001
b0001110000000000000000111 #
b00000000000000000000000111000111 %
b0001110000000000000000111 &
b00000000000000000000000111000111 (
#6286001
b1111100000000000000001100 #
b11111111111111111111111110001100 %
b1111100000000000000001100 &
b11111111111111111111111110001100 (
#6387001
b0001010000000000000001011 #
b00000000000000000000000101001011 %
b0001010000000000000001011 &
b00000000000000000000000101001011 (
#6389001
b1011000000000000000001110 #
b11111111111111111111101100001110 %
b1011000000000000000001110 &
b11111111111111111111101100001110 (
#6490001
b0010001000000000000001100 #
b00000000000000000000001000101100 %
b0010001000000000000001100 &
b00000000000000000000001000101100 (
#6492001
b1011111000000000000011000 #
b11111111111111111111101111111000 %
b1011111000000000000011000 &
b11111111111111111111101111111000 (
#6593001
b0011000000000000000001110 #
b00000000000000000000001100001110 %
b0011000000000000000001110 &
b00000000000000000000001100001110 (
#6595001
b1000110000000000000000000 #
b11111111111111111111100011000000 %
b1000110000000000000000000 &
b11111111111111111111100011000000 (
#6696001
b0000110000000000000010110 #
b00000000000000000000000011010110 %
b0000110000000000000010110 &
b00000000000000000000000011010110 (
#6698001
b1101010000000000000000111 #
b11111111111111111111110101000111 %
b1101010000000000000000111 &
b11111111111111111111110101000111 (
#6799001
b0011001000000000000000011 #
b00000000000000000000001100100011 %
b0011001000000000000000011 &
b00000000000000000000001100100011 (
#6801001
b1010100000000000000011010 #
b11111111111111111111101010011010 %
b1010100000000000000011010 &
b11111111111111111111101010011010 (
#6902001
b0000111000000000000000011 #
b00000000000000000000000011100011 %
b0000111000000000000000011 &
b00000000000000000000000011100011 (
#6904001
b1011101000000000000011001 #
b11111111111111111111101110111001 %
b1011101000000000000011001 &
b11111111111111111111101110111001 (
#7005001
b0001101000000000000011110 #
b00000000000000000000000110111110 %
b0001101000000000000011110 &
b00000000000000000000000110111110 (
#7007001
b1001110000000000000000011 #
b11111111111111111111100111000011 %
b1001110000000000000000011 &
b11111111111111111111100111000011 (
#7108001
b0010000000000000000001111 #
b00000000000000000000001000001111 %
b0010000000000000000001111 &
b00000000000000000000001000001111 (
#7110001
b1010100000000000000000111 #
b11111111111111111111101010000111 %
b1010100000000000000000111 &
b11111111111111111111101010000111 (
#7211001
b0000001000000000000000010 #
b00000000000000000000000000100010 %
b0000001000000000000000010 &
b00000000000000000000000000100010 (
#7213001
b1000111000000000000000001 #
b11111111111111111111100011100001 %
b1000111000000000000000001 &
b11111111111111111111100011100001 (
#7314001
b0000010000000000000010110 #
b00000000000000000000000001010110 %
b0000010000000000000010110 &
b00000000000000000000000001010110 (
#7316001
b1010001000000000000001110 #
b11111111111111111111101000101110 %
b1010001000000000000001110 &
b11111111111111111111101000101110 (
#7417001
b0000010000000000000000011 #
b00000000000000000000000001000011 %
b0000010000000000000000011 &
b00000000000000000000000001000011 (
#7419001
b1010100000000000000000111 #
b11111111111111111111101010000111 %
b1010100000000000000000111 &
b11111111111111111111101010000111 (
#7520001
b0001111000000000000001111 #
b00000000000000000000000111101111 %
b0001111000000000000001111 &
b00000000000000000000000111101111 (
#7522001
b1100101000000000000001101 #
b11111111111111111111110010101101 %
b1100101000000000000001101 &
b11111111111111111111110010101101 (
#7623001
b0010111000000000000000111 #
b00000000000000000000001011100111 %
b0010111000000000000000111 &
b00000000000000000000001011100111 (
#7625001
b1100000000000000000000110 #
b11111111111111111111110000000110 %
b1100000000000000000000110 &
b11111111111111111111110000000110 (
#7726001
b0001001000000000000001100 #
b00000000000000000000000100101100 %
b0001001000000000000001100 &
b00000000000000000000000100101100 (
#7728001
b1101111000000000000010101 #
b11111111111111111111110111110101 %
b1101111000000000000010101 &
b11111111111111111111110111110101 (
#7829001
b0000101000000000000000110 #
b00000000000000000000000010100110 %
b0000101000000000000000110 &
b00000000000000000000000010100110 (
#7831001
b1001100000000000000000100 #
b11111111111111111111100110000100 %
b1001100000000000000000100 &
b11111111111111111111100110000100 (
#7932001
b0000000000000000000001010 #
b00000000000000000000000000001010 %
b0000000000000000000001010 &
b00000000000000000000000000001010 (
#7934001
b1100010000000000000000111 #
b11111111111111111111110001000111 %
b1100010000000000000000111 &
b11111111111111111111110001000111 (
#8035001
b0010111000000000000010001 #
b00000000000000000000001011110001 %
b0010111000000000000010001 &
b00000000000000000000001011110001 (
#8037001
b1100011000000000000011011 #
b11111111111111111111110001111011 %
b1100011000000000000011011 &
b11111111111111111111110001111011 (
#8138001
b0001011000000000000011111 #
b00000000000000000000000101111111 %
b0001011000000000000011111 &
b00000000000000000000000101111111 (
#8140001
b1111111000000000000010111 #
b11111111111111111111111111110111 %
b1111111000000000000010111 &
b11111111111111111111111111110111 (
#8241001
b0011011000000000000000111 #
b00000000000000000000001101100111 %
b0011011000000000000000111 &
b00000000000000000000001101100111 (
#8243001
b1111111000000000000001000 #
b11111111111111111111111111101000 %
b1111111000000000000001000 &
b11111111111111111111111111101000 (
#8344001
b0001000000000000000000001 #
b00000000000000000000000100000001 %
b0001000000000000000000001 &
b00000000000000000000000100000001 (
#8346001
b1110100000000000000010010 #
b11111111111111111111111010010010 %
b1110100000000000000010010 &
b11111111111111111111111010010010 (
#8447001
b0000010000000000000000010 #
b00000000000000000000000001000010 %
b0000010000000000000000010 &
b00000000000000000000000001000010 (
#8449001
b1100010000000000000010111 #
b11111111111111111111110001010111 %
b1100010000000000000010111 &
b11111111111111111111110001010111 (
#8550001
b0001111000000000000000001 #
b00000000000000000000000111100001 %
b0001111000000000000000001 &
b00000000000000000000000111100001 (
#8552001
b1010110000000000000011101 #
b11111111111111111111101011011101 %
b1010110000000000000011101 &
b11111111111111111111101011011101 (
#8653001
b0000100000000000000010001 #
b00000000000000000000000010010001 %
b0000100000000000000010001 &
b00000000000000000000000010010001 (
#8655001
b1101001000000000000011100 #
b11111111111111111111110100111100 %
b1101001000000000000011100 &
b11111111111111111111110100111100 (
#8756001
b0001011000000000000011000 #
b00000000000000000000000101111000 %
b0001011000000000000011000 &
b00000000000000000000000101111000 (
#8758001
b1110011000000000000001001 #
b11111111111111111111111001101001 %
b1110011000000000000001001 &
b11111111111111111111111001101001 (
#8859001
b0011111000000000000000100 #
b00000000000000000000001111100100 %
b0011111000000000000000100 &
b00000000000000000000001111100100 (
#8861001
b1101100000000000000011111 #
b11111111111111111111110110011111 %
b1101100000000000000011111 &
b11111111111111111111110110011111 (
#8962001
b0001101000000000000001000 #
b00000000000000000000000110101000 %
b0001101000000000000001000 &
b00000000000000000000000110101000 (
#8964001
b1000110000000000000000101 #
b11111111111111111111100011000101 %
b1000110000000000000000101 &
b11111111111111111111100011000101 (
#9065001
b0001000000000000000011101 #
b00000000000000000000000100011101 %
b0001000000000000000011101 &
b00000000000000000000000100011101 (
#9067001
b1000011000000000000001011 #
b11111111111111111111100001101011 %
b1000011000000000000001011 &
b11111111111111111111100001101011 (
#9168001
b0001101000000000000000110 #
b00000000000000000000000110100110 %
b0001101000000000000000110 &
b00000000000000000000000110100110 (
#9170001
b1110100000000000000001010 #
b11111111111111111111111010001010 %
b1110100000000000000001010 &
b11111111111111111111111010001010 (
#9271001
b0011111000000000000010111 #
b00000000000000000000001111110111 %
b0011111000000000000010111 &
b00000000000000000000001111110111 (
#9273001
b1000010000000000000010001 #
b11111111111111111111100001010001 %
b1000010000000000000010001 &
b11111111111111111111100001010001 (
#9374001
b0010111000000000000011010 #
b00000000000000000000001011111010 %
b0010111000000000000011010 &
b00000000000000000000001011111010 (
#9376001
b1001000000000000000001000 #
b11111111111111111111100100001000 %
b1001000000000000000001000 &
b11111111111111111111100100001000 (
#9477001
b0001101000000000000000000 #
b00000000000000000000000110100000 %
b0001101000000000000000000 &
b00000000000000000000000110100000 (
#9479001
b1011110000000000000001000 #
b11111111111111111111101111001000 %
b1011110000000000000001000 &
b11111111111111111111101111001000 (
#9580001
b0010101000000000000000001 #
b00000000000000000000001010100001 %
b0010101000000000000000001 &
b00000000000000000000001010100001 (
#9582001
b1110001000000000000011001 #
b11111111111111111111111000111001 %
b1110001000000000000011001 &
b11111111111111111111111000111001 (
#9683001
b0000011000000000000001011 #
b00000000000000000000000001101011 %
b0000011000000000000001011 &
b00000000000000000000000001101011 (
#9685001
b1101001000000000000010111 #
b11111111111111111111110100110111 %
b1101001000000000000010111 &
b11111111111111111111110100110111 (
#9786001
b0011101000000000000011110 #
b00000000000000000000001110111110 %
b0011101000000000000011110 &
b00000000000000000000001110111110 (
#9788001
b1110011000000000000001101 #
b11111111111111111111111001101101 %
b1110011000000000000001101 &
b11111111111111111111111001101101 (
#9889001
b0011000000000000000001000 #
b00000000000000000000001100001000 %
b0011000000000000000001000 &
b00000000000000000000001100001000 (
#9891001
b1000011000000000000010001 #
b11111111111111111111100001110001 %
b1000011000000000000010001 &
b11111111111111111111100001110001 (
#9992001
b0011011000000000000000001 #
b00000000000000000000001101100001 %
b0011011000000000000000001 &
b00000000000000000000001101100001 (
#9994001
b1010111000000000000010010 #
b11111111111111111111101011110010 %
b1010111000000000000010010 &
b11111111111111111111101011110010 (
#10095001
b0011001000000000000011011 #
b00000000000000000000001100111011 %
b0011001000000000000011011 &
b00000000000000000000001100111011 (
#10097001
b1110010000000000000000110 #
b11111111111111111111111001000110 %
b1110010000000000000000110 &
b11111111111111111111111001000110 (
#10198001
b0001101000000000000000001 #
b00000000000000000000000110100001 %
b0001101000000000000000001 &
b00000000000000000000000110100001 (
#10200001
b1111011000000000000011011 #
b11111111111111111111111101111011 %
b1111011000000000000011011 &
b11111111111111111111111101111011 (
#10301001
b0011100000000000000010101 #
b00000000000000000000001110010101 %
b0011100000000000000010101 &
b00000000000000000000001110010101 (
#10303001
b1011111000000000000001110 #
b11111111111111111111101111101110 %
b1011111000000000000001110 &
b11111111111111111111101111101110 (
#10405002
b0110000000000000000010010 #
b010 $
b00000000000000000000011000010010 %
b0110000000000000000010010 &
b010 '
b00000000000000000000011000010010 (
#10507002
b1000000000000000000010111 #
b11111111111111111111100000010110 %
b1000000000000000000010111 &
b11111111111111111111100000010110 (
#10609002
b0101111000000000000001101 #
b00000000000000000000110111101100 %
b0101111000000000000001101 &
b00000000000000000000110111101100 (
#10711002
b1100101000000000000001100 #
b11111111111111111111010010101100 %
b1100101000000000000001100 &
b11111111111111111111010010101100 (
#10813002
b0110100000000000000011001 #
b00000000000000000000111010011000 %
b0110100000000000000011001 &
b00000000000000000000111010011000 (
#10915002
b1110000000000000000010110 #
b11111111111111111111011000010110 %
b1110000000000000000010110 &
b11111111111111111111011000010110 (
#11017002
b0100011000000000000010010 #
b00000000000000000000010001110010 %
b0100011000000000000010010 &
b00000000000000000000010001110010 (
#11119002
b1101000000000000000000011 #
b11111111111111111111110100000010 %
b1101000000000000000000011 &
b11111111111111111111110100000010 (
#11221002
b0111001000000000000010101 #
b00000000000000000000111100110100 %
b0111001000000000000010101 &
b00000000000000000000111100110100 (
#11323002
b1111000000000000000001100 #
b11111111111111111111011100001100 %
b1111000000000000000001100 &
b11111111111111111111011100001100 (
#11425002
b0000011000000000000011101 #
b00000000000000000000100001111100 %
b0000011000000000000011101 &
b00000000000000000000100001111100 (
#11527002
b1011000000000000000010100 #
b11111111111111111111001100010100 %
b1011000000000000000010100 &
b11111111111111111111001100010100 (
#11629002
b0001000000000000000010100 #
b00000000000000000000000100010100 %
b0001000000000000000010100 &
b00000000000000000000000100010100 (
#11731002
b1001111000000000000001011 #
b11111111111111111111100111101010 %
b1001111000000000000001011 &
b11111111111111111111100111101010 (
#11833002
b0001100000000000000000101 #
b00000000000000000000100110000100 %
b0001100000000000000000101 &
b00000000000000000000100110000100 (
#11935002
b1111001000000000000010000 #
b11111111111111111111011100110000 %
b1111001000000000000010000 &
b11111111111111111111011100110000 (
#12037002
b0011101000000000000000111 #
b00000000000000000000101110100110 %
b0011101000000000000000111 &
b00000000000000000000101110100110 (
#12139002
b1110000000000000000011010 #
b11111111111111111111011000011010 %
b1110000000000000000011010 &
b11111111111111111111011000011010 (
#12241002
b0000101000000000000010001 #
b00000000000000000000100010110000 %
b0000101000000000000010001 &
b00000000000000000000100010110000 (
#12343002
b1010100000000000000010011 #
b11111111111111111111101010010010 %
b1010100000000000000010011 &
b11111111111111111111101010010010 (
#12445002
b0101100000000000000011100 #
b00000000000000000000010110011100 %
b0101100000000000000011100 &
b00000000000000000000010110011100 (
#12547002
b1101010000000000000011011 #
b11111111111111111111110101011010 %
b1101010000000000000011011 &
b11111111111111111111110101011010 (
#12649002
b0101101000000000000000011 #
b00000000000000000000110110100010 %
b0101101000000000000000011 &
b00000000000000000000110110100010 (
#12751002
b1001110000000000000011001 #
b11111111111111111111100111011000 %
b1001110000000000000011001 &
b11111111111111111111100111011000 (
#12853002
b0000100000000000000000011 #
b00000000000000000000100010000010 %
b0000100000000000000000011 &
b00000000000000000000100010000010 (
