Rtype_and_or/src/alu.sv
// alu.sv
module alu (
    // IN
    input logic [2:0] alu_control,
    input logic [31:0] src1,
    input logic [31:0] src2,
    // OUT
    output logic [31:0] alu_result,
    output logic zero
);

always_comb begin
    case (alu_control)
    	// ADD +
        3'b000 : alu_result = src1 + src2;
	// AND &
	3'b010 : alu_result = src1 & src2;
	// OR |
	3'b011 : alu_result = src1 | src2;
        default: alu_result = 32'b0;
    endcase
end

assign zero = alu_result == 32'b0;
    
endmodule

Rtype_and_or/tb/alu/dump.vcd
$version Generated by VerilatedVcd $end
$timescale 1ps $end
 $scope module $rootio $end
  $var wire 3 # alu_control [2:0] $end
  $var wire 32 $ src1 [31:0] $end
  $var wire 32 % src2 [31:0] $end
  $var wire 32 & alu_result [31:0] $end
  $var wire 1 ' zero $end
 $upscope $end
 $scope module alu $end
  $var wire 3 ( alu_control [2:0] $end
  $var wire 32 ) src1 [31:0] $end
  $var wire 32 * src2 [31:0] $end
  $var wire 32 + alu_result [31:0] $end
  $var wire 1 , zero $end
 $upscope $end
$enddefinitions $end


#0
b000 #
b00000000000000000000000000000000 $
b00000000000000000000000000000000 %
b00000000000000000000000000000000 &
1'
b000 (
b00000000000000000000000000000000 )
b00000000000000000000000000000000 *
b00000000000000000000000000000000 +
1,
#1000
b10110111001110011011111111110100 $
b10011100001011001010100010110011 %
b01010011011001100110100010100111 &
0'
b10110111001110011011111111110100 )
b10011100001011001010100010110011 *
b01010011011001100110100010100111 +
0,
#2000
b10100011001101111011100100110101 $
b11010110100011110111101000001010 %
b01111001110001110011001100111111 &
b10100011001101111011100100110101 )
b11010110100011110111101000001010 *
b01111001110001110011001100111111 +
#3000
b10101010111001111111110011111101 $
b01000100100011001001101101001011 %
b11101111011101001001100001001000 &
b10101010111001111111110011111101 )
b01000100100011001001101101001011 *
b11101111011101001001100001001000 +
#4000
b11111001011010110011000010011110 $
b01000110000011000000100001001011 %
b00111111011101110011100011101001 &
b11111001011010110011000010011110 )
b01000110000011000000100001001011 *
b00111111011101110011100011101001 +
#5000
b10000010100101001011111010001100 $
b10100111001000101000110100101001 %
b00101001101101110100101110110101 &
b10000010100101001011111010001100 )
b10100111001000101000110100101001 *
b00101001101101110100101110110101 +
#6000
b00100000011001101001110011100010 $
b11111111000000000101101001011100 %
b00011111011001101111011100111110 &
b00100000011001101001110011100010 )
b11111111000000000101101001011100 *
b00011111011001101111011100111110 +
#7000
b11100101111001010000101011100111 $
b11001100110011000011111101001011 %
b10110010101100010100101000110010 &
b11100101111001010000101011100111 )
b11001100110011000011111101001011 *
b10110010101100010100101000110010 +
#8000
b01101000001011100011110001101010 $
b00111111111100001101100010001000 %
b10101000000111110001010011110010 &
b01101000001011100011110001101010 )
b00111111111100001101100010001000 *
b10101000000111110001010011110010 +
#9000
b01100111001110000000100111110100 $
b10011111111111110010110110101011 %
b00000111001101110011011110011111 &
b01100111001110000000100111110100 )
b10011111111111110010110110101011 *
b00000111001101110011011110011111 +
#10000
b00100111010111000101100010110001 $
b11010011110001111010101100111110 %
b11111011001001000000001111101111 &
b00100111010111000101100010110001 )
b11010011110001111010101100111110 *
b11111011001001000000001111101111 +
#11000
b11110010001011000011001101110001 $
b11100100010101110100110010100110 %
b11010110100000111000000000010111 &
b11110010001011000011001101110001 )
b11100100010101110100110010100110 *
b11010110100000111000000000010111 +
#12000
b00010101111111110000100111100101 $
b01011110100000001011100001111010 %
b01110100011111111100001001011111 &
b00010101111111110000100111100101 )
b01011110100000001011100001111010 *
b01110100011111111100001001011111 +
#13000
b11001110100111000110010111100011 $
b00101000010100011111001111000011 %
b11110110111011100101100110100110 &
b11001110100111000110010111100011 )
b00101000010100011111001111000011 *
b11110110111011100101100110100110 +
#14000
b11001010110010011101100010000010 $
b11010011000100001101100110000110 %
b10011101110110101011001000001000 &
b11001010110010011101100010000010 )
b11010011000100001101100110000110 *
b10011101110110101011001000001000 +
#15000
b11001010001001111101001001101101 $
b11000011000011110101111000000110 %
b10001101001101110011000001110011 &
b11001010001001111101001001101101 )
b11000011000011110101111000000110 *
b10001101001101110011000001110011 +
#16000
b11011000001100011011100100011110 $
b01101100010010011111101110101110 %
b01000100011110111011010011001100 &
b11011000001100011011100100011110 )
b01101100010010011111101110101110 *
b01000100011110111011010011001100 +
#17000
b10001011110101101111100001100010 $
b01110100011001101010000000110101 %
b00000000001111011001100010010111 &
b10001011110101101111100001100010 )
b01110100011001101010000000110101 *
b00000000001111011001100010010111 +
#18000
b01001100100011110010010101011010 $
b11101011000100110001111000011011 %
b00110111101000100100001101110101 &
b01001100100011110010010101011010 )
b11101011000100110001111000011011 *
b00110111101000100100001101110101 +
#19000
b00001110111010011101110001101011 $
b01111011011000101110010101101101 %
b10001010010011001100000111011000 &
b00001110111010011101110001101011 )
b01111011011000101110010101101101 *
b10001010010011001100000111011000 +
#20000
b01011101011001001110010100010101 $
b10111011001001000101110100110111 %
b00011000100010010100001001001100 &
b01011101011001001110010100010101 )
b10111011001001000101110100110111 *
b00011000100010010100001001001100 +
#21000
b01000111001101000110111011101001 $
b00100000010000001011001111011010 %
b01100111011101010010001011000011 &
b01000111001101000110111011101001 )
b00100000010000001011001111011010 *
b01100111011101010010001011000011 +
#22000
b01010001001110010011010001011011 $
b01000011111100011001101110111010 %
b10010101001010101101000000010101 &
b01010001001110010011010001011011 )
b01000011111100011001101110111010 *
b10010101001010101101000000010101 +
#23000
b01100100110010100110010100100111 $
b10101010101110111010010100111100 %
b00001111100001100000101001100011 &
b01100100110010100110010100100111 )
b10101010101110111010010100111100 *
b00001111100001100000101001100011 +
#24000
b11010101000001001000000001010001 $
b10000100110100100111011100001110 %
b01011001110101101111011101011111 &
b11010101000001001000000001010001 )
b10000100110100100111011100001110 *
b01011001110101101111011101011111 +
#25000
b11101001000000111111101100101001 $
b10001101110101011010101010111111 %
b01110110110110011010010111101000 &
b11101001000000111111101100101001 )
b10001101110101011010101010111111 *
b01110110110110011010010111101000 +
#26000
b10100011110100011010101101000110 $
b00101000111010011000010000001100 %
b11001100101110110010111101010010 &
b10100011110100011010101101000110 )
b00101000111010011000010000001100 *
b11001100101110110010111101010010 +
#27000
b01101011010101001111101000110010 $
b00011001010000011010010101101011 %
b10000100100101101001111110011101 &
b01101011010101001111101000110010 )
b00011001010000011010010101101011 *
b10000100100101101001111110011101 +
#28000
b10101000010010011101010111101101 $
b00111110101011101100011110000000 %
b11100110111110001001110101101101 &
b10101000010010011101010111101101 )
b00111110101011101100011110000000 *
b11100110111110001001110101101101 +
#29000
b10111100010111000111011111111100 $
b00111010110001110001010011101110 %
b11110111001000111000110011101010 &
b10111100010111000111011111111100 )
b00111010110001110001010011101110 *
b11110111001000111000110011101010 +
#30000
b00111001100110011000011110001000 $
b10100010101001001011111010000101 %
b11011100001111100100011000001101 &
b00111001100110011000011110001000 )
b10100010101001001011111010000101 *
b11011100001111100100011000001101 +
#31000
b11001011110111100011000010010110 $
b10100001100001100100001000011100 %
b01101101011001000111001010110010 &
b11001011110111100011000010010110 )
b10100001100001100100001000011100 *
b01101101011001000111001010110010 +
#32000
b01001001001011111011000011101110 $
b11100101001111100110101000111000 %
b00101110011011100001101100100110 &
b01001001001011111011000011101110 )
b11100101001111100110101000111000 *
b00101110011011100001101100100110 +
#33000
b11110010101110000100101101011000 $
b11011101111011100111110101110001 %
b11010000101001101100100011001001 &
b11110010101110000100101101011000 )
b11011101111011100111110101110001 *
b11010000101001101100100011001001 +
#34000
b00111011101010100000110101111011 $
b10000010100100010100101111110001 %
b10111110001110110101100101101100 &
b00111011101010100000110101111011 )
b10000010100100010100101111110001 *
b10111110001110110101100101101100 +
#35000
b00111111011001100101011010011010 $
b01111101101100001110011110011011 %
b10111101000101110011111000110101 &
b00111111011001100101011010011010 )
b01111101101100001110011110011011 *
b10111101000101110011111000110101 +
#36000
b01100000100000011110001010001110 $
b00011111111001000101110100111010 %
b10000000011001100011111111001000 &
b01100000100000011110001010001110 )
b00011111111001000101110100111010 *
b10000000011001100011111111001000 +
#37000
b00101100110111110100001010000001 $
b00111111010010011110111101000101 %
b01101100001010010011000111000110 &
b00101100110111110100001010000001 )
b00111111010010011110111101000101 *
b01101100001010010011000111000110 +
#38000
b01101110000110101111001101110100 $
b00001110100110110010101110000111 %
b01111100101101100001111011111011 &
b01101110000110101111001101110100 )
b00001110100110110010101110000111 *
b01111100101101100001111011111011 +
#39000
b10001010011011110101011100110010 $
b00010011101011001101101010000011 %
b10011110000111000011000110110101 &
b10001010011011110101011100110010 )
b00010011101011001101101010000011 *
b10011110000111000011000110110101 +
#40000
b01101110111101010001000101001001 $
b10111100110001110110100111000000 %
b00101011101111000111101100001001 &
b01101110111101010001000101001001 )
b10111100110001110110100111000000 *
b00101011101111000111101100001001 +
#41000
b01101111101111001000100010011001 $
b01011000100100111110100000010010 %
b11001000010100000111000010101011 &
b01101111101111001000100010011001 )
b01011000100100111110100000010010 *
b11001000010100000111000010101011 +
#42000
b00011000100001000001111010100001 $
b10110010011011010001001010001111 %
b11001010111100010011000100110000 &
b00011000100001000001111010100001 )
b10110010011011010001001010001111 *
b11001010111100010011000100110000 +
#43000
b11111001100100010011100010011000 $
b11011100011000000101001111000010 %
b11010101111100011000110001011010 &
b11111001100100010011100010011000 )
b11011100011000000101001111000010 *
b11010101111100011000110001011010 +
#44000
b01101101010101101111000010000001 $
b00010001010101100010111111011010 %
b01111110101011010010000001011011 &
b01101101010101101111000010000001 )
b00010001010101100010111111011010 *
b01111110101011010010000001011011 +
#45000
b01000110010001101010001101100001 $
b00001101000110100101101110101110 %
b01010011011000001111111100001111 &
b01000110010001101010001101100001 )
b00001101000110100101101110101110 *
b01010011011000001111111100001111 +
#46000
b01001000111110001000110000111000 $
b11111000101100110100110100001001 %
b01000001101010111101100101000001 &
b01001000111110001000110000111000 )
b11111000101100110100110100001001 *
b01000001101010111101100101000001 +
#47000
b00000011100010010001111010001110 $
b01111101011011111000111011101011 %
b10000000111110001010110101111001 &
b00000011100010010001111010001110 )
b01111101011011111000111011101011 *
b10000000111110001010110101111001 +
#48000
b00111100010010000101101110100111 $
b01011000101111010110111111000110 %
b10010101000001011100101101101101 &
b00111100010010000101101110100111 )
b01011000101111010110111111000110 *
b10010101000001011100101101101101 +
#49000
b10000001101001000111110101010110 $
b11101100010111101111011101011000 %
b01101110000000110111010010101110 &
b10000001101001000111110101010110 )
b11101100010111101111011101011000 *
b01101110000000110111010010101110 +
#50000
b11001011110111101001100000011110 $
b00101011101001101001000111010100 %
b11110111100001010010100111110010 &
b11001011110111101001100000011110 )
b00101011101001101001000111010100 *
b11110111100001010010100111110010 +
#51000
b11001000000010000101001111010011 $
b10110011010111101110111101100111 %
b01111011011001110100001100111010 &
b11001000000010000101001111010011 )
b10110011010111101110111101100111 *
b01111011011001110100001100111010 +
#52000
b11011001100110000011110111110001 $
b00010001100101111110000110110011 %
b11101011001100000001111110100100 &
b11011001100110000011110111110001 )
b00010001100101111110000110110011 *
b11101011001100000001111110100100 +
#53000
b11010101110101111000001001001100 $
b11111101110110001011001001111101 %
b11010011101100000011010011001001 &
b11010101110101111000001001001100 )
b11111101110110001011001001111101 *
b11010011101100000011010011001001 +
#54000
b11010001011111101110001000011011 $
b01111101101010111101100011101010 %
b01001111001010101011101100000101 &
b11010001011111101110001000011011 )
b01111101101010111101100011101010 *
b01001111001010101011101100000101 +
#55000
b10010001000010101000000111000000 $
b11001100001011011110011110110000 %
b01011101001110000110100101110000 &
b10010001000010101000000111000000 )
b11001100001011011110011110110000 *
b01011101001110000110100101110000 +
#56000
b01110010011000111011111010101111 $
b00010011110101111000101000101011 %
b10000110001110110100100011011010 &
b01110010011000111011111010101111 )
b00010011110101111000101000101011 *
b10000110001110110100100011011010 +
#57000
b11000001100111100110111010011111 $
b11011010100000110111100001011010 %
b10011100001000011110011011111001 &
b11000001100111100110111010011111 )
b11011010100000110111100001011010 *
b10011100001000011110011011111001 +
#58000
b01000100001011010111100110110100 $
b01101001100110011000101101001100 %
b10101101110001110000010100000000 &
b01000100001011010111100110110100 )
b01101001100110011000101101001100 *
b10101101110001110000010100000000 +
#59000
b00110110100010100111100011010001 $
b11101101110101001110110011111001 %
b00100100010111110110010111001010 &
b00110110100010100111100011010001 )
b11101101110101001110110011111001 *
b00100100010111110110010111001010 +
#60000
b11000101111111111000001111110111 $
b00010000101111000001010010101000 %
b11010110101110111001100010011111 &
b11000101111111111000001111110111 )
b00010000101111000001010010101000 *
b11010110101110111001100010011111 +
#61000
b11011111101000110101110010011000 $
b11101101011100000001100110011111 %
b11001101000100110111011000110111 &
b11011111101000110101110010011000 )
b11101101011100000001100110011111 *
b11001101000100110111011000110111 +
#62000
b01001000100111100100011100100000 $
b01100000011010100101001011010011 %
b10101001000010001001100111110011 &
b01001000100111100100011100100000 )
b01100000011010100101001011010011 *
b10101001000010001001100111110011 +
#63000
b11100001111000110001111111100111 $
b01110011001101111101110111110100 %
b01010101000110101111110111011011 &
b11100001111000110001111111100111 )
b01110011001101111101110111110100 *
b01010101000110101111110111011011 +
#64000
b00100101110000001010101101000001 $
b10101000010011111111000000011110 %
b11001110000100001001101101011111 &
b00100101110000001010101101000001 )
b10101000010011111111000000011110 *
b11001110000100001001101101011111 +
#65000
b11001011011011000111011100011101 $
b00010110011010001100111111011010 %
b11100001110101010100011011110111 &
b11001011011011000111011100011101 )
b00010110011010001100111111011010 *
b11100001110101010100011011110111 +
#66000
b11100100010011010100101101101111 $
b11111001001111000010001100011111 %
b11011101100010010110111010001110 &
b11100100010011010100101101101111 )
b11111001001111000010001100011111 *
b11011101100010010110111010001110 +
#67000
b11111101000010111010010101100100 $
b00000001100001101010100001101000 %
b11111110100100100100110111001100 &
b11111101000010111010010101100100 )
b00000001100001101010100001101000 *
b11111110100100100100110111001100 +
#68000
b01101110100001111000010001000111 $
b01000101000100001101110010000010 %
b10110011100110000110000011001001 &
b01101110100001111000010001000111 )
b01000101000100001101110010000010 *
b10110011100110000110000011001001 +
#69000
b00111000101010111001110000100011 $
b01011101100101111111011100001101 %
b10010110010000111001001100110000 &
b00111000101010111001110000100011 )
b01011101100101111111011100001101 *
b10010110010000111001001100110000 +
#70000
b00100000000111100010111010010100 $
b00010100111111100011111011010000 %
b00110101000111000110110101100100 &
b00100000000111100010111010010100 )
b00010100111111100011111011010000 *
b00110101000111000110110101100100 +
#71000
b11101110110001111110011101010111 $
b00100101001000011000111100100000 %
b00010011111010010111011001110111 &
b11101110110001111110011101010111 )
b00100101001000011000111100100000 *
b00010011111010010111011001110111 +
#72000
b10000000010001101100011011010000 $
b00001111000100111000110111111100 %
b10001111010110100101010011001100 &
b10000000010001101100011011010000 )
b00001111000100111000110111111100 *
b10001111010110100101010011001100 +
#73000
b11001101001111010111111001010111 $
b10010010110000101100111011010110 %
b01100000000000000100110100101101 &
b11001101001111010111111001010111 )
b10010010110000101100111011010110 *
b01100000000000000100110100101101 +
#74000
b10000100011000011111000110001101 $
b00000100100111000000100000101010 %
b10001000111111011111100110110111 &
b10000100011000011111000110001101 )
b00000100100111000000100000101010 *
b10001000111111011111100110110111 +
#75000
b11110000110110000010010000100010 $
b01000010101001100001010010001100 %
b00110011011111100011100010101110 &
b11110000110110000010010000100010 )
b01000010101001100001010010001100 *
b00110011011111100011100010101110 +
#76000
b11100001001011001110011001100010 $
b01001101001001101000101111100110 %
b00101110010100110111001001001000 &
b11100001001011001110011001100010 )
b01001101001001101000101111100110 *
b00101110010100110111001001001000 +
#77000
b01110110000011111001010010110111 $
b00000111111000101101101000101110 %
b01111101111100100110111011100101 &
b01110110000011111001010010110111 )
b00000111111000101101101000101110 *
b01111101111100100110111011100101 +
#78000
b00011011111011101101001111000101 $
b10110100110001101101011000100110 %
b11010000101101011010100111101011 &
b00011011111011101101001111000101 )
b10110100110001101101011000100110 *
b11010000101101011010100111101011 +
#79000
b11001100101011000100111001000101 $
b10110010100101111111001000010010 %
b01111111010001000100000001010111 &
b11001100101011000100111001000101 )
b10110010100101111111001000010010 *
b01111111010001000100000001010111 +
#80000
b00011000101101010101111111101100 $
b11101011111110001000110111011001 %
b00000100101011011110110111000101 &
b00011000101101010101111111101100 )
b11101011111110001000110111011001 *
b00000100101011011110110111000101 +
#81000
b00010110101011000001010110111101 $
b01110010000110100101111101010000 %
b10001000110001100111010100001101 &
b00010110101011000001010110111101 )
b01110010000110100101111101010000 *
b10001000110001100111010100001101 +
#82000
b11010100011010000100011100101011 $
b00010101111100111111010101101000 %
b11101010010111000011110010010011 &
b11010100011010000100011100101011 )
b00010101111100111111010101101000 *
b11101010010111000011110010010011 +
#83000
b11111011100000110100110010001001 $
b10100101101111011101000010110100 %
b10100001010000010001110100111101 &
b11111011100000110100110010001001 )
b10100101101111011101000010110100 *
b10100001010000010001110100111101 +
#84000
b00100000111011100111010101100001 $
b00001011111011100101111000010000 %
b00101100110111001101001101110001 &
b00100000111011100111010101100001 )
b00001011111011100101111000010000 *
b00101100110111001101001101110001 +
#85000
b10000001001011000011011010100111 $
b00111010111101011101010101111011 %
b10111100001000100000110000100010 &
b10000001001011000011011010100111 )
b00111010111101011101010101111011 *
b10111100001000100000110000100010 +
#86000
b11001110111000101110111110101010 $
b01110010011100110111101110000011 %
b01000001010101100110101100101101 &
b11001110111000101110111110101010 )
b01110010011100110111101110000011 *
b01000001010101100110101100101101 +
#87000
b01101101000000000010111100111101 $
b11111000101110111011001010111111 %
b01100101101110111110000111111100 &
b01101101000000000010111100111101 )
b11111000101110111011001010111111 *
b01100101101110111110000111111100 +
#88000
b11111111101011110101010011000110 $
b10110000001010110010010010011001 %
b10101111110110100111100101011111 &
b11111111101011110101010011000110 )
b10110000001010110010010010011001 *
b10101111110110100111100101011111 +
#89000
b00001101111011000000110111001011 $
b10111010011000100010001100000100 %
b11001000010011100011000011001111 &
b00001101111011000000110111001011 )
b10111010011000100010001100000100 *
b11001000010011100011000011001111 +
#90000
b10110110000111000000001101000001 $
b11110110101100000100011110111000 %
b10101100110011000100101011111001 &
b10110110000111000000001101000001 )
b11110110101100000100011110111000 *
b10101100110011000100101011111001 +
#91000
b11000000100010101001110101111001 $
b00100011100100111000101001101110 %
b11100100000111100010011111100111 &
b11000000100010101001110101111001 )
b00100011100100111000101001101110 *
b11100100000111100010011111100111 +
#92000
b01001101010110011011001010011110 $
b11011011100111001111100011100000 %
b00101000111101101010101101111110 &
b01001101010110011011001010011110 )
b11011011100111001111100011100000 *
b00101000111101101010101101111110 +
#93000
b11011111001001000100000010000001 $
b00100000100110010101100101111011 %
b11111111101111011001100111111100 &
b11011111001001000100000010000001 )
b00100000100110010101100101111011 *
b11111111101111011001100111111100 +
#94000
b01110011101111110101000000110101 $
b10001101111100110110001111110011 %
b00000001101100101011010000101000 &
b01110011101111110101000000110101 )
b10001101111100110110001111110011 *
b00000001101100101011010000101000 +
#95000
b10010110111111110101001001100000 $
b01111101000000100100100101001110 %
b00010100000000011001101110101110 &
b10010110111111110101001001100000 )
b01111101000000100100100101001110 *
b00010100000000011001101110101110 +
#96000
b11110001101111100001010000101000 $
b01111110100111110010110001001111 %
b01110000010111010100000001110111 &
b11110001101111100001010000101000 )
b01111110100111110010110001001111 *
b01110000010111010100000001110111 +
#97000
b11000110100010000001111100001110 $
b10100111011010101000011100001100 %
b01101101111100101010011000011010 &
b11000110100010000001111100001110 )
b10100111011010101000011100001100 *
b01101101111100101010011000011010 +
#98000
b00000011111000110011001000001111 $
b01101100001110110011001100100110 %
b01110000000111100110010100110101 &
b00000011111000110011001000001111 )
b01101100001110110011001100100110 *
b01110000000111100110010100110101 +
#99000
b10101110000010011001001100001011 $
b11000110101000001110100111001000 %
b01110100101010100111110011010011 &
b10101110000010011001001100001011 )
b11000110101000001110100111001000 *
b01110100101010100111110011010011 +
#100000
b01110010101001100110100110111100 $
b10100111100110001000010100011001 %
b00011010001111101110111011010101 &
b01110010101001100110100110111100 )
b10100111100110001000010100011001 *
b00011010001111101110111011010101 +
#101000
b00001000010000000011000010001011 $
b01101101111110111110111110001011 %
b01110110001111000010000000010110 &
b00001000010000000011000010001011 )
b01101101111110111110111110001011 *
b01110110001111000010000000010110 +
#102000
b10111101001000101100010011101000 $
b01010111110111010000101111000100 %
b00010100111111111101000010101100 &
b10111101001000101100010011101000 )
b01010111110111010000101111000100 *
b00010100111111111101000010101100 +
#103000
b11100000010100010000100011001111 $
b00011101011000111011101010000001 %
b11111101101101001100001101010000 &
b11100000010100010000100011001111 )
b00011101011000111011101010000001 *
b11111101101101001100001101010000 +
#104000
b01011001010100111001010001001000 $
b00111110110000101100001011101101 %
b10011000000101100101011100110101 &
b01011001010100111001010001001000 )
b00111110110000101100001011101101 *
b10011000000101100101011100110101 +
#105000
b11000000001010111010001110000000 $
b01001100111110010000111111101110 %
b00001101001001001011001101101110 &
b11000000001010111010001110000000 )
b01001100111110010000111111101110 *
b00001101001001001011001101101110 +
#106000
b00010101001101111101100010111000 $
b10101111010100111001010011110010 %
b11000100100010110110110110101010 &
b00010101001101111101100010111000 )
b10101111010100111001010011110010 *
b11000100100010110110110110101010 +
#107000
b11101100010111000001010110010111 $
b00001110010100010111101001010111 %
b11111010101011011000111111101110 &
b11101100010111000001010110010111 )
b00001110010100010111101001010111 *
b11111010101011011000111111101110 +
#108000
b00111000100000001110110010110001 $
b11010010010011100001010110110010 %
b00001010110011110000001001100011 &
b00111000100000001110110010110001 )
b11010010010011100001010110110010 *
b00001010110011110000001001100011 +
#109000
b00000111110111110101100001111001 $
b01100101001011010001001011010100 %
b01101101000011000110101101001101 &
b00000111110111110101100001111001 )
b01100101001011010001001011010100 *
b01101101000011000110101101001101 +
#110000
b01001111111011000011101100110010 $
b01000110011000110111101111111101 %
b10010110010011111011011100101111 &
b01001111111011000011101100110010 )
b01000110011000110111101111111101 *
b10010110010011111011011100101111 +
#111000
b11101000100011111111110101110010 $
b01110010010001110000011100100101 %
b01011010110101110000010010010111 &
b11101000100011111111110101110010 )
b01110010010001110000011100100101 *
b01011010110101110000010010010111 +
#112000
b00101011011001001000110010100101 $
b00100100011001011001011110101010 %
b01001111110010100010010001001111 &
b00101011011001001000110010100101 )
b00100100011001011001011110101010 *
b01001111110010100010010001001111 +
#113000
b00111101000011001110011010010111 $
b01101110010011110011010011000011 %
b10101011010111000001101101011010 &
b00111101000011001110011010010111 )
b01101110010011110011010011000011 *
b10101011010111000001101101011010 +
#114000
b01100111010010101110010000111100 $
b11000111000111011101000110000010 %
b00101110011010001011010110111110 &
b01100111010010101110010000111100 )
b11000111000111011101000110000010 *
b00101110011010001011010110111110 +
#115000
b00101100110000011010011011110011 $
b10011010010100010110001000111001 %
b11000111000100110000100100101100 &
b00101100110000011010011011110011 )
b10011010010100010110001000111001 *
b11000111000100110000100100101100 +
#116000
b00010010001100010100110000000111 $
b10011000010010000111100100110011 %
b10101010011110011100010100111010 &
b00010010001100010100110000000111 )
b10011000010010000111100100110011 *
b10101010011110011100010100111010 +
#117000
b11001111001011101101111110001110 $
b01110010100111000011000011001110 %
b01000001110010110001000001011100 &
b11001111001011101101111110001110 )
b01110010100111000011000011001110 *
b01000001110010110001000001011100 +
#118000
b11100000111110111011001001111100 $
b10010010011110100001101011010000 %
b01110011011101011100110101001100 &
b11100000111110111011001001111100 )
b10010010011110100001101011010000 *
b01110011011101011100110101001100 +
#119000
b11000001011110100110000110010110 $
b10100100011101110000011000101101 %
b01100101111100010110011111000011 &
b11000001011110100110000110010110 )
b10100100011101110000011000101101 *
b01100101111100010110011111000011 +
#120000
b01000110100011110100100111111011 $
b11111010100011100010110101001001 %
b01000001000111010111011101000100 &
b01000110100011110100100111111011 )
b11111010100011100010110101001001 *
b01000001000111010111011101000100 +
#121000
b01101000111011000001101001101011 $
b01000011100000001100110000001100 %
b10101100011011001110011001110111 &
b01101000111011000001101001101011 )
b01000011100000001100110000001100 *
b10101100011011001110011001110111 +
#122000
b01100010010001010000011010111111 $
b01011000110000011110100101000010 %
b10111011000001101111000000000001 &
b01100010010001010000011010111111 )
b01011000110000011110100101000010 *
b10111011000001101111000000000001 +
#123000
b00101101110001111001110010111011 $
b11100110011101100010100001111010 %
b00010100001111011100010100110101 &
b00101101110001111001110010111011 )
b11100110011101100010100001111010 *
b00010100001111011100010100110101 +
#124000
b01111100111101000101101101100101 $
b01010111100100100100001011001100 %
b11010100100001101001111000110001 &
b01111100111101000101101101100101 )
b01010111100100100100001011001100 *
b11010100100001101001111000110001 +
#125000
b00111111010110011111101100111010 $
b01111101000011011001111110001010 %
b10111100011001111001101011000100 &
b00111111010110011111101100111010 )
b01111101000011011001111110001010 *
b10111100011001111001101011000100 +
#126000
b10100110001100100000011101010000 $
b10001010101010111101100011111010 %
b00110000110111011110000001001010 &
b10100110001100100000011101010000 )
b10001010101010111101100011111010 *
b00110000110111011110000001001010 +
#127000
b01110101100101001000000011010110 $
b10100100000001001110001101010101 %
b00011001100110010110010000101011 &
b01110101100101001000000011010110 )
b10100100000001001110001101010101 *
b00011001100110010110010000101011 +
#128000
b11111111000011001100110110001101 $
b10111000110111110110110010010101 %
b10110111111011000011101000100010 &
b11111111000011001100110110001101 )
b10111000110111110110110010010101 *
b10110111111011000011101000100010 +
#129000
b01011100111110101101010010000101 $
b00100001011111011001101110010010 %
b01111110011110000111000000010111 &
b01011100111110101101010010000101 )
b00100001011111011001101110010010 *
b01111110011110000111000000010111 +
#130000
b01001001000010101101010000110000 $
b01100101100111101111100111000100 %
b10101110101010011100110111110100 &
b01001001000010101101010000110000 )
b01100101100111101111100111000100 *
b10101110101010011100110111110100 +
#131000
b11100111011100001110111000110110 $
b00101001011011101011111111110101 %
b00010000110111111010111000101011 &
b11100111011100001110111000110110 )
b00101001011011101011111111110101 *
b00010000110111111010111000101011 +
#132000
b00000111000101010011100110001010 $
b11011001111010111001001000011010 %
b11100001000000001100101110100100 &
b00000111000101010011100110001010 )
b11011001111010111001001000011010 *
b11100001000000001100101110100100 +
#133000
b10010011001101000100110110011100 $
b00010010111110010101101101001101 %
b10100110001011011010100011101001 &
b10010011001101000100110110011100 )
b00010010111110010101101101001101 *
b10100110001011011010100011101001 +
#134000
b10101001111000100100100010000010 $
b01010101000110110110101101111101 %
b11111110111111011011001111111111 &
b10101001111000100100100010000010 )
b01010101000110110110101101111101 *
b11111110111111011011001111111111 +
#135000
b01010100010101111101100111010001 $
b10110010101111101100111010101011 %
b00000111000101101010100001111100 &
b01010100010101111101100111010001 )
b10110010101111101100111010101011 *
b00000111000101101010100001111100 +
#136000
b01000101011000001110110101100000 $
b11100101011101001111111010101111 %
b00101010110101011110110000001111 &
b01000101011000001110110101100000 )
b11100101011101001111111010101111 *
b00101010110101011110110000001111 +
#137000
b11111001001001100101110110010111 $
b10100100010001000000111101000011 %
b10011101011010100110110011011010 &
b11111001001001100101110110010111 )
b10100100010001000000111101000011 *
b10011101011010100110110011011010 +
#138000
b01011011000001011111010010101101 $
b00110101100111100100011111101011 %
b10010000101001000011110010011000 &
b01011011000001011111010010101101 )
b00110101100111100100011111101011 *
b10010000101001000011110010011000 +
#139000
b01001010100000111001010100010101 $
b10110011110110101000110001010001 %
b11111110010111100010000101100110 &
b01001010100000111001010100010101 )
b10110011110110101000110001010001 *
b11111110010111100010000101100110 +
#140000
b10100101111001111110101111110011 $
b11111110101011011011101001111001 %
b10100100100101011010011001101100 &
b10100101111001111110101111110011 )
b11111110101011011011101001111001 *
b10100100100101011010011001101100 +
#141000
b11011000101001110111101010100001 $
b01010001100111011001110010001010 %
b00101010010001010001011100101011 &
b11011000101001110111101010100001 )
b01010001100111011001110010001010 *
b00101010010001010001011100101011 +
#142000
b01100110000010000101110000100111 $
b01110100001100010001100100000000 %
b11011010001110010111010100100111 &
b01100110000010000101110000100111 )
b01110100001100010001100100000000 *
b11011010001110010111010100100111 +
#143000
b10101110100001110110011110011000 $
b00101110000101110111010010000101 %
b11011100100111101101110000011101 &
b10101110100001110110011110011000 )
b00101110000101110111010010000101 *
b11011100100111101101110000011101 +
#144000
b00111001010000101100011000011101 $
b10110011101111101101000001010010 %
b11101101000000011001011001101111 &
b00111001010000101100011000011101 )
b10110011101111101101000001010010 *
b11101101000000011001011001101111 +
#145000
b10011111111100010000001101110101 $
b11000011101010000111100000000011 %
b01100011100110010111101101111000 &
b10011111111100010000001101110101 )
b11000011101010000111100000000011 *
b01100011100110010111101101111000 +
#146000
b11111010010110010111101101010010 $
b11011101110000001001100111101100 %
b11011000000110100001010100111110 &
b11111010010110010111101101010010 )
b11011101110000001001100111101100 *
b11011000000110100001010100111110 +
#147000
b10110000100111100110111111101001 $
b10111111111001110110001000001001 %
b01110000100001011101000111110010 &
b10110000100111100110111111101001 )
b10111111111001110110001000001001 *
b01110000100001011101000111110010 +
#148000
b11000101111001001011101010001011 $
b01011110100100001000011110111101 %
b00100100011101010100001001001000 &
b11000101111001001011101010001011 )
b01011110100100001000011110111101 *
b00100100011101010100001001001000 +
#149000
b11101111001011010101110100001010 $
b10100000111010101101100000001110 %
b10010000000110000011010100011000 &
b11101111001011010101110100001010 )
b10100000111010101101100000001110 *
b10010000000110000011010100011000 +
#150000
b11101110010001011100000111101110 $
b00111011110001101110001001101101 %
b00101010000011001010010001011011 &
b11101110010001011100000111101110 )
b00111011110001101110001001101101 *
b00101010000011001010010001011011 +
#151000
b10101010010110001010011100100100 $
b00101011001111001101100101100000 %
b11010101100101011000000010000100 &
b10101010010110001010011100100100 )
b00101011001111001101100101100000 *
b11010101100101011000000010000100 +
#152000
b00110100111001011010100110010011 $
b01011110101100000010110000011111 %
b10010011100101011101010110110010 &
b00110100111001011010100110010011 )
b01011110101100000010110000011111 *
b10010011100101011101010110110010 +
