aluItype/src/signext.sv
// signext.sv 
module signext (
    // IN
    input logic [24:0] raw_src,
    input logic [1:0] imm_source,

    // OUT (immediate)
    output logic [31:0] immediate
);

always_comb begin
    case (imm_source)
        // For I-Types
        2'b00 : immediate = {{20{raw_src[24]}}, raw_src[24:13]};
        // For S-types
        2'b01 : immediate = {{20{raw_src[24]}},raw_src[24:18],raw_src[4:0]};
        // For B-types
        2'b10 : immediate = {{20{raw_src[24]}},raw_src[0],raw_src[23:18],raw_src[4:1],1'b0};
        // For J-types
        2'b11 : immediate = {{12{raw_src[24]}}, 
                            raw_src[12:5],
                            raw_src[13],
                            raw_src[23:14],
                            1'b0};
        default: immediate = 32'b0;
    endcase
end
    
endmodule


// https://fraserinnovations.com/risc-v/risc-v-instruction-set-explanation/
// above link has the best explanations on each type of riscv instructions



// Instruction guide for b type
// Map of index

// raw_src       = [0, 1, 2, 3,  4,  5,  6,  7,  8,  9,  10, 11, 12, 13, 14, 15, 16, 17, 18, 19, 20, 21, 22, 23, 24]
// instruction   = [7, 8, 9, 10, 11, 12, 13, 14, 15, 16, 17, 18, 19, 20, 21, 22, 23, 24, 25, 26, 27, 28, 29, 30, 31]
// 


// Instruction[6:0] = opcode
// Instruction[7] = immediate[11]
// Instruction[11:8] = immediate[4:1]
// Instruction[12:14] = func3
// Instruction[15:19] = RS1
// Instruction[24:20] = RS2
// Instruction[30:25] = immediate[10:5]
// Instruction[31] = immediate[12]

// immediate represenst memory offset, so having immedite[0] = 0, is the only choice.
// The memory is multiples of 2, immediate[0] ensures that the number is always even and mutiple of 2

aluItype/tb/signExt/dump.vcd
$version Generated by VerilatedVcd $end
$timescale 1ps $end
 $scope module $rootio $end
  $var wire 25 # raw_src [24:0] $end
  $var wire 2 $ imm_source [1:0] $end
  $var wire 32 % immediate [31:0] $end
 $upscope $end
 $scope module signext $end
  $var wire 25 & raw_src [24:0] $end
  $var wire 2 ' imm_source [1:0] $end
  $var wire 32 ( immediate [31:0] $end
 $upscope $end
$enddefinitions $end


#0
b0000000000000000000000000 #
b00 $
b00000000000000000000000000000000 %
b0000000000000000000000000 &
b00 '
b00000000000000000000000000000000 (
#1000
b0000011110111010101010101 #
b00000000000000000000000001111011 %
b0000011110111010101010101 &
b00000000000000000000000001111011 (
#3000
b1111110101101010101010101 #
b11111111111111111111111111010110 %
b1111110101101010101010101 &
b11111111111111111111111111010110 (
#104001
b0011001000000000000001101 #
b01 $
b00000000000000000000001100101101 %
b0011001000000000000001101 &
b01 '
b00000000000000000000001100101101 (
#106001
b1111101000000000000001011 #
b11111111111111111111111110101011 %
b1111101000000000000001011 &
b11111111111111111111111110101011 (
#207001
b0000000000000000000011110 #
b00000000000000000000000000011110 %
b0000000000000000000011110 &
b00000000000000000000000000011110 (
#209001
b1011111000000000000000110 #
b11111111111111111111101111100110 %
b1011111000000000000000110 &
b11111111111111111111101111100110 (
#310001
b0010100000000000000000011 #
b00000000000000000000001010000011 %
b0010100000000000000000011 &
b00000000000000000000001010000011 (
#312001
b1000110000000000000001010 #
b11111111111111111111100011001010 %
b1000110000000000000001010 &
b11111111111111111111100011001010 (
#413001
b0010100000000000000001000 #
b00000000000000000000001010001000 %
b0010100000000000000001000 &
b00000000000000000000001010001000 (
#415001
b1110100000000000000010101 #
b11111111111111111111111010010101 %
b1110100000000000000010101 &
b11111111111111111111111010010101 (
#516001
b0010010000000000000011100 #
b00000000000000000000001001011100 %
b0010010000000000000011100 &
b00000000000000000000001001011100 (
#518001
b1010000000000000000001000 #
b11111111111111111111101000001000 %
b1010000000000000000001000 &
b11111111111111111111101000001000 (
#619001
b0001100000000000000010010 #
b00000000000000000000000110010010 %
b0001100000000000000010010 &
b00000000000000000000000110010010 (
#621001
b1000010000000000000000001 #
b11111111111111111111100001000001 %
b1000010000000000000000001 &
b11111111111111111111100001000001 (
#722001
b0000000000000000000010101 #
b00000000000000000000000000010101 %
b0000000000000000000010101 &
b00000000000000000000000000010101 (
#724001
b1101000000000000000011011 #
b11111111111111111111110100011011 %
b1101000000000000000011011 &
b11111111111111111111110100011011 (
#825001
b0001011000000000000011111 #
b00000000000000000000000101111111 %
b0001011000000000000011111 &
b00000000000000000000000101111111 (
#827001
b1100011000000000000000011 #
b11111111111111111111110001100011 %
b1100011000000000000000011 &
b11111111111111111111110001100011 (
#928001
b0001000000000000000001000 #
b00000000000000000000000100001000 %
b0001000000000000000001000 &
b00000000000000000000000100001000 (
#930001
b1010111000000000000010000 #
b11111111111111111111101011110000 %
b1010111000000000000010000 &
b11111111111111111111101011110000 (
#1031001
b0011111000000000000010011 #
b00000000000000000000001111110011 %
b0011111000000000000010011 &
b00000000000000000000001111110011 (
#1033001
b1001101000000000000011000 #
b11111111111111111111100110111000 %
b1001101000000000000011000 &
b11111111111111111111100110111000 (
#1134001
b0001000000000000000001000 #
b00000000000000000000000100001000 %
b0001000000000000000001000 &
b00000000000000000000000100001000 (
#1136001
b1101010000000000000011101 #
b11111111111111111111110101011101 %
b1101010000000000000011101 &
b11111111111111111111110101011101 (
#1237001
b0010111000000000000011011 #
b00000000000000000000001011111011 %
b0010111000000000000011011 &
b00000000000000000000001011111011 (
#1239001
b1111010000000000000001110 #
b11111111111111111111111101001110 %
b1111010000000000000001110 &
b11111111111111111111111101001110 (
#1340001
b0000011000000000000001010 #
b00000000000000000000000001101010 %
b0000011000000000000001010 &
b00000000000000000000000001101010 (
#1342001
b1010011000000000000010010 #
b11111111111111111111101001110010 %
b1010011000000000000010010 &
b11111111111111111111101001110010 (
#1443001
b0010001000000000000011101 #
b00000000000000000000001000111101 %
b0010001000000000000011101 &
b00000000000000000000001000111101 (
#1445001
b1110010000000000000011101 #
b11111111111111111111111001011101 %
b1110010000000000000011101 &
b11111111111111111111111001011101 (
#1546001
b0011010000000000000011011 #
b00000000000000000000001101011011 %
b0011010000000000000011011 &
b00000000000000000000001101011011 (
#1548001
b1100101000000000000001000 #
b11111111111111111111110010101000 %
b1100101000000000000001000 &
b11111111111111111111110010101000 (
#1649001
b0010011000000000000001101 #
b00000000000000000000001001101101 %
b0010011000000000000001101 &
b00000000000000000000001001101101 (
#1651001
b1111001000000000000001101 #
b11111111111111111111111100101101 %
b1111001000000000000001101 &
b11111111111111111111111100101101 (
#1752001
b0010000000000000000011011 #
b00000000000000000000001000011011 %
b0010000000000000000011011 &
b00000000000000000000001000011011 (
#1754001
b1001001000000000000010011 #
b11111111111111111111100100110011 %
b1001001000000000000010011 &
b11111111111111111111100100110011 (
#1855001
b0001010000000000000011110 #
b00000000000000000000000101011110 %
b0001010000000000000011110 &
b00000000000000000000000101011110 (
#1857001
b1000011000000000000001110 #
b11111111111111111111100001101110 %
b1000011000000000000001110 &
b11111111111111111111100001101110 (
#1958001
b0001010000000000000010000 #
b00000000000000000000000101010000 %
b0001010000000000000010000 &
b00000000000000000000000101010000 (
#1960001
b1011101000000000000000111 #
b11111111111111111111101110100111 %
b1011101000000000000000111 &
b11111111111111111111101110100111 (
#2061001
b0000111000000000000001110 #
b00000000000000000000000011101110 %
b0000111000000000000001110 &
b00000000000000000000000011101110 (
#2063001
b1110000000000000000011100 #
b11111111111111111111111000011100 %
b1110000000000000000011100 &
b11111111111111111111111000011100 (
#2164001
b0000111000000000000010100 #
b00000000000000000000000011110100 %
b0000111000000000000010100 &
b00000000000000000000000011110100 (
#2166001
b1000111000000000000000000 #
b11111111111111111111100011100000 %
b1000111000000000000000000 &
b11111111111111111111100011100000 (
#2267001
b0001000000000000000001110 #
b00000000000000000000000100001110 %
b0001000000000000000001110 &
b00000000000000000000000100001110 (
#2269001
b1100101000000000000011111 #
b11111111111111111111110010111111 %
b1100101000000000000011111 &
b11111111111111111111110010111111 (
#2370001
b0000101000000000000000011 #
b00000000000000000000000010100011 %
b0000101000000000000000011 &
b00000000000000000000000010100011 (
#2372001
b1001001000000000000010010 #
b11111111111111111111100100110010 %
b1001001000000000000010010 &
b11111111111111111111100100110010 (
#2473001
b0011010000000000000001101 #
b00000000000000000000001101001101 %
b0011010000000000000001101 &
b00000000000000000000001101001101 (
#2475001
b1101001000000000000011011 #
b11111111111111111111110100111011 %
b1101001000000000000011011 &
b11111111111111111111110100111011 (
#2576001
b0001100000000000000011111 #
b00000000000000000000000110011111 %
b0001100000000000000011111 &
b00000000000000000000000110011111 (
#2578001
b1110000000000000000000111 #
b11111111111111111111111000000111 %
b1110000000000000000000111 &
b11111111111111111111111000000111 (
#2679001
b0010001000000000000010101 #
b00000000000000000000001000110101 %
b0010001000000000000010101 &
b00000000000000000000001000110101 (
#2681001
b1110010000000000000010100 #
b11111111111111111111111001010100 %
b1110010000000000000010100 &
b11111111111111111111111001010100 (
#2782001
b0010101000000000000001101 #
b00000000000000000000001010101101 %
b0010101000000000000001101 &
b00000000000000000000001010101101 (
#2784001
b1011000000000000000000001 #
b11111111111111111111101100000001 %
b1011000000000000000000001 &
b11111111111111111111101100000001 (
#2885001
b0011011000000000000001101 #
b00000000000000000000001101101101 %
b0011011000000000000001101 &
b00000000000000000000001101101101 (
#2887001
b1111100000000000000011001 #
b11111111111111111111111110011001 %
b1111100000000000000011001 &
b11111111111111111111111110011001 (
#2988001
b0011000000000000000010000 #
b00000000000000000000001100010000 %
b0011000000000000000010000 &
b00000000000000000000001100010000 (
#2990001
b1111110000000000000011001 #
b11111111111111111111111111011001 %
b1111110000000000000011001 &
b11111111111111111111111111011001 (
#3091001
b0010100000000000000010111 #
b00000000000000000000001010010111 %
b0010100000000000000010111 &
b00000000000000000000001010010111 (
#3093001
b1001101000000000000011110 #
b11111111111111111111100110111110 %
b1001101000000000000011110 &
b11111111111111111111100110111110 (
#3194001
b0010010000000000000001000 #
b00000000000000000000001001001000 %
b0010010000000000000001000 &
b00000000000000000000001001001000 (
#3196001
b1011010000000000000010111 #
b11111111111111111111101101010111 %
b1011010000000000000010111 &
b11111111111111111111101101010111 (
#3297001
b0001001000000000000000001 #
b00000000000000000000000100100001 %
b0001001000000000000000001 &
b00000000000000000000000100100001 (
#3299001
b1001110000000000000001001 #
b11111111111111111111100111001001 %
b1001110000000000000001001 &
b11111111111111111111100111001001 (
#3400001
b0001110000000000000001011 #
b00000000000000000000000111001011 %
b0001110000000000000001011 &
b00000000000000000000000111001011 (
#3402001
b1110101000000000000001110 #
b11111111111111111111111010101110 %
b1110101000000000000001110 &
b11111111111111111111111010101110 (
#3503001
b0010001000000000000001001 #
b00000000000000000000001000101001 %
b0010001000000000000001001 &
b00000000000000000000001000101001 (
#3505001
b1000111000000000000010011 #
b11111111111111111111100011110011 %
b1000111000000000000010011 &
b11111111111111111111100011110011 (
#3606001
b0000111000000000000010001 #
b00000000000000000000000011110001 %
b0000111000000000000010001 &
b00000000000000000000000011110001 (
#3608001
b1000111000000000000001111 #
b11111111111111111111100011101111 %
b1000111000000000000001111 &
b11111111111111111111100011101111 (
#3709001
b0011101000000000000011101 #
b00000000000000000000001110111101 %
b0011101000000000000011101 &
b00000000000000000000001110111101 (
#3711001
b1000101000000000000011000 #
b11111111111111111111100010111000 %
b1000101000000000000011000 &
b11111111111111111111100010111000 (
#3812001
b0011110000000000000010011 #
b00000000000000000000001111010011 %
b0011110000000000000010011 &
b00000000000000000000001111010011 (
#3814001
b1101100000000000000010101 #
b11111111111111111111110110010101 %
b1101100000000000000010101 &
b11111111111111111111110110010101 (
#3915001
b0000111000000000000001000 #
b00000000000000000000000011101000 %
b0000111000000000000001000 &
b00000000000000000000000011101000 (
#3917001
b1000010000000000000001011 #
b11111111111111111111100001001011 %
b1000010000000000000001011 &
b11111111111111111111100001001011 (
#4018001
b0001111000000000000010100 #
b00000000000000000000000111110100 %
b0001111000000000000010100 &
b00000000000000000000000111110100 (
#4020001
b1111000000000000000000110 #
b11111111111111111111111100000110 %
b1111000000000000000000110 &
b11111111111111111111111100000110 (
#4121001
b0001000000000000000000100 #
b00000000000000000000000100000100 %
b0001000000000000000000100 &
b00000000000000000000000100000100 (
#4123001
b1010011000000000000010001 #
b11111111111111111111101001110001 %
b1010011000000000000010001 &
b11111111111111111111101001110001 (
#4224001
b0010011000000000000001010 #
b00000000000000000000001001101010 %
b0010011000000000000001010 &
b00000000000000000000001001101010 (
#4226001
b1011100000000000000010001 #
b11111111111111111111101110010001 %
b1011100000000000000010001 &
b11111111111111111111101110010001 (
#4327001
b0011100000000000000001001 #
b00000000000000000000001110001001 %
b0011100000000000000001001 &
b00000000000000000000001110001001 (
#4329001
b1110100000000000000010110 #
b11111111111111111111111010010110 %
b1110100000000000000010110 &
b11111111111111111111111010010110 (
#4430001
b0010010000000000000000101 #
b00000000000000000000001001000101 %
b0010010000000000000000101 &
b00000000000000000000001001000101 (
#4432001
b1101111000000000000000111 #
b11111111111111111111110111100111 %
b1101111000000000000000111 &
b11111111111111111111110111100111 (
#4533001
b0010111000000000000010011 #
b00000000000000000000001011110011 %
b0010111000000000000010011 &
b00000000000000000000001011110011 (
#4535001
b1010100000000000000011100 #
b11111111111111111111101010011100 %
b1010100000000000000011100 &
b11111111111111111111101010011100 (
#4636001
b0011001000000000000000100 #
b00000000000000000000001100100100 %
b0011001000000000000000100 &
b00000000000000000000001100100100 (
#4638001
b1110011000000000000010110 #
b11111111111111111111111001110110 %
b1110011000000000000010110 &
b11111111111111111111111001110110 (
#4739001
b0000001000000000000011000 #
b00000000000000000000000000111000 %
b0000001000000000000011000 &
b00000000000000000000000000111000 (
#4741001
b1100001000000000000001000 #
b11111111111111111111110000101000 %
b1100001000000000000001000 &
b11111111111111111111110000101000 (
#4842001
b0011100000000000000001001 #
b00000000000000000000001110001001 %
b0011100000000000000001001 &
b00000000000000000000001110001001 (
#4844001
b1010011000000000000010100 #
b11111111111111111111101001110100 %
b1010011000000000000010100 &
b11111111111111111111101001110100 (
#4945001
b0010000000000000000010001 #
b00000000000000000000001000010001 %
b0010000000000000000010001 &
b00000000000000000000001000010001 (
#4947001
b1000010000000000000000101 #
b11111111111111111111100001000101 %
b1000010000000000000000101 &
b11111111111111111111100001000101 (
#5048001
b0011110000000000000010101 #
b00000000000000000000001111010101 %
b0011110000000000000010101 &
b00000000000000000000001111010101 (
#5050001
b1001110000000000000001111 #
b11111111111111111111100111001111 %
b1001110000000000000001111 &
b11111111111111111111100111001111 (
#5151001
b0011110000000000000001001 #
b00000000000000000000001111001001 %
b0011110000000000000001001 &
b00000000000000000000001111001001 (
#5153001
b1010101000000000000010100 #
b11111111111111111111101010110100 %
b1010101000000000000010100 &
b11111111111111111111101010110100 (
#5254001
b0001101000000000000010110 #
b00000000000000000000000110110110 %
b0001101000000000000010110 &
b00000000000000000000000110110110 (
#5256001
b1110111000000000000000110 #
b11111111111111111111111011100110 %
b1110111000000000000000110 &
b11111111111111111111111011100110 (
#5357001
b0000011000000000000010011 #
b00000000000000000000000001110011 %
b0000011000000000000010011 &
b00000000000000000000000001110011 (
#5359001
b1101110000000000000001010 #
b11111111111111111111110111001010 %
b1101110000000000000001010 &
b11111111111111111111110111001010 (
#5460001
b0011111000000000000011100 #
b00000000000000000000001111111100 %
b0011111000000000000011100 &
b00000000000000000000001111111100 (
#5462001
b1000111000000000000011010 #
b11111111111111111111100011111010 %
b1000111000000000000011010 &
b11111111111111111111100011111010 (
#5563001
b0001101000000000000001111 #
b00000000000000000000000110101111 %
b0001101000000000000001111 &
b00000000000000000000000110101111 (
#5565001
b1001111000000000000001010 #
b11111111111111111111100111101010 %
b1001111000000000000001010 &
b11111111111111111111100111101010 (
#5666001
b0010010000000000000000001 #
b00000000000000000000001001000001 %
b0010010000000000000000001 &
b00000000000000000000001001000001 (
#5668001
b1000010000000000000010110 #
b11111111111111111111100001010110 %
b1000010000000000000010110 &
b11111111111111111111100001010110 (
#5769001
b0000100000000000000011101 #
b00000000000000000000000010011101 %
b0000100000000000000011101 &
b00000000000000000000000010011101 (
#5771001
b1000101000000000000010001 #
b11111111111111111111100010110001 %
b1000101000000000000010001 &
b11111111111111111111100010110001 (
#5872001
b0001000000000000000011011 #
b00000000000000000000000100011011 %
b0001000000000000000011011 &
b00000000000000000000000100011011 (
#5874001
b1101000000000000000000000 #
b11111111111111111111110100000000 %
b1101000000000000000000000 &
b11111111111111111111110100000000 (
#5975001
b0011100000000000000000101 #
b00000000000000000000001110000101 %
b0011100000000000000000101 &
b00000000000000000000001110000101 (
#5977001
b1111111000000000000001101 #
b11111111111111111111111111101101 %
b1111111000000000000001101 &
b11111111111111111111111111101101 (
#6078001
b0010011000000000000010100 #
b00000000000000000000001001110100 %
b0010011000000000000010100 &
b00000000000000000000001001110100 (
#6080001
b1101101000000000000000011 #
b11111111111111111111110110100011 %
b1101101000000000000000011 &
b11111111111111111111110110100011 (
#6181001
b0011100000000000000001001 #
b00000000000000000000001110001001 %
b0011100000000000000001001 &
b00000000000000000000001110001001 (
#6183001
b1001101000000000000011101 #
b11111111111111111111100110111101 %
b1001101000000000000011101 &
b11111111111111111111100110111101 (
#6284001
b0001110000000000000010000 #
b00000000000000000000000111010000 %
b0001110000000000000010000 &
b00000000000000000000000111010000 (
#6286001
b1001001000000000000001000 #
b11111111111111111111100100101000 %
b1001001000000000000001000 &
b11111111111111111111100100101000 (
#6387001
b0010000000000000000001110 #
b00000000000000000000001000001110 %
b0010000000000000000001110 &
b00000000000000000000001000001110 (
#6389001
b1111110000000000000010011 #
b11111111111111111111111111010011 %
b1111110000000000000010011 &
b11111111111111111111111111010011 (
#6490001
b0011110000000000000001100 #
b00000000000000000000001111001100 %
b0011110000000000000001100 &
b00000000000000000000001111001100 (
#6492001
b1101001000000000000000001 #
b11111111111111111111110100100001 %
b1101001000000000000000001 &
b11111111111111111111110100100001 (
#6593001
b0000111000000000000000100 #
b00000000000000000000000011100100 %
b0000111000000000000000100 &
b00000000000000000000000011100100 (
#6595001
b1101100000000000000001110 #
b11111111111111111111110110001110 %
b1101100000000000000001110 &
b11111111111111111111110110001110 (
#6696001
b0010100000000000000001101 #
b00000000000000000000001010001101 %
b0010100000000000000001101 &
b00000000000000000000001010001101 (
#6698001
b1101001000000000000000100 #
b11111111111111111111110100100100 %
b1101001000000000000000100 &
b11111111111111111111110100100100 (
#6799001
b0001000000000000000001000 #
b00000000000000000000000100001000 %
b0001000000000000000001000 &
b00000000000000000000000100001000 (
#6801001
b1010110000000000000001011 #
b11111111111111111111101011001011 %
b1010110000000000000001011 &
b11111111111111111111101011001011 (
#6902001
b0000001000000000000001101 #
b00000000000000000000000000101101 %
b0000001000000000000001101 &
b00000000000000000000000000101101 (
#6904001
b1000011000000000000011000 #
b11111111111111111111100001111000 %
b1000011000000000000011000 &
b11111111111111111111100001111000 (
#7005001
b0010101000000000000000111 #
b00000000000000000000001010100111 %
b0010101000000000000000111 &
b00000000000000000000001010100111 (
#7007001
b1000000000000000000010110 #
b11111111111111111111100000010110 %
b1000000000000000000010110 &
b11111111111111111111100000010110 (
#7108001
b0011010000000000000001010 #
b00000000000000000000001101001010 %
b0011010000000000000001010 &
b00000000000000000000001101001010 (
#7110001
b1111010000000000000010010 #
b11111111111111111111111101010010 %
b1111010000000000000010010 &
b11111111111111111111111101010010 (
#7211001
b0011001000000000000000010 #
b00000000000000000000001100100010 %
b0011001000000000000000010 &
b00000000000000000000001100100010 (
#7213001
b1100111000000000000011111 #
b11111111111111111111110011111111 %
b1100111000000000000011111 &
b11111111111111111111110011111111 (
#7314001
b0011110000000000000010110 #
b00000000000000000000001111010110 %
b0011110000000000000010110 &
b00000000000000000000001111010110 (
#7316001
b1110100000000000000000110 #
b11111111111111111111111010000110 %
b1110100000000000000000110 &
b11111111111111111111111010000110 (
#7417001
b0010000000000000000011111 #
b00000000000000000000001000011111 %
b0010000000000000000011111 &
b00000000000000000000001000011111 (
#7419001
b1101111000000000000001011 #
b11111111111111111111110111101011 %
b1101111000000000000001011 &
b11111111111111111111110111101011 (
#7520001
b0010010000000000000000100 #
b00000000000000000000001001000100 %
b0010010000000000000000100 &
b00000000000000000000001001000100 (
#7522001
b1111100000000000000000101 #
b11111111111111111111111110000101 %
b1111100000000000000000101 &
b11111111111111111111111110000101 (
#7623001
b0010100000000000000011111 #
b00000000000000000000001010011111 %
b0010100000000000000011111 &
b00000000000000000000001010011111 (
#7625001
b1001001000000000000010011 #
b11111111111111111111100100110011 %
b1001001000000000000010011 &
b11111111111111111111100100110011 (
#7726001
b0010101000000000000011101 #
b00000000000000000000001010111101 %
b0010101000000000000011101 &
b00000000000000000000001010111101 (
#7728001
b1110010000000000000000001 #
b11111111111111111111111001000001 %
b1110010000000000000000001 &
b11111111111111111111111001000001 (
#7829001
b0010000000000000000001111 #
b00000000000000000000001000001111 %
b0010000000000000000001111 &
b00000000000000000000001000001111 (
#7831001
b1011111000000000000011001 #
b11111111111111111111101111111001 %
b1011111000000000000011001 &
b11111111111111111111101111111001 (
#7932001
b0010001000000000000001011 #
b00000000000000000000001000101011 %
b0010001000000000000001011 &
b00000000000000000000001000101011 (
#7934001
b1111010000000000000001000 #
b11111111111111111111111101001000 %
b1111010000000000000001000 &
b11111111111111111111111101001000 (
#8035001
b0001001000000000000000000 #
b00000000000000000000000100100000 %
b0001001000000000000000000 &
b00000000000000000000000100100000 (
#8037001
b1110111000000000000001111 #
b11111111111111111111111011101111 %
b1110111000000000000001111 &
b11111111111111111111111011101111 (
#8138001
b0001001000000000000011010 #
b00000000000000000000000100111010 %
b0001001000000000000011010 &
b00000000000000000000000100111010 (
#8140001
b1001110000000000000010010 #
b11111111111111111111100111010010 %
b1001110000000000000010010 &
b11111111111111111111100111010010 (
#8241001
b0000000000000000000000011 #
b00000000000000000000000000000011 %
b0000000000000000000000011 &
b00000000000000000000000000000011 (
#8243001
b1000110000000000000011000 #
b11111111111111111111100011011000 %
b1000110000000000000011000 &
b11111111111111111111100011011000 (
#8344001
b0011001000000000000010110 #
b00000000000000000000001100110110 %
b0011001000000000000010110 &
b00000000000000000000001100110110 (
#8346001
b1000101000000000000011010 #
b11111111111111111111100010111010 %
b1000101000000000000011010 &
b11111111111111111111100010111010 (
#8447001
b0001011000000000000011000 #
b00000000000000000000000101111000 %
b0001011000000000000011000 &
b00000000000000000000000101111000 (
#8449001
b1001100000000000000001111 #
b11111111111111111111100110001111 %
b1001100000000000000001111 &
b11111111111111111111100110001111 (
#8550001
b0010110000000000000001100 #
b00000000000000000000001011001100 %
b0010110000000000000001100 &
b00000000000000000000001011001100 (
#8552001
b1100010000000000000010000 #
b11111111111111111111110001010000 %
b1100010000000000000010000 &
b11111111111111111111110001010000 (
#8653001
b0000000000000000000011011 #
b00000000000000000000000000011011 %
b0000000000000000000011011 &
b00000000000000000000000000011011 (
#8655001
b1110010000000000000010111 #
b11111111111111111111111001010111 %
b1110010000000000000010111 &
b11111111111111111111111001010111 (
#8756001
b0010000000000000000001011 #
b00000000000000000000001000001011 %
b0010000000000000000001011 &
b00000000000000000000001000001011 (
#8758001
b1110000000000000000001010 #
b11111111111111111111111000001010 %
b1110000000000000000001010 &
b11111111111111111111111000001010 (
#8859001
b0000001000000000000000111 #
b00000000000000000000000000100111 %
b0000001000000000000000111 &
b00000000000000000000000000100111 (
#8861001
b1100100000000000000001001 #
b11111111111111111111110010001001 %
b1100100000000000000001001 &
b11111111111111111111110010001001 (
#8962001
b0011001000000000000000101 #
b00000000000000000000001100100101 %
b0011001000000000000000101 &
b00000000000000000000001100100101 (
#8964001
b1011100000000000000001000 #
b11111111111111111111101110001000 %
b1011100000000000000001000 &
b11111111111111111111101110001000 (
#9065001
b0001001000000000000000100 #
b00000000000000000000000100100100 %
b0001001000000000000000100 &
b00000000000000000000000100100100 (
#9067001
b1100001000000000000000001 #
b11111111111111111111110000100001 %
b1100001000000000000000001 &
b11111111111111111111110000100001 (
#9168001
b0000100000000000000001100 #
b00000000000000000000000010001100 %
b0000100000000000000001100 &
b00000000000000000000000010001100 (
#9170001
b1101101000000000000010100 #
b11111111111111111111110110110100 %
b1101101000000000000010100 &
b11111111111111111111110110110100 (
#9271001
b0010110000000000000010111 #
b00000000000000000000001011010111 %
b0010110000000000000010111 &
b00000000000000000000001011010111 (
#9273001
b1011010000000000000001010 #
b11111111111111111111101101001010 %
b1011010000000000000001010 &
b11111111111111111111101101001010 (
#9374001
b0000110000000000000000010 #
b00000000000000000000000011000010 %
b0000110000000000000000010 &
b00000000000000000000000011000010 (
#9376001
b1100100000000000000011000 #
b11111111111111111111110010011000 %
b1100100000000000000011000 &
b11111111111111111111110010011000 (
#9477001
b0011101000000000000000100 #
b00000000000000000000001110100100 %
b0011101000000000000000100 &
b00000000000000000000001110100100 (
#9479001
b1011001000000000000011010 #
b11111111111111111111101100111010 %
b1011001000000000000011010 &
b11111111111111111111101100111010 (
#9580001
b0000001000000000000011111 #
b00000000000000000000000000111111 %
b0000001000000000000011111 &
b00000000000000000000000000111111 (
#9582001
b1001111000000000000000101 #
b11111111111111111111100111100101 %
b1001111000000000000000101 &
b11111111111111111111100111100101 (
#9683001
b0011011000000000000010110 #
b00000000000000000000001101110110 %
b0011011000000000000010110 &
b00000000000000000000001101110110 (
#9685001
b1100011000000000000011010 #
b11111111111111111111110001111010 %
b1100011000000000000011010 &
b11111111111111111111110001111010 (
#9786001
b0001010000000000000001100 #
b00000000000000000000000101001100 %
b0001010000000000000001100 &
b00000000000000000000000101001100 (
#9788001
b1110110000000000000011001 #
b11111111111111111111111011011001 %
b1110110000000000000011001 &
b11111111111111111111111011011001 (
#9889001
b0011000000000000000010001 #
b00000000000000000000001100010001 %
b0011000000000000000010001 &
b00000000000000000000001100010001 (
#9891001
b1100110000000000000010100 #
b11111111111111111111110011010100 %
b1100110000000000000010100 &
b11111111111111111111110011010100 (
#9992001
b0011101000000000000000101 #
b00000000000000000000001110100101 %
b0011101000000000000000101 &
b00000000000000000000001110100101 (
#9994001
b1100101000000000000010100 #
b11111111111111111111110010110100 %
b1100101000000000000010100 &
b11111111111111111111110010110100 (
#10095001
b0011100000000000000011010 #
b00000000000000000000001110011010 %
b0011100000000000000011010 &
b00000000000000000000001110011010 (
#10097001
b1111111000000000000010010 #
b11111111111111111111111111110010 %
b1111111000000000000010010 &
b11111111111111111111111111110010 (
#10198001
b0000100000000000000000111 #
b00000000000000000000000010000111 %
b0000100000000000000000111 &
b00000000000000000000000010000111 (
#10200001
b1100100000000000000010100 #
b11111111111111111111110010010100 %
b1100100000000000000010100 &
b11111111111111111111110010010100 (
#10301001
b0011001000000000000000010 #
b00000000000000000000001100100010 %
b0011001000000000000000010 &
b00000000000000000000001100100010 (
#10303001
b1011110000000000000000111 #
b11111111111111111111101111000111 %
b1011110000000000000000111 &
b11111111111111111111101111000111 (
#10405002
b0110011000000000000001110 #
b10 $
b00000000000000000000011001101110 %
b0110011000000000000001110 &
b10 '
b00000000000000000000011001101110 (
#10507002
b1101101000000000000010110 #
b11111111111111111111010110110110 %
b1101101000000000000010110 &
b11111111111111111111010110110110 (
#10609002
b0100110000000000000001100 #
b00000000000000000000010011001100 %
b0100110000000000000001100 &
b00000000000000000000010011001100 (
#10711002
b1110011000000000000010001 #
b11111111111111111111111001110000 %
b1110011000000000000010001 &
b11111111111111111111111001110000 (
#10813002
b0111011000000000000010001 #
b00000000000000000000111101110000 %
b0111011000000000000010001 &
b00000000000000000000111101110000 (
#10915002
b1000101000000000000000111 #
b11111111111111111111100010100110 %
b1000101000000000000000111 &
b11111111111111111111100010100110 (
#11017002
b0111101000000000000010110 #
b00000000000000000000011110110110 %
b0111101000000000000010110 &
b00000000000000000000011110110110 (
#11119002
b1101011000000000000001001 #
b11111111111111111111110101101000 %
b1101011000000000000001001 &
b11111111111111111111110101101000 (
#11221002
b0010110000000000000011010 #
b00000000000000000000001011011010 %
b0010110000000000000011010 &
b00000000000000000000001011011010 (
#11323002
b1100010000000000000010000 #
b11111111111111111111010001010000 %
b1100010000000000000010000 &
b11111111111111111111010001010000 (
#11425002
b0110010000000000000011100 #
b00000000000000000000011001011100 %
b0110010000000000000011100 &
b00000000000000000000011001011100 (
#11527002
b1110111000000000000010110 #
b11111111111111111111011011110110 %
b1110111000000000000010110 &
b11111111111111111111011011110110 (
#11629002
b0111110000000000000010110 #
b00000000000000000000011111010110 %
b0111110000000000000010110 &
b00000000000000000000011111010110 (
#11731002
b1101001000000000000001101 #
b11111111111111111111110100101100 %
b1101001000000000000001101 &
b11111111111111111111110100101100 (
#11833002
b0101101000000000000001011 #
b00000000000000000000110110101010 %
b0101101000000000000001011 &
b00000000000000000000110110101010 (
#11935002
b1010111000000000000010111 #
b11111111111111111111101011110110 %
b1010111000000000000010111 &
b11111111111111111111101011110110 (
#12037002
b0001110000000000000001110 #
b00000000000000000000000111001110 %
b0001110000000000000001110 &
b00000000000000000000000111001110 (
#12139002
b1110011000000000000011101 #
b11111111111111111111111001111100 %
b1110011000000000000011101 &
b11111111111111111111111001111100 (
#12241002
b0001010000000000000010001 #
b00000000000000000000100101010000 %
b0001010000000000000010001 &
b00000000000000000000100101010000 (
#12343002
b1010111000000000000001100 #
b11111111111111111111001011101100 %
b1010111000000000000001100 &
b11111111111111111111001011101100 (
#12445002
b0110011000000000000001101 #
b00000000000000000000111001101100 %
b0110011000000000000001101 &
b00000000000000000000111001101100 (
#12547002
b1110000000000000000011010 #
b11111111111111111111011000011010 %
b1110000000000000000011010 &
b11111111111111111111011000011010 (
#12649002
b0110010000000000000011011 #
b00000000000000000000111001011010 %
b0110010000000000000011011 &
b00000000000000000000111001011010 (
#12751002
b1111111000000000000000010 #
b11111111111111111111011111100010 %
b1111111000000000000000010 &
b11111111111111111111011111100010 (
#12853002
b0111111000000000000011100 #
b00000000000000000000011111111100 %
b0111111000000000000011100 &
b00000000000000000000011111111100 (
#12955002
b1100000000000000000010110 #
b11111111111111111111010000010110 %
b1100000000000000000010110 &
b11111111111111111111010000010110 (
