utype/src/alu.sv
// alu.sv
module alu (
    // IN
    input logic [2:0] alu_control,
    input logic [31:0] src1,
    input logic [31:0] src2,
    // OUT
    output logic [31:0] alu_result,
    output logic zero
);

always_comb begin
    case (alu_control)
    	// ADD +
        3'b000 : alu_result = src1 + src2;
	// AND &
	3'b010 : alu_result = src1 & src2;
	// OR |
	3'b011 : alu_result = src1 | src2;
	// SUB (rs1 - rs2), 2's compliment
        3'b001 : alu_result = src1 + (~src2 + 1'b1);
        default: alu_result = 32'b0;
    endcase
end

assign zero = alu_result == 32'b0;
    
endmodule

utype/tb/alu/dump.vcd
$version Generated by VerilatedVcd $end
$timescale 1ps $end
 $scope module $rootio $end
  $var wire 3 # alu_control [2:0] $end
  $var wire 32 $ src1 [31:0] $end
  $var wire 32 % src2 [31:0] $end
  $var wire 32 & alu_result [31:0] $end
  $var wire 1 ' zero $end
 $upscope $end
 $scope module alu $end
  $var wire 3 ( alu_control [2:0] $end
  $var wire 32 ) src1 [31:0] $end
  $var wire 32 * src2 [31:0] $end
  $var wire 32 + alu_result [31:0] $end
  $var wire 1 , zero $end
 $upscope $end
$enddefinitions $end


#0
b000 #
b00000000000000000000000000000000 $
b00000000000000000000000000000000 %
b00000000000000000000000000000000 &
1'
b000 (
b00000000000000000000000000000000 )
b00000000000000000000000000000000 *
b00000000000000000000000000000000 +
1,
#1000
b01101111000100100011111100100011 $
b01010001111100010100100111001000 %
b11000001000000111000100011101011 &
0'
b01101111000100100011111100100011 )
b01010001111100010100100111001000 *
b11000001000000111000100011101011 +
0,
#2000
b01100011001110111101100001011011 $
b11110000100101000011110101111100 %
b01010011110100000001010111010111 &
b01100011001110111101100001011011 )
b11110000100101000011110101111100 *
b01010011110100000001010111010111 +
#3000
b00011010010111011000010001011000 $
b11110101101110011111011101111010 %
b00010000000101110111101111010010 &
b00011010010111011000010001011000 )
b11110101101110011111011101111010 *
b00010000000101110111101111010010 +
#4000
b10101001110101111111011011011100 $
b00101010100110010011011001110001 %
b11010100011100010010110101001101 &
b10101001110101111111011011011100 )
b00101010100110010011011001110001 *
b11010100011100010010110101001101 +
#5000
b11011010001100010000010101000010 $
b00001100110110010111001010101110 %
b11100111000010100111011111110000 &
b11011010001100010000010101000010 )
b00001100110110010111001010101110 *
b11100111000010100111011111110000 +
#6000
b00001111010111111010010101000111 $
b10111001010110001000101001101010 %
b11001000101110000010111110110001 &
b00001111010111111010010101000111 )
b10111001010110001000101001101010 *
b11001000101110000010111110110001 +
#7000
b10100000100100110111000001101010 $
b11100001011110110001001101110100 %
b10000010000011101000001111011110 &
b10100000100100110111000001101010 )
b11100001011110110001001101110100 *
b10000010000011101000001111011110 +
#8000
b01101111001001101001000001000000 $
b11101010101110000010100100010001 %
b01011001110111101011100101010001 &
b01101111001001101001000001000000 )
b11101010101110000010100100010001 *
b01011001110111101011100101010001 +
#9000
b11010100010001100111001011000011 $
b01010001010000010101001001011001 %
b00100101100001111100010100011100 &
b11010100010001100111001011000011 )
b01010001010000010101001001011001 *
b00100101100001111100010100011100 +
#10000
b11010101110010100111101110010110 $
b11100000111111001111000001111101 %
b10110110110001110110110000010011 &
b11010101110010100111101110010110 )
b11100000111111001111000001111101 *
b10110110110001110110110000010011 +
#11000
b01001111101001101101100101000000 $
b00111001111001001001010010110110 %
b10001001100010110110110111110110 &
b01001111101001101101100101000000 )
b00111001111001001001010010110110 *
b10001001100010110110110111110110 +
#12000
b00100000010001100101001100001011 $
b11111100010101101001100000011010 %
b00011100100111001110101100100101 &
b00100000010001100101001100001011 )
b11111100010101101001100000011010 *
b00011100100111001110101100100101 +
#13000
b11000111000100110001101101111010 $
b01001100111010010010010111001010 %
b00010011111111000100000101000100 &
b11000111000100110001101101111010 )
b01001100111010010010010111001010 *
b00010011111111000100000101000100 +
#14000
b00110110101110110111101010011110 $
b00000111100000110110011100111000 %
b00111110001111101110000111010110 &
b00110110101110110111101010011110 )
b00000111100000110110011100111000 *
b00111110001111101110000111010110 +
#15000
b01110101100010011100101001101100 $
b01010010111010011010000100111011 %
b11001000011100110110101110100111 &
b01110101100010011100101001101100 )
b01010010111010011010000100111011 *
b11001000011100110110101110100111 +
#16000
b01010001001000111110011100110011 $
b00011111100001101110000101011001 %
b01110000101010101100100010001100 &
b01010001001000111110011100110011 )
b00011111100001101110000101011001 *
b01110000101010101100100010001100 +
#17000
b01101000111101011011100001001000 $
b10010000011100000110000111111010 %
b11111001011001100001101001000010 &
b01101000111101011011100001001000 )
b10010000011100000110000111111010 *
b11111001011001100001101001000010 +
#18000
b11100001000101111000100000100110 $
b00100110110000100001100010001100 %
b00000111110110011010000010110010 &
b11100001000101111000100000100110 )
b00100110110000100001100010001100 *
b00000111110110011010000010110010 +
#19000
b00000001001110000011011100101010 $
b11100100001011010000011110111101 %
b11100101011001010011111011100111 &
b00000001001110000011011100101010 )
b11100100001011010000011110111101 *
b11100101011001010011111011100111 +
#20000
b10110100011111001011111100110101 $
b00101001110101101011001111100110 %
b11011110010100110111001100011011 &
b10110100011111001011111100110101 )
b00101001110101101011001111100110 *
b11011110010100110111001100011011 +
#21000
b11000010011111100111000101101010 $
b10101010010001010001000101110010 %
b01101100110000111000001011011100 &
b11000010011111100111000101101010 )
b10101010010001010001000101110010 *
b01101100110000111000001011011100 +
#22000
b10100100000000010100100001011001 $
b00101011010111010010100001011100 %
b11001111010111100111000010110101 &
b10100100000000010100100001011001 )
b00101011010111010010100001011100 *
b11001111010111100111000010110101 +
#23000
b00011001010000010011011000101011 $
b10011101111100000100010111000111 %
b10110111001100010111101111110010 &
b00011001010000010011011000101011 )
b10011101111100000100010111000111 *
b10110111001100010111101111110010 +
#24000
b00011100001100000111100010100000 $
b10100100010101000011010001110101 %
b11000000100001001010110100010101 &
b00011100001100000111100010100000 )
b10100100010101000011010001110101 *
b11000000100001001010110100010101 +
#25000
b01011001000010110010101011011011 $
b00010111101111100010110110011110 %
b01110000110010010101100001111001 &
b01011001000010110010101011011011 )
b00010111101111100010110110011110 *
b01110000110010010101100001111001 +
#26000
b01000000110001111111101011110000 $
b11100000001000001101101110000101 %
b00100000111010001101011001110101 &
b01000000110001111111101011110000 )
b11100000001000001101101110000101 *
b00100000111010001101011001110101 +
#27000
b01111100000110001010011110010000 $
b00110001000101101101101110100010 %
b10101101001011111000001100110010 &
b01111100000110001010011110010000 )
b00110001000101101101101110100010 *
b10101101001011111000001100110010 +
#28000
b01100011011111010000011000000101 $
b01000000111110011000010000101000 %
b10100100011101101000101000101101 &
b01100011011111010000011000000101 )
b01000000111110011000010000101000 *
b10100100011101101000101000101101 +
#29000
b01111001011101010110101100000000 $
b10110100011110111100010101111010 %
b00101101111100010011000001111010 &
b01111001011101010110101100000000 )
b10110100011110111100010101111010 *
b00101101111100010011000001111010 +
#30000
b01110111010100000101011000001010 $
b11111010100010001001011101000111 %
b01110001110110001110110101010001 &
b01110111010100000101011000001010 )
b11111010100010001001011101000111 *
b01110001110110001110110101010001 +
#31000
b11011101110100011111000011110111 $
b11110000100011001011100111010110 %
b11001110010111101010101011001101 &
b11011101110100011111000011110111 )
b11110000100011001011100111010110 *
b11001110010111101010101011001101 +
#32000
b01011110110000101110010001010001 $
b01001100101011001000111001110101 %
b10101011011011110111001011000110 &
b01011110110000101110010001010001 )
b01001100101011001000111001110101 *
b10101011011011110111001011000110 +
#33000
b10010010011101001001010010110011 $
b01100011101101011000001111010101 %
b11110110001010100001100010001000 &
b10010010011101001001010010110011 )
b01100011101101011000001111010101 *
b11110110001010100001100010001000 +
#34000
b10010101010011101000110010110100 $
b11010010010010010011111011011010 %
b01100111100101111100101110001110 &
b10010101010011101000110010110100 )
b11010010010010010011111011011010 *
b01100111100101111100101110001110 +
#35000
b01000010011100000110110000100001 $
b01001111100110000110110010110101 %
b10010010000010001101100011010110 &
b01000010011100000110110000100001 )
b01001111100110000110110010110101 *
b10010010000010001101100011010110 +
#36000
b00111010111111100101101010100100 $
b10011100011101011001011111100011 %
b11010111011100111111001010000111 &
b00111010111111100101101010100100 )
b10011100011101011001011111100011 *
b11010111011100111111001010000111 +
#37000
b11100010010111111010011110011010 $
b11000011110111111100011000011001 %
b10100110001111110110110110110011 &
b11100010010111111010011110011010 )
b11000011110111111100011000011001 *
b10100110001111110110110110110011 +
#38000
b01111110000001100000111111110001 $
b11000001111111100010011100001111 %
b01000000000001000011011100000000 &
b01111110000001100000111111110001 )
b11000001111111100010011100001111 *
b01000000000001000011011100000000 +
#39000
b00010000011111110101100101100000 $
b00101000110111111100111000010101 %
b00111001010111110010011101110101 &
b00010000011111110101100101100000 )
b00101000110111111100111000010101 *
b00111001010111110010011101110101 +
#40000
b01111111100001100010100000011000 $
b11010110010011001110111010001111 %
b01010101110100110001011010100111 &
b01111111100001100010100000011000 )
b11010110010011001110111010001111 *
b01010101110100110001011010100111 +
#41000
b00110001001000101110101110100011 $
b11001011101010001001001001111000 %
b11111100110010110111111000011011 &
b00110001001000101110101110100011 )
b11001011101010001001001001111000 *
b11111100110010110111111000011011 +
#42000
b00010110111111000110000101111001 $
b01110101110011011000011100000011 %
b10001100110010011110100001111100 &
b00010110111111000110000101111001 )
b01110101110011011000011100000011 *
b10001100110010011110100001111100 +
#43000
b10000101000000100111011101000001 $
b00000011100001111111101000100111 %
b10001000100010100111000101101000 &
b10000101000000100111011101000001 )
b00000011100001111111101000100111 *
b10001000100010100111000101101000 +
#44000
b10111101011100010111100111101001 $
b10110110111101111001001111001100 %
b01110100011010010000110110110101 &
b10111101011100010111100111101001 )
b10110110111101111001001111001100 *
b01110100011010010000110110110101 +
#45000
b00011011011111001110110011110001 $
b01100011110001101001100110001101 %
b01111111010000111000011001111110 &
b00011011011111001110110011110001 )
b01100011110001101001100110001101 *
b01111111010000111000011001111110 +
#46000
b00110011111001100001000100110111 $
b00000000101001000100100011010001 %
b00110100100010100101101000001000 &
b00110011111001100001000100110111 )
b00000000101001000100100011010001 *
b00110100100010100101101000001000 +
#47000
b10010111111000111101000000001000 $
b00000010110101101101001001110011 %
b10011010101110101010001001111011 &
b10010111111000111101000000001000 )
b00000010110101101101001001110011 *
b10011010101110101010001001111011 +
#48000
b11101011110001010001100110011010 $
b11011010000101000000110011100011 %
b11000101110110010010011001111101 &
b11101011110001010001100110011010 )
b11011010000101000000110011100011 *
b11000101110110010010011001111101 +
#49000
b00001111010001011111110000001110 $
b11100001010001100100101101000110 %
b11110000100011000100011101010100 &
b00001111010001011111110000001110 )
b11100001010001100100101101000110 *
b11110000100011000100011101010100 +
#50000
b00100100001110101000101011010010 $
b11001010100111100001111111001111 %
b11101110110110001010101010100001 &
b00100100001110101000101011010010 )
b11001010100111100001111111001111 *
b11101110110110001010101010100001 +
#51000
b01000010011101101001000011110001 $
b00000111111101000000010110101100 %
b01001010011010101001011010011101 &
b01000010011101101001000011110001 )
b00000111111101000000010110101100 *
b01001010011010101001011010011101 +
#52000
b00000010001111011010011010100011 $
b10111110001101001100101101101101 %
b11000000011100100111001000010000 &
b00000010001111011010011010100011 )
b10111110001101001100101101101101 *
b11000000011100100111001000010000 +
#53000
b00110100011010011101100110001101 $
b00110001110001111111111110100110 %
b01100110001100011101100100110011 &
b00110100011010011101100110001101 )
b00110001110001111111111110100110 *
b01100110001100011101100100110011 +
#54000
b00011110011110110111100101011100 $
b11110000100001111011001010110100 %
b00001111000000110010110000010000 &
b00011110011110110111100101011100 )
b11110000100001111011001010110100 *
b00001111000000110010110000010000 +
#55000
b01110101010000000111011101111101 $
b01000100111110110000011000101101 %
b10111010001110110111110110101010 &
b01110101010000000111011101111101 )
b01000100111110110000011000101101 *
b10111010001110110111110110101010 +
#56000
b01011101001110000011010100111110 $
b10010000000110111001101011000111 %
b11101101010100111101000000000101 &
b01011101001110000011010100111110 )
b10010000000110111001101011000111 *
b11101101010100111101000000000101 +
#57000
b01100111101101010011010010110101 $
b00100000001100010110001010101110 %
b10000111111001101001011101100011 &
b01100111101101010011010010110101 )
b00100000001100010110001010101110 *
b10000111111001101001011101100011 +
#58000
b01010011000100101000011101101100 $
b01011010001111010100100100101000 %
b10101101010011111101000010010100 &
b01010011000100101000011101101100 )
b01011010001111010100100100101000 *
b10101101010011111101000010010100 +
#59000
b10101100010111111000111010000001 $
b00100100000110011010110110111111 %
b11010000011110010011110001000000 &
b10101100010111111000111010000001 )
b00100100000110011010110110111111 *
b11010000011110010011110001000000 +
#60000
b01001000101111001110001000100001 $
b10110111101011010110001100111101 %
b00000000011010100100010101011110 &
b01001000101111001110001000100001 )
b10110111101011010110001100111101 *
b00000000011010100100010101011110 +
#61000
b01110010000001011100000100111110 $
b10110010100010001011011000011101 %
b00100100100011100111011101011011 &
b01110010000001011100000100111110 )
b10110010100010001011011000011101 *
b00100100100011100111011101011011 +
#62000
b10011011110010010101101100011011 $
b11100010101011000110000111101111 %
b01111110011101011011110100001010 &
b10011011110010010101101100011011 )
b11100010101011000110000111101111 *
b01111110011101011011110100001010 +
#63000
b11100011101011011011000011001011 $
b10111011011101111111001010110001 %
b10011111001001011010001101111100 &
b11100011101011011011000011001011 )
b10111011011101111111001010110001 *
b10011111001001011010001101111100 +
#64000
b11000101011100000010010100010001 $
b00111100110011111010011001011010 %
b00000010001111111100101101101011 &
b11000101011100000010010100010001 )
b00111100110011111010011001011010 *
b00000010001111111100101101101011 +
#65000
b01000001011101010111010111101001 $
b01000011101011000111001010001100 %
b10000101001000011110100001110101 &
b01000001011101010111010111101001 )
b01000011101011000111001010001100 *
b10000101001000011110100001110101 +
#66000
b01111010001110001100001000110111 $
b11110111101011011101110010111011 %
b01110001111001101001111011110010 &
b01111010001110001100001000110111 )
b11110111101011011101110010111011 *
b01110001111001101001111011110010 +
#67000
b00111110011000011100100000001011 $
b00011000000010100111101110111000 %
b01010110011011000100001111000011 &
b00111110011000011100100000001011 )
b00011000000010100111101110111000 *
b01010110011011000100001111000011 +
#68000
b00000101110100000011011100100110 $
b00011010001000001000111100000101 %
b00011111111100001100011000101011 &
b00000101110100000011011100100110 )
b00011010001000001000111100000101 *
b00011111111100001100011000101011 +
#69000
b00111011001000000111101101100111 $
b11000010111101001100110011010111 %
b11111110000101010100100000111110 &
b00111011001000000111101101100111 )
b11000010111101001100110011010111 *
b11111110000101010100100000111110 +
#70000
b00000000001110111001011011001010 $
b01010110000010111011100010000000 %
b01010110010001110100111101001010 &
b00000000001110111001011011001010 )
b01010110000010111011100010000000 *
b01010110010001110100111101001010 +
#71000
b01100010110001001010110101001110 $
b00011001110000111010110000110010 %
b01111100100010000101100110000000 &
b01100010110001001010110101001110 )
b00011001110000111010110000110010 *
b01111100100010000101100110000000 +
#72000
b01010110110110100001101100101000 $
b11010001110110111000001101111100 %
b00101000101101011001111010100100 &
b01010110110110100001101100101000 )
b11010001110110111000001101111100 *
b00101000101101011001111010100100 +
#73000
b01000011111100101111110101001001 $
b10101111011001110000000010101111 %
b11110011010110011111110111111000 &
b01000011111100101111110101001001 )
b10101111011001110000000010101111 *
b11110011010110011111110111111000 +
#74000
b01110010101001101001010010111010 $
b11001010010110111101101010001100 %
b00111101000000100110111101000110 &
b01110010101001101001010010111010 )
b11001010010110111101101010001100 *
b00111101000000100110111101000110 +
#75000
b11011011011001001000111010010001 $
b01000011110110000101001101010011 %
b00011111001111001110000111100100 &
b11011011011001001000111010010001 )
b01000011110110000101001101010011 *
b00011111001111001110000111100100 +
#76000
b00110110010011000000011100001010 $
b11101101001010000101111001000101 %
b00100011011101000110010101001111 &
b00110110010011000000011100001010 )
b11101101001010000101111001000101 *
b00100011011101000110010101001111 +
#77000
b01101010100100110110011010011100 $
b00001110100000110001111111100001 %
b01111001000101101000011001111101 &
b01101010100100110110011010011100 )
b00001110100000110001111111100001 *
b01111001000101101000011001111101 +
#78000
b10110000000010110011110100010110 $
b10000010100100011111000000110111 %
b00110010100111010010110101001101 &
b10110000000010110011110100010110 )
b10000010100100011111000000110111 *
b00110010100111010010110101001101 +
#79000
b01110010011110101001000101101000 $
b01110000101010101000010110101100 %
b11100011001001010001011100010100 &
b01110010011110101001000101101000 )
b01110000101010101000010110101100 *
b11100011001001010001011100010100 +
#80000
b00111100110111101011100000000011 $
b11010111101111000101000001000101 %
b00010100100110110000100001001000 &
b00111100110111101011100000000011 )
b11010111101111000101000001000101 *
b00010100100110110000100001001000 +
#81000
b00000010101100111110100001111000 $
b01100111100100001110100100010100 %
b01101010010001001101000110001100 &
b00000010101100111110100001111000 )
b01100111100100001110100100010100 *
b01101010010001001101000110001100 +
#82000
b10110100000101111000100101100000 $
b11010111110100011001011110110100 %
b10001011111010010010000100010100 &
b10110100000101111000100101100000 )
b11010111110100011001011110110100 *
b10001011111010010010000100010100 +
#83000
b01010010110100100111110001011100 $
b10010001010100000010001101101100 %
b11100100001000101001111111001000 &
b01010010110100100111110001011100 )
b10010001010100000010001101101100 *
b11100100001000101001111111001000 +
#84000
b00110101111001101010111111001110 $
b01100111011000100000000011010001 %
b10011101010010001011000010011111 &
b00110101111001101010111111001110 )
b01100111011000100000000011010001 *
b10011101010010001011000010011111 +
#85000
b01011101101110110110001000010110 $
b01011101110011010111110110010011 %
b10111011100010001101111110101001 &
b01011101101110110110001000010110 )
b01011101110011010111110110010011 *
b10111011100010001101111110101001 +
#86000
b00010011110000110011010110011000 $
b00110111110110001101101000110001 %
b01001011100111000000111111001001 &
b00010011110000110011010110011000 )
b00110111110110001101101000110001 *
b01001011100111000000111111001001 +
#87000
b10010010000000110101101010001011 $
b00001011110111100011011000000101 %
b10011101111000011001000010010000 &
b10010010000000110101101010001011 )
b00001011110111100011011000000101 *
b10011101111000011001000010010000 +
#88000
b10111110011000110101111101011010 $
b11001111101101110000110110001001 %
b10001110000110100110110011100011 &
b10111110011000110101111101011010 )
b11001111101101110000110110001001 *
b10001110000110100110110011100011 +
#89000
b01110100110100111100000100101110 $
b00100001001011001111001100101010 %
b10010110000000001011010001011000 &
b01110100110100111100000100101110 )
b00100001001011001111001100101010 *
b10010110000000001011010001011000 +
#90000
b00001111010101100010111011000010 $
b00010011110100001001000011011011 %
b00100011001001101011111110011101 &
b00001111010101100010111011000010 )
b00010011110100001001000011011011 *
b00100011001001101011111110011101 +
#91000
b10100000110011001001110111110111 $
b10001100000001100011001010111100 %
b00101100110100101101000010110011 &
b10100000110011001001110111110111 )
b10001100000001100011001010111100 *
b00101100110100101101000010110011 +
#92000
b10011010011010010011010110111110 $
b10111111001100100010011111001111 %
b01011001100110110101110110001101 &
b10011010011010010011010110111110 )
b10111111001100100010011111001111 *
b01011001100110110101110110001101 +
#93000
b11000010100110111100010011001000 $
b00110010010011001100000100001001 %
b11110100111010001000010111010001 &
b11000010100110111100010011001000 )
b00110010010011001100000100001001 *
b11110100111010001000010111010001 +
#94000
b10101000111000000110000010101100 $
b10010101111010000110000110011010 %
b00111110110010001100001001000110 &
b10101000111000000110000010101100 )
b10010101111010000110000110011010 *
b00111110110010001100001001000110 +
#95000
b00011110011101001101001101001111 $
b01000101010011101011110101111000 %
b01100011110000111001000011000111 &
b00011110011101001101001101001111 )
b01000101010011101011110101111000 *
b01100011110000111001000011000111 +
#96000
b01001001101101100011000110000001 $
b11010100111100001101011000100111 %
b00011110101001110000011110101000 &
b01001001101101100011000110000001 )
b11010100111100001101011000100111 *
b00011110101001110000011110101000 +
#97000
b10111000101101001011011001010101 $
b10100001110011000110001000100110 %
b01011010100000010001100001111011 &
b10111000101101001011011001010101 )
b10100001110011000110001000100110 *
b01011010100000010001100001111011 +
#98000
b00111101111100111010011011110111 $
b01000101010111011011000111011111 %
b10000011010100010101100011010110 &
b00111101111100111010011011110111 )
b01000101010111011011000111011111 *
b10000011010100010101100011010110 +
#99000
b01011000011111101101101010010110 $
b10010101001100011110111110001000 %
b11101101101100001100101000011110 &
b01011000011111101101101010010110 )
b10010101001100011110111110001000 *
b11101101101100001100101000011110 +
#100000
b01100000110100101111010100010100 $
b11000000001111011010000010010101 %
b00100001000100001001010110101001 &
b01100000110100101111010100010100 )
b11000000001111011010000010010101 *
b00100001000100001001010110101001 +
#101000
b11100001111111011101100011110000 $
b00100110110011000111101010111011 %
b00001000110010100101001110101011 &
b11100001111111011101100011110000 )
b00100110110011000111101010111011 *
b00001000110010100101001110101011 +
#102000
b00100110001110111011010011111011 $
b00110000111011100000010001011001 %
b01010111001010011011100101010100 &
b00100110001110111011010011111011 )
b00110000111011100000010001011001 *
b01010111001010011011100101010100 +
#103000
b11111001011000110011111101011011 $
b11100001000001000001000110010000 %
b11011010011001110101000011101011 &
b11111001011000110011111101011011 )
b11100001000001000001000110010000 *
b11011010011001110101000011101011 +
#104000
b11100100010010010100111110001001 $
b11010010110111100010100101011101 %
b10110111001001110111100011100110 &
b11100100010010010100111110001001 )
b11010010110111100010100101011101 *
b10110111001001110111100011100110 +
#105000
b10101101000010000110010010100011 $
b10110110010100110101000110010011 %
b01100011010110111011011000110110 &
b10101101000010000110010010100011 )
b10110110010100110101000110010011 *
b01100011010110111011011000110110 +
#106000
b01111000000001011110011010010110 $
b00011110000100111001010111111110 %
b10010110000110010111110010010100 &
b01111000000001011110011010010110 )
b00011110000100111001010111111110 *
b10010110000110010111110010010100 +
#107000
b01001100111001100100000001110110 $
b00110001100000000001010011111101 %
b01111110011001100101010101110011 &
b01001100111001100100000001110110 )
b00110001100000000001010011111101 *
b01111110011001100101010101110011 +
#108000
b00001010100100000111111111111010 $
b00100011001010010010100100111011 %
b00101101101110011010100100110101 &
b00001010100100000111111111111010 )
b00100011001010010010100100111011 *
b00101101101110011010100100110101 +
#109000
b10101101100101101111101110110010 $
b00100110001011100011000111101110 %
b11010011110001010010110110100000 &
b10101101100101101111101110110010 )
b00100110001011100011000111101110 *
b11010011110001010010110110100000 +
#110000
b01001111011010101101011101111001 $
b00000111101111110100001101000011 %
b01010111001010100001101010111100 &
b01001111011010101101011101111001 )
b00000111101111110100001101000011 *
b01010111001010100001101010111100 +
#111000
b11011111110000011001001010010111 $
b01111111001101110000011101010110 %
b01011110111110001001100111101101 &
b11011111110000011001001010010111 )
b01111111001101110000011101010110 *
b01011110111110001001100111101101 +
#112000
b10011111100111111000010010101010 $
b01111011000011100000011000000010 %
b00011010101011011000101010101100 &
b10011111100111111000010010101010 )
b01111011000011100000011000000010 *
b00011010101011011000101010101100 +
#113000
b10111101110111001000001001110010 $
b10100110101111000001001101011011 %
b01100100100110001001010111001101 &
b10111101110111001000001001110010 )
b10100110101111000001001101011011 *
b01100100100110001001010111001101 +
#114000
b10110100111100100100110010100011 $
b10100011000100101000011101001010 %
b01011000000001001101001111101101 &
b10110100111100100100110010100011 )
b10100011000100101000011101001010 *
b01011000000001001101001111101101 +
#115000
b10011011101010010001111000001100 $
b10011010110000110111110101101101 %
b00110110011011001001101101111001 &
b10011011101010010001111000001100 )
b10011010110000110111110101101101 *
b00110110011011001001101101111001 +
#116000
b11000101010111110100100011011000 $
b10100000001011010110101000101101 %
b01100101100011001011001100000101 &
b11000101010111110100100011011000 )
b10100000001011010110101000101101 *
b01100101100011001011001100000101 +
#117000
b11101101111001100100010000101010 $
b10111010011000001110110001010011 %
b10101000010001110011000001111101 &
b11101101111001100100010000101010 )
b10111010011000001110110001010011 *
b10101000010001110011000001111101 +
#118000
b10111111001101010110101011000000 $
b10100110000101111010110000111011 %
b01100101010011010001011011111011 &
b10111111001101010110101011000000 )
b10100110000101111010110000111011 *
b01100101010011010001011011111011 +
#119000
b01101101101001110110001000000101 $
b01100001010001001011010101100111 %
b11001110111011000001011101101100 &
b01101101101001110110001000000101 )
b01100001010001001011010101100111 *
b11001110111011000001011101101100 +
#120000
b10000011101100000011100000110110 $
b00011011100001000110110110101100 %
b10011111001101001010010111100010 &
b10000011101100000011100000110110 )
b00011011100001000110110110101100 *
b10011111001101001010010111100010 +
#121000
b11000101011000000100001111001100 $
b11011100110000000011001001111001 %
b10100010001000000111011001000101 &
b11000101011000000100001111001100 )
b11011100110000000011001001111001 *
b10100010001000000111011001000101 +
#122000
b00101001000111000011010100010111 $
b10100011101011000000110111101110 %
b11001100110010000100001100000101 &
b00101001000111000011010100010111 )
b10100011101011000000110111101110 *
b11001100110010000100001100000101 +
#123000
b10111010111101011111001001000101 $
b00110010011111010011110000111100 %
b11101101011100110010111010000001 &
b10111010111101011111001001000101 )
b00110010011111010011110000111100 *
b11101101011100110010111010000001 +
#124000
b11100110101101000101111110100001 $
b01011011010110101010010100010010 %
b01000010000011110000010010110011 &
b11100110101101000101111110100001 )
b01011011010110101010010100010010 *
b01000010000011110000010010110011 +
#125000
b00100100111001110011011101010101 $
b11011010001000011101000101010100 %
b11111111000010010000100010101001 &
b00100100111001110011011101010101 )
b11011010001000011101000101010100 *
b11111111000010010000100010101001 +
#126000
b11010000110111000010011100000100 $
b11100111111101111011111000110111 %
b10111000110100111110010100111011 &
b11010000110111000010011100000100 )
b11100111111101111011111000110111 *
b10111000110100111110010100111011 +
#127000
b00100010101010010010110010111100 $
b11100000011000010100010011011110 %
b00000011000010100111000110011010 &
b00100010101010010010110010111100 )
b11100000011000010100010011011110 *
b00000011000010100111000110011010 +
#128000
b01010000010110110110101010010111 $
b01111010100101100100111111000010 %
b11001010111100011011101001011001 &
b01010000010110110110101010010111 )
b01111010100101100100111111000010 *
b11001010111100011011101001011001 +
#129000
b01111000000101101101110110110001 $
b10010011110011000001010110010000 %
b00001011111000101111001101000001 &
b01111000000101101101110110110001 )
b10010011110011000001010110010000 *
b00001011111000101111001101000001 +
#130000
b11101000000101011111000001110101 $
b00000000111000100111100100110100 %
b11101000111110000110100110101001 &
b11101000000101011111000001110101 )
b00000000111000100111100100110100 *
b11101000111110000110100110101001 +
#131000
b11001111100000000000010100001110 $
b11110000111100110011000001011110 %
b11000000011100110011010101101100 &
b11001111100000000000010100001110 )
b11110000111100110011000001011110 *
b11000000011100110011010101101100 +
#132000
b01010000110010101111001010001110 $
b01100111011000011101110001011010 %
b10111000001011001100111011101000 &
b01010000110010101111001010001110 )
b01100111011000011101110001011010 *
b10111000001011001100111011101000 +
#133000
b01000110000001100110000110101010 $
b00000101011110011101000001001101 %
b01001011100000000011000111110111 &
b01000110000001100110000110101010 )
b00000101011110011101000001001101 *
b01001011100000000011000111110111 +
#134000
b10110111011010110101110110100001 $
b00000100111000100000111101101010 %
b10111100010011010110110100001011 &
b10110111011010110101110110100001 )
b00000100111000100000111101101010 *
b10111100010011010110110100001011 +
#135000
b10001001110111010100010100001011 $
b10100010011011100000001101010010 %
b00101100010010110100100001011101 &
b10001001110111010100010100001011 )
b10100010011011100000001101010010 *
b00101100010010110100100001011101 +
#136000
b00011001000111011101111100101001 $
b00110110001000110111001101010111 %
b01001111010000010101001010000000 &
b00011001000111011101111100101001 )
b00110110001000110111001101010111 *
b01001111010000010101001010000000 +
#137000
b10011011000010001101011110010000 $
b11110000101110010100101001111100 %
b10001011110000100010001000001100 &
b10011011000010001101011110010000 )
b11110000101110010100101001111100 *
b10001011110000100010001000001100 +
#138000
b10100011000101110101100011000000 $
b10101000101110001100001001111010 %
b01001011110100000001101100111010 &
b10100011000101110101100011000000 )
b10101000101110001100001001111010 *
b01001011110100000001101100111010 +
#139000
b11100101011100010000001001101111 $
b01011010010010011110101101101110 %
b00111111101110101110110111011101 &
b11100101011100010000001001101111 )
b01011010010010011110101101101110 *
b00111111101110101110110111011101 +
#140000
b10111000101101101010001111000100 $
b11111110110011001010000100101010 %
b10110111100000110100010011101110 &
b10111000101101101010001111000100 )
b11111110110011001010000100101010 *
b10110111100000110100010011101110 +
#141000
b11111011111011011011010011011010 $
b01110100110110010111010000001101 %
b01110000110001110010100011100111 &
b11111011111011011011010011011010 )
b01110100110110010111010000001101 *
b01110000110001110010100011100111 +
#142000
b11011000100100010101111101001101 $
b01010110101000010011100111011010 %
b00101111001100101001100100100111 &
b11011000100100010101111101001101 )
b01010110101000010011100111011010 *
b00101111001100101001100100100111 +
#143000
b10000100000111100110011100011000 $
b01111110000111001110001010101101 %
b00000010001110110100100111000101 &
b10000100000111100110011100011000 )
b01111110000111001110001010101101 *
b00000010001110110100100111000101 +
#144000
b10101111001111110100001111000001 $
b01101001011110000001011100011111 %
b00011000101101110101101011100000 &
b10101111001111110100001111000001 )
b01101001011110000001011100011111 *
b00011000101101110101101011100000 +
#145000
b00001010101000101101001000001110 $
b00001111000101100101000100000111 %
b00011001101110010010001100010101 &
b00001010101000101101001000001110 )
b00001111000101100101000100000111 *
b00011001101110010010001100010101 +
#146000
b11000010100110010001101010100100 $
b11011100100000111000100001001010 %
b10011111000111001010001011101110 &
b11000010100110010001101010100100 )
b11011100100000111000100001001010 *
b10011111000111001010001011101110 +
#147000
b01111001110100000001100010100100 $
b11011101111000111001011110110100 %
b01010111101100111011000001011000 &
b01111001110100000001100010100100 )
b11011101111000111001011110110100 *
b01010111101100111011000001011000 +
#148000
b10011011000110011000110011101100 $
b00111011000001110111010010101000 %
b11010110001000010000000110010100 &
b10011011000110011000110011101100 )
b00111011000001110111010010101000 *
b11010110001000010000000110010100 +
#149000
b01001110001000010111111010110010 $
b11101100111011100010011010100011 %
b00111011000011111010010101010101 &
b01001110001000010111111010110010 )
b11101100111011100010011010100011 *
b00111011000011111010010101010101 +
#150000
b01011000100000100011111011111110 $
b10010011000110011010010111100000 %
b11101011100110111110010011011110 &
b01011000100000100011111011111110 )
b10010011000110011010010111100000 *
b11101011100110111110010011011110 +
#151000
b10111101110011000010101010110001 $
b00111110111010110011011010011110 %
b11111100101101110110000101001111 &
b10111101110011000010101010110001 )
b00111110111010110011011010011110 *
b11111100101101110110000101001111 +
#152000
b01101011100101000001010010101010 $
b01010100101000101101101101000100 %
b11000000001101101110111111101110 &
b01101011100101000001010010101010 )
b01010100101000101101101101000100 *
b11000000001101101110111111101110 +
