Rtype_and_or/src/alu.sv
// alu.sv
module alu (
    // IN
    input logic [2:0] alu_control,
    input logic [31:0] src1,
    input logic [31:0] src2,
    // OUT
    output logic [31:0] alu_result,
    output logic zero
);

always_comb begin
    case (alu_control)
    	// ADD +
        3'b000 : alu_result = src1 + src2;
	// AND &
	3'b010 : alu_result = src1 & src2;
	// OR |
	3'b011 : alu_result = src1 | src2;
        default: alu_result = 32'b0;
    endcase
end

assign zero = alu_result == 32'b0;
    
endmodule

otherItype/tb/alu/dump.vcd
$version Generated by VerilatedVcd $end
$timescale 1ps $end
 $scope module $rootio $end
  $var wire 3 # alu_control [2:0] $end
  $var wire 32 $ src1 [31:0] $end
  $var wire 32 % src2 [31:0] $end
  $var wire 32 & alu_result [31:0] $end
  $var wire 1 ' zero $end
 $upscope $end
 $scope module alu $end
  $var wire 3 ( alu_control [2:0] $end
  $var wire 32 ) src1 [31:0] $end
  $var wire 32 * src2 [31:0] $end
  $var wire 32 + alu_result [31:0] $end
  $var wire 1 , zero $end
 $upscope $end
$enddefinitions $end


#0
b000 #
b00000000000000000000000000000000 $
b00000000000000000000000000000000 %
b00000000000000000000000000000000 &
1'
b000 (
b00000000000000000000000000000000 )
b00000000000000000000000000000000 *
b00000000000000000000000000000000 +
1,
#1000
b11101010111101001110101001101101 $
b11010111111111111110110000110100 %
b11000010111101001101011010100001 &
0'
b11101010111101001110101001101101 )
b11010111111111111110110000110100 *
b11000010111101001101011010100001 +
0,
#2000
b11001111110010011111100011100011 $
b10001010010001111001101010100011 %
b01011010000100011001001110000110 &
b11001111110010011111100011100011 )
b10001010010001111001101010100011 *
b01011010000100011001001110000110 +
#3000
b11011110010001010110010111011000 $
b00001101101101001011100000011010 %
b11101011111110100001110111110010 &
b11011110010001010110010111011000 )
b00001101101101001011100000011010 *
b11101011111110100001110111110010 +
#4000
b11011100101000111111101011111000 $
b00000100110000011001101110111111 %
b11100001011001011001011010110111 &
b11011100101000111111101011111000 )
b00000100110000011001101110111111 *
b11100001011001011001011010110111 +
#5000
b00110011000010000010011000111100 $
b10010100110010011010111110011000 %
b11000111110100011101010111010100 &
b00110011000010000010011000111100 )
b10010100110010011010111110011000 *
b11000111110100011101010111010100 +
#6000
b01110011000010000001010101010001 $
b10000110000111000100101000001000 %
b11111001001001000101111101011001 &
b01110011000010000001010101010001 )
b10000110000111000100101000001000 *
b11111001001001000101111101011001 +
#7000
b10011100011000110001001110000000 $
b11111011111000101001100011111011 %
b10011000010001011010110001111011 &
b10011100011000110001001110000000 )
b11111011111000101001100011111011 *
b10011000010001011010110001111011 +
#8000
b01100010111011010010011001001010 $
b11101001000111111100011001111000 %
b01001100000011001110110011000010 &
b01100010111011010010011001001010 )
b11101001000111111100011001111000 *
b01001100000011001110110011000010 +
#9000
b10001000001011001000011111010101 $
b11010111110010010001111000101000 %
b01011111111101011010010111111101 &
b10001000001011001000011111010101 )
b11010111110010010001111000101000 *
b01011111111101011010010111111101 +
#10000
b10001111010011101101100011100010 $
b11011110011100000100011001010100 %
b01101101101111110001111100110110 &
b10001111010011101101100011100010 )
b11011110011100000100011001010100 *
b01101101101111110001111100110110 +
#11000
b00010001001101101100001010000111 $
b00111111111010011001000001000011 %
b01010001001000000101001011001010 &
b00010001001101101100001010000111 )
b00111111111010011001000001000011 *
b01010001001000000101001011001010 +
#12000
b10101001100111010100010100111001 $
b11010001101001100000101111010100 %
b01111011010000110101000100001101 &
b10101001100111010100010100111001 )
b11010001101001100000101111010100 *
b01111011010000110101000100001101 +
#13000
b11011100110010110001000011011111 $
b00111101011110001101101011100111 %
b00011010010000111110101111000110 &
b11011100110010110001000011011111 )
b00111101011110001101101011100111 *
b00011010010000111110101111000110 +
#14000
b11011110000110001110110101000110 $
b11111011001100111110111010111100 %
b11011001010011001101110000000010 &
b11011110000110001110110101000110 )
b11111011001100111110111010111100 *
b11011001010011001101110000000010 +
#15000
b11111000000110001111000000011110 $
b11101101001000000111010100110101 %
b11100101001110010110010101010011 &
b11111000000110001111000000011110 )
b11101101001000000111010100110101 *
b11100101001110010110010101010011 +
#16000
b01101110111101001000111010100011 $
b00001100101100101110010011000110 %
b01111011101001110111001101101001 &
b01101110111101001000111010100011 )
b00001100101100101110010011000110 *
b01111011101001110111001101101001 +
#17000
b11100101110101001011001010011010 $
b00011111100111001001100010111010 %
b00000101011100010100101101010100 &
b11100101110101001011001010011010 )
b00011111100111001001100010111010 *
b00000101011100010100101101010100 +
#18000
b11100110110001010001110101011101 $
b11000011000111110001000011010110 %
b10101001111001000010111000110011 &
b11100110110001010001110101011101 )
b11000011000111110001000011010110 *
b10101001111001000010111000110011 +
#19000
b00000110010001001110000010010101 $
b11100101001011111000100110001010 %
b11101011011101000110101000011111 &
b00000110010001001110000010010101 )
b11100101001011111000100110001010 *
b11101011011101000110101000011111 +
#20000
b10000011000101011001101111100100 $
b01001010011000001011000000110000 %
b11001101011101100100110000010100 &
b10000011000101011001101111100100 )
b01001010011000001011000000110000 *
b11001101011101100100110000010100 +
#21000
b00101001111011101010011100010001 $
b00100110000110011111100110010011 %
b01010000000010001010000010100100 &
b00101001111011101010011100010001 )
b00100110000110011111100110010011 *
b01010000000010001010000010100100 +
#22000
b00000110010110111010010011101110 $
b10111101011111110001100000111001 %
b11000011110110101011110100100111 &
b00000110010110111010010011101110 )
b10111101011111110001100000111001 *
b11000011110110101011110100100111 +
#23000
b11000011101111100000011111110110 $
b01111101000001100110110000111011 %
b01000000110001000111010000110001 &
b11000011101111100000011111110110 )
b01111101000001100110110000111011 *
b01000000110001000111010000110001 +
#24000
b01111100111110000001100100000110 $
b01110011000001111001100110011000 %
b11101111111111111011001010011110 &
b01111100111110000001100100000110 )
b01110011000001111001100110011000 *
b11101111111111111011001010011110 +
#25000
b11011110000111001111010110110101 $
b10011101011101111000101010000001 %
b01111011100101001000000000110110 &
b11011110000111001111010110110101 )
b10011101011101111000101010000001 *
b01111011100101001000000000110110 +
#26000
b10110011110001010111101011000001 $
b10000110110000001001110000010010 %
b00111010100001100001011011010011 &
b10110011110001010111101011000001 )
b10000110110000001001110000010010 *
b00111010100001100001011011010011 +
#27000
b01011000111010110000101001100101 $
b00011011001100111010000001001110 %
b01110100000111101010101010110011 &
b01011000111010110000101001100101 )
b00011011001100111010000001001110 *
b01110100000111101010101010110011 +
#28000
b01000001011001010100011101111001 $
b01110011100001001011010111010111 %
b10110100111010011111110101010000 &
b01000001011001010100011101111001 )
b01110011100001001011010111010111 *
b10110100111010011111110101010000 +
#29000
b00001100100111110001011001000110 $
b10110011011011010100110110000000 %
b11000000000011000110001111000110 &
b00001100100111110001011001000110 )
b10110011011011010100110110000000 *
b11000000000011000110001111000110 +
#30000
b10000011011100011010000011100101 $
b10011011001100101111111111111100 %
b00011110101001001010000011100001 &
b10000011011100011010000011100101 )
b10011011001100101111111111111100 *
b00011110101001001010000011100001 +
#31000
b11101101110111100111010010001100 $
b11001110100000100011100111101111 %
b10111100011000001010111001111011 &
b11101101110111100111010010001100 )
b11001110100000100011100111101111 *
b10111100011000001010111001111011 +
#32000
b10100100101001001111111000111100 $
b10010000110011101101111001010011 %
b00110101011100111101110010001111 &
b10100100101001001111111000111100 )
b10010000110011101101111001010011 *
b00110101011100111101110010001111 +
#33000
b11101110001001101100011000011001 $
b00100011100111101101010001101010 %
b00010001110001011001101010000011 &
b11101110001001101100011000011001 )
b00100011100111101101010001101010 *
b00010001110001011001101010000011 +
#34000
b00011011100000001100001101101000 $
b11101101001010110011110011010010 %
b00001000101011000000000000111010 &
b00011011100000001100001101101000 )
b11101101001010110011110011010010 *
b00001000101011000000000000111010 +
#35000
b10001010110000101110100110011110 $
b11011100100001110000011001000110 %
b01100111010010011110111111100100 &
b10001010110000101110100110011110 )
b11011100100001110000011001000110 *
b01100111010010011110111111100100 +
#36000
b11011111011001000000100110001101 $
b00101101001001100000001110011001 %
b00001100100010100000110100100110 &
b11011111011001000000100110001101 )
b00101101001001100000001110011001 *
b00001100100010100000110100100110 +
#37000
b10111011100000100101000111111010 $
b11111100011110010110011011100111 %
b10110111111110111011100011100001 &
b10111011100000100101000111111010 )
b11111100011110010110011011100111 *
b10110111111110111011100011100001 +
#38000
b11010001110100010011000011101000 $
b01100010101000001101010101000110 %
b00110100011100100000011000101110 &
b11010001110100010011000011101000 )
b01100010101000001101010101000110 *
b00110100011100100000011000101110 +
#39000
b00100101111001001101010111110100 $
b11001010100011101100111011101111 %
b11110000011100111010010011100011 &
b00100101111001001101010111110100 )
b11001010100011101100111011101111 *
b11110000011100111010010011100011 +
#40000
b01001001111101101001100000101011 $
b01001000101000110101101110110001 %
b10010010100110011111001111011100 &
b01001001111101101001100000101011 )
b01001000101000110101101110110001 *
b10010010100110011111001111011100 +
#41000
b11011101110111110010111110011010 $
b01001101000000000010101111101110 %
b00101010110111110101101110001000 &
b11011101110111110010111110011010 )
b01001101000000000010101111101110 *
b00101010110111110101101110001000 +
#42000
b11111001100101110111000000000010 $
b10011111101011001000000100001111 %
b10011001010000111111000100010001 &
b11111001100101110111000000000010 )
b10011111101011001000000100001111 *
b10011001010000111111000100010001 +
#43000
b00010101111100010001101001000101 $
b11001000100101100010111001111110 %
b11011110100001110100100011000011 &
b00010101111100010001101001000101 )
b11001000100101100010111001111110 *
b11011110100001110100100011000011 +
#44000
b01000010001011101000100000001001 $
b10000111010101001000010000011101 %
b11001001100000110000110000100110 &
b01000010001011101000100000001001 )
b10000111010101001000010000011101 *
b11001001100000110000110000100110 +
#45000
b00011000001101011100010110010111 $
b10011100011111010001111010110001 %
b10110100101100101110010001001000 &
b00011000001101011100010110010111 )
b10011100011111010001111010110001 *
b10110100101100101110010001001000 +
#46000
b01011000110011001100000001001111 $
b11001011100001101001111001110000 %
b00100100010100110101111010111111 &
b01011000110011001100000001001111 )
b11001011100001101001111001110000 *
b00100100010100110101111010111111 +
#47000
b11101110011111111011010100010010 $
b01000100100100101110110101001100 %
b00110011000100101010001001011110 &
b11101110011111111011010100010010 )
b01000100100100101110110101001100 *
b00110011000100101010001001011110 +
#48000
b10110100011110110111110100000100 $
b10110110011010010100011100000111 %
b01101010111001001100010000001011 &
b10110100011110110111110100000100 )
b10110110011010010100011100000111 *
b01101010111001001100010000001011 +
#49000
b01000110011101101110000110100100 $
b01001000000011110101000110100010 %
b10001110100001100011001101000110 &
b01000110011101101110000110100100 )
b01001000000011110101000110100010 *
b10001110100001100011001101000110 +
#50000
b11100100000011100101001001001111 $
b01111110011010000001000000101010 %
b01100010011101100110001001111001 &
b11100100000011100101001001001111 )
b01111110011010000001000000101010 *
b01100010011101100110001001111001 +
#51000
b11000010010111010111100101111010 $
b11100001001000101000011100010011 %
b10100011100000000000000010001101 &
b11000010010111010111100101111010 )
b11100001001000101000011100010011 *
b10100011100000000000000010001101 +
#52000
b00000010111110100011001000110111 $
b01011010110111001011001000101110 %
b01011101110101101110010001100101 &
b00000010111110100011001000110111 )
b01011010110111001011001000101110 *
b01011101110101101110010001100101 +
#53000
b11000000111111100000101011010100 $
b00110111001011000000101000011101 %
b11111000001010100001010011110001 &
b11000000111111100000101011010100 )
b00110111001011000000101000011101 *
b11111000001010100001010011110001 +
#54000
b11100100101000100011010101100101 $
b11011100011010001011001111111011 %
b11000001000010101110100101100000 &
b11100100101000100011010101100101 )
b11011100011010001011001111111011 *
b11000001000010101110100101100000 +
#55000
b10010001010010110101110100000000 $
b00100011001001010001110100010011 %
b10110100011100000111101000010011 &
b10010001010010110101110100000000 )
b00100011001001010001110100010011 *
b10110100011100000111101000010011 +
#56000
b00110100011011110010011100100100 $
b10011001001001010111110110101111 %
b11001101100101001010010011010011 &
b00110100011011110010011100100100 )
b10011001001001010111110110101111 *
b11001101100101001010010011010011 +
#57000
b00100101010101100110011010110101 $
b00000000111010101111001110000111 %
b00100110010000010101101000111100 &
b00100101010101100110011010110101 )
b00000000111010101111001110000111 *
b00100110010000010101101000111100 +
#58000
b00110001111001010000011110111111 $
b00011011101010010000111111111100 %
b01001101100011100001011110111011 &
b00110001111001010000011110111111 )
b00011011101010010000111111111100 *
b01001101100011100001011110111011 +
#59000
b01000001011010110001100111011100 $
b11001000101010010001110100111010 %
b00001010000101000011011100010110 &
b01000001011010110001100111011100 )
b11001000101010010001110100111010 *
b00001010000101000011011100010110 +
#60000
b01111011000000101100010100001110 $
b10111010000111001111101111010100 %
b00110101000111111100000011100010 &
b01111011000000101100010100001110 )
b10111010000111001111101111010100 *
b00110101000111111100000011100010 +
#61000
b11101010110111100001110100010111 $
b01110101101100001110110111111011 %
b01100000100011110000101100010010 &
b11101010110111100001110100010111 )
b01110101101100001110110111111011 *
b01100000100011110000101100010010 +
#62000
b11010000011001101000001111000101 $
b01010100101010000000110000100110 %
b00100101000011101000111111101011 &
b11010000011001101000001111000101 )
b01010100101010000000110000100110 *
b00100101000011101000111111101011 +
#63000
b01100010010101101000111101101000 $
b10100100011100010000100110001110 %
b00000110110001111001100011110110 &
b01100010010101101000111101101000 )
b10100100011100010000100110001110 *
b00000110110001111001100011110110 +
#64000
b00100101000101100001101100011001 $
b00110001101100101100110011101001 %
b01010110110010001110100000000010 &
b00100101000101100001101100011001 )
b00110001101100101100110011101001 *
b01010110110010001110100000000010 +
#65000
b01000000010010010001010111000111 $
b10110010010101111101010010001000 %
b11110010101000001110101001001111 &
b01000000010010010001010111000111 )
b10110010010101111101010010001000 *
b11110010101000001110101001001111 +
#66000
b00011010001000011010111100001110 $
b10110101110111010111001101000011 %
b11001111111111110010001001010001 &
b00011010001000011010111100001110 )
b10110101110111010111001101000011 *
b11001111111111110010001001010001 +
#67000
b00110100000000000110010110010000 $
b00111101100101110000111000000100 %
b01110001100101110111001110010100 &
b00110100000000000110010110010000 )
b00111101100101110000111000000100 *
b01110001100101110111001110010100 +
#68000
b10001010100010010101011001110010 $
b00101010111101101110000011001101 %
b10110101100000000011011100111111 &
b10001010100010010101011001110010 )
b00101010111101101110000011001101 *
b10110101100000000011011100111111 +
#69000
b01010010001101111010101101011011 $
b10010101100100001001011110101111 %
b11100111110010000100001100001010 &
b01010010001101111010101101011011 )
b10010101100100001001011110101111 *
b11100111110010000100001100001010 +
#70000
b01011010010010010001111101110010 $
b11110101111000111001101101011011 %
b01010000001011001011101011001101 &
b01011010010010010001111101110010 )
b11110101111000111001101101011011 *
b01010000001011001011101011001101 +
#71000
b10001111011010010010100111000000 $
b00010011010001000100110011001000 %
b10100010101011010111011010001000 &
b10001111011010010010100111000000 )
b00010011010001000100110011001000 *
b10100010101011010111011010001000 +
#72000
b11110001101110111101100010111110 $
b10100001100111010011110010101101 %
b10010011010110010001010101101011 &
b11110001101110111101100010111110 )
b10100001100111010011110010101101 *
b10010011010110010001010101101011 +
#73000
b01110100010110010110100011101011 $
b00100111000100100001011010111111 %
b10011011011010110111111110101010 &
b01110100010110010110100011101011 )
b00100111000100100001011010111111 *
b10011011011010110111111110101010 +
#74000
b10011010100100111000010100111101 $
b00010011011001100110001100101111 %
b10101101111110011110100001101100 &
b10011010100100111000010100111101 )
b00010011011001100110001100101111 *
b10101101111110011110100001101100 +
#75000
b10101010011100011110110100000111 $
b11000000101000111011100010000111 %
b01101011000101011010010110001110 &
b10101010011100011110110100000111 )
b11000000101000111011100010000111 *
b01101011000101011010010110001110 +
#76000
b00000111000000000111101011001011 $
b00111100101101111110011011110000 %
b01000011101110000110000110111011 &
b00000111000000000111101011001011 )
b00111100101101111110011011110000 *
b01000011101110000110000110111011 +
#77000
b10001111100101101010111000110101 $
b10100100110111111010001011000110 %
b00110100011101100101000011111011 &
b10001111100101101010111000110101 )
b10100100110111111010001011000110 *
b00110100011101100101000011111011 +
#78000
b10010101010100010000111000100100 $
b11110111101010110001010100000100 %
b10001100111111000010001100101000 &
b10010101010100010000111000100100 )
b11110111101010110001010100000100 *
b10001100111111000010001100101000 +
#79000
b11111110110011011101110000101000 $
b11011110010110011100100010101010 %
b11011101001001111010010011010010 &
b11111110110011011101110000101000 )
b11011110010110011100100010101010 *
b11011101001001111010010011010010 +
#80000
b01110011001011110111110000101111 $
b00000010110001110110101100111100 %
b01110101111101101110011101101011 &
b01110011001011110111110000101111 )
b00000010110001110110101100111100 *
b01110101111101101110011101101011 +
#81000
b01101011100000010011101001111011 $
b00100000011010000101100110101000 %
b10001011111010011001010000100011 &
b01101011100000010011101001111011 )
b00100000011010000101100110101000 *
b10001011111010011001010000100011 +
#82000
b01101000110011101010011010000101 $
b11011110000110101101001011000010 %
b01000110111010010111100101000111 &
b01101000110011101010011010000101 )
b11011110000110101101001011000010 *
b01000110111010010111100101000111 +
#83000
b10011111100110100001011011000111 $
b00001001101110110010001011100101 %
b10101001010101010011100110101100 &
b10011111100110100001011011000111 )
b00001001101110110010001011100101 *
b10101001010101010011100110101100 +
#84000
b11100001100111000001010110000100 $
b11101001100010000110011100110010 %
b11001011001001000111110010110110 &
b11100001100111000001010110000100 )
b11101001100010000110011100110010 *
b11001011001001000111110010110110 +
#85000
b10100001001110111101101110001101 $
b11100110110100010010010100010011 %
b10001000000011010000000010100000 &
b10100001001110111101101110001101 )
b11100110110100010010010100010011 *
b10001000000011010000000010100000 +
#86000
b00111011111011111000101011110010 $
b10110100111100010110010100111000 %
b11110000111000001111000000101010 &
b00111011111011111000101011110010 )
b10110100111100010110010100111000 *
b11110000111000001111000000101010 +
#87000
b11110110100100010000010101100111 $
b01000011001101000001110101100101 %
b00111001110001010010001011001100 &
b11110110100100010000010101100111 )
b01000011001101000001110101100101 *
b00111001110001010010001011001100 +
#88000
b11110110100100111101001100001100 $
b00111111010010011111010101001001 %
b00110101110111011100100001010101 &
b11110110100100111101001100001100 )
b00111111010010011111010101001001 *
b00110101110111011100100001010101 +
#89000
b01101011011001101010100011110000 $
b10000111100010010100101010000001 %
b11110010111011111111001101110001 &
b01101011011001101010100011110000 )
b10000111100010010100101010000001 *
b11110010111011111111001101110001 +
#90000
b11110010101011010110100011111110 $
b11101010000110001011100010010101 %
b11011100110001100010000110010011 &
b11110010101011010110100011111110 )
b11101010000110001011100010010101 *
b11011100110001100010000110010011 +
#91000
b01111101010001000100010000110100 $
b01111010011111101010101010001110 %
b11110111110000101110111011000010 &
b01111101010001000100010000110100 )
b01111010011111101010101010001110 *
b11110111110000101110111011000010 +
#92000
b01000111010111111001101010001100 $
b00001111011111101100111010010110 %
b01010110110111100110100100100010 &
b01000111010111111001101010001100 )
b00001111011111101100111010010110 *
b01010110110111100110100100100010 +
#93000
b01101011000010010011101001000111 $
b11110010010111101111000011111101 %
b01011101011010000010101101000100 &
b01101011000010010011101001000111 )
b11110010010111101111000011111101 *
b01011101011010000010101101000100 +
#94000
b11110010000101010101110010001100 $
b10110000110010010101100100111001 %
b10100010110111101011010111000101 &
b11110010000101010101110010001100 )
b10110000110010010101100100111001 *
b10100010110111101011010111000101 +
#95000
b10011111111000100000000101011100 $
b01100000010100110001111101010011 %
b00000000001101010010000010101111 &
b10011111111000100000000101011100 )
b01100000010100110001111101010011 *
b00000000001101010010000010101111 +
#96000
b10111011100001010001111010111111 $
b10101001011010100110001000100101 %
b01100100111011111000000011100100 &
b10111011100001010001111010111111 )
b10101001011010100110001000100101 *
b01100100111011111000000011100100 +
#97000
b10100010110111010101000100110101 $
b10100001100111010111000101100001 %
b01000100011110101100001010010110 &
b10100010110111010101000100110101 )
b10100001100111010111000101100001 *
b01000100011110101100001010010110 +
#98000
b10101100001100011101101101110000 $
b01111100010101110000000011000110 %
b00101000100010001101110000110110 &
b10101100001100011101101101110000 )
b01111100010101110000000011000110 *
b00101000100010001101110000110110 +
#99000
b11110010111100100000111010100000 $
b11110101010011110100001000111001 %
b11101000010000010101000011011001 &
b11110010111100100000111010100000 )
b11110101010011110100001000111001 *
b11101000010000010101000011011001 +
#100000
b11010101001011101001110001101101 $
b00000100101110001001110011110010 %
b11011001111001110011100101011111 &
b11010101001011101001110001101101 )
b00000100101110001001110011110010 *
b11011001111001110011100101011111 +
#101000
b10010100011000011011101001111011 $
b00100011000000100011010000111011 %
b10110111011000111110111010110110 &
b10010100011000011011101001111011 )
b00100011000000100011010000111011 *
b10110111011000111110111010110110 +
#102000
b11111100100110010100111111011100 $
b00110000111111000100101110101001 %
b00101101100101011001101110000101 &
b11111100100110010100111111011100 )
b00110000111111000100101110101001 *
b00101101100101011001101110000101 +
#103000
b10011100111111000010010000110010 $
b01111001101010101100001111111101 %
b00010110101001101110100000101111 &
b10011100111111000010010000110010 )
b01111001101010101100001111111101 *
b00010110101001101110100000101111 +
#104000
b00010001101000111001010101111100 $
b10100110001011111111010101000111 %
b10110111110100111000101011000011 &
b00010001101000111001010101111100 )
b10100110001011111111010101000111 *
b10110111110100111000101011000011 +
#105000
b01011011100000010000001010101100 $
b11010111010010010111000110001001 %
b00110010110010100111010000110101 &
b01011011100000010000001010101100 )
b11010111010010010111000110001001 *
b00110010110010100111010000110101 +
#106000
b01001000101010110110001100111111 $
b11100111101000011110000100010010 %
b00110000010011010100010001010001 &
b01001000101010110110001100111111 )
b11100111101000011110000100010010 *
b00110000010011010100010001010001 +
#107000
b00011100010010100101101111001011 $
b01110111011000110010000001101001 %
b10010011101011010111110000110100 &
b00011100010010100101101111001011 )
b01110111011000110010000001101001 *
b10010011101011010111110000110100 +
#108000
b00011110100000110001111110111010 $
b11001010110001101110010011101110 %
b11101001010010100000010010101000 &
b00011110100000110001111110111010 )
b11001010110001101110010011101110 *
b11101001010010100000010010101000 +
#109000
b10101000001001000010000111010101 $
b11101100100101010100011000011110 %
b10010100101110010110011111110011 &
b10101000001001000010000111010101 )
b11101100100101010100011000011110 *
b10010100101110010110011111110011 +
#110000
b01010110001100010111100101001101 $
b10100110110110011001011010011011 %
b11111101000010110000111111101000 &
b01010110001100010111100101001101 )
b10100110110110011001011010011011 *
b11111101000010110000111111101000 +
#111000
b10110001101010001011001001001001 $
b00100010011011100011100100010110 %
b11010100000101101110101101011111 &
b10110001101010001011001001001001 )
b00100010011011100011100100010110 *
b11010100000101101110101101011111 +
#112000
b10110011111101110000111111110110 $
b10111001100010111000001111100111 %
b01101101100000101001001111011101 &
b10110011111101110000111111110110 )
b10111001100010111000001111100111 *
b01101101100000101001001111011101 +
#113000
b01101100001011100010101111011011 $
b10011111000011101011110111000000 %
b00001011001111001110100110011011 &
b01101100001011100010101111011011 )
b10011111000011101011110111000000 *
b00001011001111001110100110011011 +
#114000
b01111111111001101100101010011001 $
b01011001101100101011100011011010 %
b11011001100110011000001101110011 &
b01111111111001101100101010011001 )
b01011001101100101011100011011010 *
b11011001100110011000001101110011 +
#115000
b00000000010010110110000100101110 $
b00000111001010011110100110100011 %
b00000111011101010100101011010001 &
b00000000010010110110000100101110 )
b00000111001010011110100110100011 *
b00000111011101010100101011010001 +
#116000
b00000000100111011011100001001001 $
b10100010101101010000110100000101 %
b10100011010100101100010101001110 &
b00000000100111011011100001001001 )
b10100010101101010000110100000101 *
b10100011010100101100010101001110 +
#117000
b11100010100101111001111010000100 $
b01110111011010001110101111010110 %
b01011010000000001000101001011010 &
b11100010100101111001111010000100 )
b01110111011010001110101111010110 *
b01011010000000001000101001011010 +
#118000
b00001010000111111110000000001010 $
b10100001011100000101110011101101 %
b10101011100100000011110011110111 &
b00001010000111111110000000001010 )
b10100001011100000101110011101101 *
b10101011100100000011110011110111 +
#119000
b10000000110010100111100111111011 $
b11011001100011111011000110000110 %
b01011010010110100010101110000001 &
b10000000110010100111100111111011 )
b11011001100011111011000110000110 *
b01011010010110100010101110000001 +
#120000
b01000000101010000100110001001010 $
b00011111100111011001110100111111 %
b01100000010001011110100110001001 &
b01000000101010000100110001001010 )
b00011111100111011001110100111111 *
b01100000010001011110100110001001 +
#121000
b11100101010100100111000000111110 $
b01000010100011100111110001010110 %
b00100111111000001110110010010100 &
b11100101010100100111000000111110 )
b01000010100011100111110001010110 *
b00100111111000001110110010010100 +
#122000
b11111001010001111011110011000000 $
b00001000001101110111001000000001 %
b00000001011111110010111011000001 &
b11111001010001111011110011000000 )
b00001000001101110111001000000001 *
b00000001011111110010111011000001 +
#123000
b10010011101000101010100000111110 $
b11101101100010110110101100110011 %
b10000001001011100001001101110001 &
b10010011101000101010100000111110 )
b11101101100010110110101100110011 *
b10000001001011100001001101110001 +
#124000
b01010110011100110100100001100101 $
b10111110000011111011110111111010 %
b00010100100000110000011001011111 &
b01010110011100110100100001100101 )
b10111110000011111011110111111010 *
b00010100100000110000011001011111 +
#125000
b10001111111101011101001101010000 $
b00010111011101011110011111010110 %
b10100111011010111011101100100110 &
b10001111111101011101001101010000 )
b00010111011101011110011111010110 *
b10100111011010111011101100100110 +
#126000
b11111010110100001011000000111011 $
b01010001011000100100000101000010 %
b01001100001100101111000101111101 &
b11111010110100001011000000111011 )
b01010001011000100100000101000010 *
b01001100001100101111000101111101 +
#127000
b00110100011101111110110110001101 $
b01110101101101010111101011110010 %
b10101010001011010110100001111111 &
b00110100011101111110110110001101 )
b01110101101101010111101011110010 *
b10101010001011010110100001111111 +
#128000
b11011101101111011011110111001011 $
b11100001001111101001000011010110 %
b10111110111111000100111010100001 &
b11011101101111011011110111001011 )
b11100001001111101001000011010110 *
b10111110111111000100111010100001 +
#129000
b10110000001001001101110011111101 $
b11010111011010001100011100001010 %
b10000111100011011010010000000111 &
b10110000001001001101110011111101 )
b11010111011010001100011100001010 *
b10000111100011011010010000000111 +
#130000
b10101100111111010101010011000110 $
b11010100100111110011001010001010 %
b10000001100111001000011101010000 &
b10101100111111010101010011000110 )
b11010100100111110011001010001010 *
b10000001100111001000011101010000 +
#131000
b01111001000011001101011011000011 $
b00111100101101010101110010001110 %
b10110101110000100011001101010001 &
b01111001000011001101011011000011 )
b00111100101101010101110010001110 *
b10110101110000100011001101010001 +
#132000
b11110110100110000000011001110000 $
b01001100100100001000101010010100 %
b01000011001010001001000100000100 &
b11110110100110000000011001110000 )
b01001100100100001000101010010100 *
b01000011001010001001000100000100 +
#133000
b00010011101001100110111101000110 $
b11000110010101100111111101101011 %
b11011001111111001110111010110001 &
b00010011101001100110111101000110 )
b11000110010101100111111101101011 *
b11011001111111001110111010110001 +
#134000
b00001001000101000110001011110001 $
b01101001000111111001000111000100 %
b01110010001100111111010010110101 &
b00001001000101000110001011110001 )
b01101001000111111001000111000100 *
b01110010001100111111010010110101 +
#135000
b10000100001011101011101001110000 $
b10101110000000101000110011100011 %
b00110010001100010100011101010011 &
b10000100001011101011101001110000 )
b10101110000000101000110011100011 *
b00110010001100010100011101010011 +
#136000
b11000000001111011011010001001101 $
b00100111110001010011110101101101 %
b11101000000000101111000110111010 &
b11000000001111011011010001001101 )
b00100111110001010011110101101101 *
b11101000000000101111000110111010 +
#137000
b00000000010100010101011101001000 $
b11111010000001001011110000101011 %
b11111010010101100001001101110011 &
b00000000010100010101011101001000 )
b11111010000001001011110000101011 *
b11111010010101100001001101110011 +
#138000
b00001100111010110110111000110001 $
b01010000011100100100010010111110 %
b01011101010111011011001011101111 &
b00001100111010110110111000110001 )
b01010000011100100100010010111110 *
b01011101010111011011001011101111 +
#139000
b00010100001110000010110001011110 $
b00100101101010000010001110111110 %
b00111001111000000101000000011100 &
b00010100001110000010110001011110 )
b00100101101010000010001110111110 *
b00111001111000000101000000011100 +
#140000
b00100110011101010110100000110010 $
b10101111110010111001011111111100 %
b11010110010000010000000000101110 &
b00100110011101010110100000110010 )
b10101111110010111001011111111100 *
b11010110010000010000000000101110 +
#141000
b01101001010100000010001011101110 $
b10101001110001110101111111010000 %
b00010011000101111000001010111110 &
b01101001010100000010001011101110 )
b10101001110001110101111111010000 *
b00010011000101111000001010111110 +
#142000
b00100010111000101001001110011110 $
b11100110000010010110001001110100 %
b00001000111010111111011000010010 &
b00100010111000101001001110011110 )
b11100110000010010110001001110100 *
b00001000111010111111011000010010 +
#143000
b11110000001000000001100000011100 $
b01000000111000100010110110001010 %
b00110001000000100100010110100110 &
b11110000001000000001100000011100 )
b01000000111000100010110110001010 *
b00110001000000100100010110100110 +
#144000
b01010001011101000011000011110001 $
b00111111010000000000011101000101 %
b10010000101101000011100000110110 &
b01010001011101000011000011110001 )
b00111111010000000000011101000101 *
b10010000101101000011100000110110 +
#145000
b10110111001101011111000101001001 $
b00101010000010100001101111011111 %
b11100001010000000000110100101000 &
b10110111001101011111000101001001 )
b00101010000010100001101111011111 *
b11100001010000000000110100101000 +
#146000
b11110011101101111101100000001001 $
b01001100110011101110111000101011 %
b01000000100001101100011000110100 &
b11110011101101111101100000001001 )
b01001100110011101110111000101011 *
b01000000100001101100011000110100 +
#147000
b00010000001111100010110111000101 $
b10001010000010011101110100111010 %
b10011010010010000000101011111111 &
b00010000001111100010110111000101 )
b10001010000010011101110100111010 *
b10011010010010000000101011111111 +
#148000
b01110010010111010101110000101011 $
b10010010111011101011010111000110 %
b00000101010011000001000111110001 &
b01110010010111010101110000101011 )
b10010010111011101011010111000110 *
b00000101010011000001000111110001 +
#149000
b01111001000011011011110000111111 $
b01000010000001011100001010100101 %
b10111011000100110111111011100100 &
b01111001000011011011110000111111 )
b01000010000001011100001010100101 *
b10111011000100110111111011100100 +
#150000
b11110101100100101101101001110101 $
b11101101110011111111011110101101 %
b11100011011000101101001000100010 &
b11110101100100101101101001110101 )
b11101101110011111111011110101101 *
b11100011011000101101001000100010 +
#151000
b01100110101111011110101111100100 $
b11000000111011110100100011111100 %
b00100111101011010011010011100000 &
b01100110101111011110101111100100 )
b11000000111011110100100011111100 *
b00100111101011010011010011100000 +
#152000
b11000001010101111010001001100111 $
b10010111111110010111110100110110 %
b01011001010100010001111110011101 &
b11000001010101111010001001100111 )
b10010111111110010111110100110110 *
b01011001010100010001111110011101 +
